Workbook

Sheet PANDUAN
A1: R | P | K PANDUAN SISTEM KEUANGAN | B1: R | P | K PANDUAN SISTEM KEUANGAN | C1: R | P | K PANDUAN SISTEM KEUANGAN | D1: R | P | K PANDUAN SISTEM KEUANGAN | E1: R | P | K PANDUAN SISTEM KEUANGAN | F1: R | P | K PANDUAN SISTEM KEUANGAN | G1: R | P | K PANDUAN SISTEM KEUANGAN | H1: R | P | K PANDUAN SISTEM KEUANGAN | I1: R | P | K PANDUAN SISTEM KEUANGAN
A2: R | P | K PANDUAN SISTEM KEUANGAN | B2: R | P | K PANDUAN SISTEM KEUANGAN | C2: R | P | K PANDUAN SISTEM KEUANGAN | D2: R | P | K PANDUAN SISTEM KEUANGAN | E2: R | P | K PANDUAN SISTEM KEUANGAN | F2: R | P | K PANDUAN SISTEM KEUANGAN | G2: R | P | K PANDUAN SISTEM KEUANGAN | H2: R | P | K PANDUAN SISTEM KEUANGAN | I2: R | P | K PANDUAN SISTEM KEUANGAN
A3: Panduan operasional untuk pemasukan, pengeluaran, penggajian, reimburse, piutang, kas/bank, dana klien, partner, ekuitas dan laporan manajemen. | B3: Panduan operasional untuk pemasukan, pengeluaran, penggajian, reimburse, piutang, kas/bank, dana klien, partner, ekuitas dan laporan manajemen. | C3: Panduan operasional untuk pemasukan, pengeluaran, penggajian, reimburse, piutang, kas/bank, dana klien, partner, ekuitas dan laporan manajemen. | D3: Panduan operasional untuk pemasukan, pengeluaran, penggajian, reimburse, piutang, kas/bank, dana klien, partner, ekuitas dan laporan manajemen. | E3: Panduan operasional untuk pemasukan, pengeluaran, penggajian, reimburse, piutang, kas/bank, dana klien, partner, ekuitas dan laporan manajemen. | F3: Panduan operasional untuk pemasukan, pengeluaran, penggajian, reimburse, piutang, kas/bank, dana klien, partner, ekuitas dan laporan manajemen. | G3: Panduan operasional untuk pemasukan, pengeluaran, penggajian, reimburse, piutang, kas/bank, dana klien, partner, ekuitas dan laporan manajemen. | H3: Panduan operasional untuk pemasukan, pengeluaran, penggajian, reimburse, piutang, kas/bank, dana klien, partner, ekuitas dan laporan manajemen. | I3: Panduan operasional untuk pemasukan, pengeluaran, penggajian, reimburse, piutang, kas/bank, dana klien, partner, ekuitas dan laporan manajemen.
A5: URUTAN PENCATATAN YANG DISARANKAN | B5: URUTAN PENCATATAN YANG DISARANKAN | C5: URUTAN PENCATATAN YANG DISARANKAN | D5: URUTAN PENCATATAN YANG DISARANKAN | E5: URUTAN PENCATATAN YANG DISARANKAN | F5: URUTAN PENCATATAN YANG DISARANKAN | G5: URUTAN PENCATATAN YANG DISARANKAN | H5: URUTAN PENCATATAN YANG DISARANKAN | I5: URUTAN PENCATATAN YANG DISARANKAN
A6: No. | B6: Aktivitas | C6: Cara Mencatat
A7: 01 | B7: Tetapkan master data | C7: Periksa partner, rekening, kategori biaya, periode laporan, dan parameter di MASTER.
A8: 02 | B8: Daftarkan perkara dan kontrak | C8: Isi ID perkara dan nama klien satu kali di PERKARA. Pilih ID pada sheet transaksi; nama klien terisi otomatis dan ikut berubah jika master diperbarui.
A9: 03 | B9: Terbitkan invoice | C9: Catat tagihan dan jatuh tempo pada INVOICE_PIUTANG agar piutang dapat dipantau.
A10: 04 | B10: Catat penerimaan uang | C10: Isi PEMASUKAN. Pilih jenis yang tepat: jasa hukum, reimburse, dana klien, modal, atau pinjaman.
A11: 05 | B11: Catat biaya dasar | C11: Isi PENGELUARAN satu kali dan bedakan beban Kantor, Klien, atau Partner.
A12: 06 | B12: Ajukan reimbursement | C12: Buat ID di REIMBURSE, lalu masukkan ID yang sama pada PENGELUARAN terkait.
A13: 07 | B13: Proses gaji tenaga kerja | C13: Isi GAJI untuk pegawai dan tenaga lepas; pembagian laba partner dicatat di PARTNER.
A14: 08 | B14: Pisahkan dana milik klien | C14: Setiap titipan dicatat di PEMASUKAN dan DANA_KLIEN; pembayaran klien dicatat hanya di DANA_KLIEN.
A15: 09 | B15: Catat pajak dan utang | C15: Isi KEWAJIBAN sesuai nilai nyata dan tanggal jatuh tempo; hindari menebak tarif pajak.
A16: 10 | B16: Rekonsiliasi kas dan bank | C16: Isi saldo awal serta saldo fisik/rekening di KAS_BANK; telusuri seluruh selisih.
A17: 11 | B17: Pantau anggaran dan laporan | C17: Tinjau DASHBOARD, ANGGARAN, LABA_RUGI, ARUS_KAS, dan profitabilitas per PERKARA.
A18: 12 | B18: Tutup periode dengan kontrol | C18: Buka KONTROL dan tindak lanjuti invoice jatuh tempo, bukti kurang, selisih kas, atau dana klien negatif.
A21: EMPAT PEMISAHAN YANG WAJIB DIJAGA | B21: EMPAT PEMISAHAN YANG WAJIB DIJAGA | C21: EMPAT PEMISAHAN YANG WAJIB DIJAGA | D21: EMPAT PEMISAHAN YANG WAJIB DIJAGA | E21: EMPAT PEMISAHAN YANG WAJIB DIJAGA | F21: EMPAT PEMISAHAN YANG WAJIB DIJAGA | G21: EMPAT PEMISAHAN YANG WAJIB DIJAGA | H21: EMPAT PEMISAHAN YANG WAJIB DIJAGA | I21: EMPAT PEMISAHAN YANG WAJIB DIJAGA
A22: Pendapatan jasa hukum | B22: Honorarium, retainer, success fee dan konsultasi merupakan pendapatan operasional kantor.
A23: Reimburse biaya | B23: Penggantian biaya bukan honorarium baru; pembayaran reimburse partner juga bukan biaya kedua.
A24: Dana titipan klien | B24: Dana klien merupakan kewajiban/dana terbatas, tidak boleh digunakan sebagai kas bebas kantor.
A25: Partner dan pegawai | B25: Gaji pegawai adalah beban; setoran modal, prive dan pembagian laba partner adalah transaksi ekuitas.
A28: KETERANGAN WARNA & BATASAN | B28: KETERANGAN WARNA & BATASAN | C28: KETERANGAN WARNA & BATASAN | D28: KETERANGAN WARNA & BATASAN | E28: KETERANGAN WARNA & BATASAN | F28: KETERANGAN WARNA & BATASAN | G28: KETERANGAN WARNA & BATASAN | H28: KETERANGAN WARNA & BATASAN | I28: KETERANGAN WARNA & BATASAN
A29: Krem / teks biru | B29: Sel input yang diisi atau diperbarui pengguna.
A30: Abu-abu | B30: Rumus otomatis; jangan dihapus atau ditimpa.
A31: Merah | B31: Pengecualian atau hal yang perlu ditindaklanjuti.
A32: Catatan pajak | B32: PPh, PPN dan BPJS diisi sesuai data aktual; workbook ini bukan penetapan tarif atau opini pajak.
A34: ALUR DATA YANG SALING TERHUBUNG
A35: 01 | B35: PERKARA | C35: Daftarkan ID perkara, nama klien, kontak, email, dan alamat penagihan satu kali.
A36: 02 | B36: INVOICE_PIUTANG | C36: Isi tanggal, pilih ID perkara, jenis tagihan, dan nilai. Nomor invoice, klien, jatuh tempo, piutang, dan umur tagihan terisi otomatis.
A37: 03 | B37: PEMASUKAN | C37: Pilih nomor invoice; ID perkara dan nama klien mengikuti register invoice. Masukkan tanggal, jenis penerimaan, nominal, dan akun.
A38: 04 | B38: REIMBURSE / PENGELUARAN | C38: Buat klaim dengan tanggal pengajuan; pilih ID klaim yang sama pada setiap pengeluaran terkait.
A39: 05 | B39: TRANSFER_KAS | C39: Catat perpindahan uang antar rekening di satu tempat agar tidak membuat kas/bank tidak seimbang.
A40: 06 | B40: NERACA / KONTROL | C40: Periksa saldo neraca, talangan partner, umur piutang, bukti transaksi, dan rekonsiliasi sebelum menutup bulan.
A42: PERSETUJUAN MANUAL & MEMBACA RUGI BULANAN
A43: 07 | B43: OTORISASI | C43: Periksa status, nama partner penyetuju, dan transaksi yang sudah berjalan tetapi belum mempunyai otorisasi lengkap.
A44: 08 | B44: PENGELUARAN | C44: Kolom Status Persetujuan, Nilai Disetujui, Disetujui Oleh, dan Tanggal Persetujuan diisi manual; jangan mengarang data lama.
A45: 09 | B45: REIMBURSE | C45: Setujui klaim dan setiap rincian pengeluaran secara manual; nilai disetujui baru dihitung setelah keduanya lengkap.
A46: 10 | B46: INVOICE / GAJI | C46: Nama penandatangan invoice dan slip gaji mengikuti penyetuju manual pada register sumber.
A47: 11 | B47: LABA_RUGI | C47: Bedakan rugi bulan berjalan dari laba kumulatif dan saldo kas. Dana bulan lalu bukan pemasukan bulan ini.
A48: 12 | B48: MASTER | C48: Ubah Bulan analisis laporan (1–12) untuk mengganti kartu interpretasi otomatis di LABA_RUGI dan DASHBOARD.
A49: 13 | B49: PERALATAN KANTOR | C49: Pembelian printer/peralatan saat ini dibebankan langsung; telaah kapitalisasi hanya setelah kebijakan, nilai residu, dan umur manfaat ditetapkan.
A51: MEMBUKA TAHUN 2027 TANPA MENGHAPUS ARSIP 2026
A52: 14 | B52: SALDO_AWAL_2027 | C52: Sesuaikan saldo kas, bank, talangan, modal, laba ditahan, dan riwayat perkara setelah tutup buku 31 Desember 2026.
A53: 15 | B53: MASTER | C53: Tahun laporan sudah 2027; Bulan analisis harus berupa angka 1–12, bukan format tanggal.
A54: 16 | B54: TRANSAKSI 2027 | C54: Register pemasukan, pengeluaran, payroll, reimburse, partner, transfer, dan invoice lunas dimulai kosong.
A55: 17 | B55: PERKARA | C55: ID dan nama klien tetap dipakai; invoice/pembayaran/biaya sebelum 2027 tersimpan di SALDO_AWAL_2027 bagian C.
A56: 18 | B56: KAS_BANK / EKUITAS | C56: Saldo awal otomatis mengambil angka sheet SALDO_AWAL_2027. Perubahan saldo pembukaan dilakukan pada sel krem.
A57: 19 | B57: ARSIP & TAHUN BARU | C57: Simpan workbook 2026 sebagai arsip. Workbook 2027 dipakai penuh Januari–Desember tanpa membuat file baru setiap bulan.

Sheet DASHBOARD
A1: R | P | K DASHBOARD KEUANGAN & ARUS KAS PARTNER | B1: R | P | K DASHBOARD KEUANGAN & ARUS KAS PARTNER | C1: R | P | K DASHBOARD KEUANGAN & ARUS KAS PARTNER | D1: R | P | K DASHBOARD KEUANGAN & ARUS KAS PARTNER | E1: R | P | K DASHBOARD KEUANGAN & ARUS KAS PARTNER | F1: R | P | K DASHBOARD KEUANGAN & ARUS KAS PARTNER | G1: R | P | K DASHBOARD KEUANGAN & ARUS KAS PARTNER | H1: R | P | K DASHBOARD KEUANGAN & ARUS KAS PARTNER | I1: R | P | K DASHBOARD KEUANGAN & ARUS KAS PARTNER | J1: R | P | K DASHBOARD KEUANGAN & ARUS KAS PARTNER | K1: R | P | K DASHBOARD KEUANGAN & ARUS KAS PARTNER | L1: R | P | K DASHBOARD KEUANGAN & ARUS KAS PARTNER | M1: R | P | K DASHBOARD KEUANGAN & ARUS KAS PARTNER | N1: R | P | K DASHBOARD KEUANGAN & ARUS KAS PARTNER
A2: R | P | K DASHBOARD KEUANGAN & ARUS KAS PARTNER | B2: R | P | K DASHBOARD KEUANGAN & ARUS KAS PARTNER | C2: R | P | K DASHBOARD KEUANGAN & ARUS KAS PARTNER | D2: R | P | K DASHBOARD KEUANGAN & ARUS KAS PARTNER | E2: R | P | K DASHBOARD KEUANGAN & ARUS KAS PARTNER | F2: R | P | K DASHBOARD KEUANGAN & ARUS KAS PARTNER | G2: R | P | K DASHBOARD KEUANGAN & ARUS KAS PARTNER | H2: R | P | K DASHBOARD KEUANGAN & ARUS KAS PARTNER | I2: R | P | K DASHBOARD KEUANGAN & ARUS KAS PARTNER | J2: R | P | K DASHBOARD KEUANGAN & ARUS KAS PARTNER | K2: R | P | K DASHBOARD KEUANGAN & ARUS KAS PARTNER | L2: R | P | K DASHBOARD KEUANGAN & ARUS KAS PARTNER | M2: R | P | K DASHBOARD KEUANGAN & ARUS KAS PARTNER | N2: R | P | K DASHBOARD KEUANGAN & ARUS KAS PARTNER
A3: Laba usaha, saldo awal, pembayaran partner, reimburse, talangan, kas akhir, dan kontrol akuntansi ditampilkan terpisah serta saling terhubung. | B3: Laba usaha, saldo awal, pembayaran partner, reimburse, talangan, kas akhir, dan kontrol akuntansi ditampilkan terpisah serta saling terhubung. | C3: Laba usaha, saldo awal, pembayaran partner, reimburse, talangan, kas akhir, dan kontrol akuntansi ditampilkan terpisah serta saling terhubung. | D3: Laba usaha, saldo awal, pembayaran partner, reimburse, talangan, kas akhir, dan kontrol akuntansi ditampilkan terpisah serta saling terhubung. | E3: Laba usaha, saldo awal, pembayaran partner, reimburse, talangan, kas akhir, dan kontrol akuntansi ditampilkan terpisah serta saling terhubung. | F3: Laba usaha, saldo awal, pembayaran partner, reimburse, talangan, kas akhir, dan kontrol akuntansi ditampilkan terpisah serta saling terhubung. | G3: Laba usaha, saldo awal, pembayaran partner, reimburse, talangan, kas akhir, dan kontrol akuntansi ditampilkan terpisah serta saling terhubung. | H3: Laba usaha, saldo awal, pembayaran partner, reimburse, talangan, kas akhir, dan kontrol akuntansi ditampilkan terpisah serta saling terhubung. | I3: Laba usaha, saldo awal, pembayaran partner, reimburse, talangan, kas akhir, dan kontrol akuntansi ditampilkan terpisah serta saling terhubung. | J3: Laba usaha, saldo awal, pembayaran partner, reimburse, talangan, kas akhir, dan kontrol akuntansi ditampilkan terpisah serta saling terhubung. | K3: Laba usaha, saldo awal, pembayaran partner, reimburse, talangan, kas akhir, dan kontrol akuntansi ditampilkan terpisah serta saling terhubung. | L3: Laba usaha, saldo awal, pembayaran partner, reimburse, talangan, kas akhir, dan kontrol akuntansi ditampilkan terpisah serta saling terhubung. | M3: Laba usaha, saldo awal, pembayaran partner, reimburse, talangan, kas akhir, dan kontrol akuntansi ditampilkan terpisah serta saling terhubung. | N3: Laba usaha, saldo awal, pembayaran partner, reimburse, talangan, kas akhir, dan kontrol akuntansi ditampilkan terpisah serta saling terhubung.
A4: Tahun Laporan | B4: =MASTER!$AF$7 -> 2026 | D4: Bulan Analisis | E4: =CHOOSE(MASTER!$AF$15,"Januari","Februari","Maret","April","Mei","Juni","Juli","Agustus","September","Oktober","November","Desember") -> Agustus | H4: =KONTROL!A68 -> PERIKSA — ADA TEMUAN KRITIS / TINGGI
A6: PENDAPATAN JASA HUKUM | B6: PENDAPATAN JASA HUKUM | C6: PENDAPATAN JASA HUKUM | D6: BEBAN OPERASIONAL | E6: BEBAN OPERASIONAL | F6: BEBAN OPERASIONAL | G6: LABA / (RUGI) OPERASIONAL | H6: LABA / (RUGI) OPERASIONAL | I6: LABA / (RUGI) OPERASIONAL | J6: LABA / (RUGI) OPERASIONAL | K6: PIUTANG KLIEN | L6: PIUTANG KLIEN | M6: PIUTANG KLIEN | N6: PIUTANG KLIEN
A7: =LABA_RUGI!N7 -> 0 | D7: =LABA_RUGI!N14 -> 0 | G7: =LABA_RUGI!N26 -> 0 | K7: =SUM(INVOICE_PIUTANG!$L$5:$L$151) -> 33500000
A10: KAS & BANK OPERASIONAL | B10: KAS & BANK OPERASIONAL | C10: KAS & BANK OPERASIONAL | D10: DANA TITIPAN KLIEN | E10: DANA TITIPAN KLIEN | F10: DANA TITIPAN KLIEN | G10: TALANGAN / UTANG PARTNER | H10: TALANGAN / UTANG PARTNER | I10: TALANGAN / UTANG PARTNER | J10: TALANGAN / UTANG PARTNER | K10: PAJAK / KEWAJIBAN TERUTANG | L10: PAJAK / KEWAJIBAN TERUTANG | M10: PAJAK / KEWAJIBAN TERUTANG | N10: PAJAK / KEWAJIBAN TERUTANG
A11: =NERACA!E6 -> 2904092 | D11: =SUM(DANA_KLIEN!$G$5:$G$154)-SUM(DANA_KLIEN!$H$5:$H$154) -> 0 | G11: =TALANGAN_PARTNER!I9 -> 1000000 | K11: =SUM(KEWAJIBAN!$G$5:$G$124) -> 3000000
A15: KINERJA BULANAN — LABA USAHA, PEMBAGIAN PARTNER, DAN PERGERAKAN KAS | B15: KINERJA BULANAN — LABA USAHA, PEMBAGIAN PARTNER, DAN PERGERAKAN KAS | C15: KINERJA BULANAN — LABA USAHA, PEMBAGIAN PARTNER, DAN PERGERAKAN KAS | D15: KINERJA BULANAN — LABA USAHA, PEMBAGIAN PARTNER, DAN PERGERAKAN KAS | E15: KINERJA BULANAN — LABA USAHA, PEMBAGIAN PARTNER, DAN PERGERAKAN KAS | F15: KINERJA BULANAN — LABA USAHA, PEMBAGIAN PARTNER, DAN PERGERAKAN KAS | G15: KINERJA BULANAN — LABA USAHA, PEMBAGIAN PARTNER, DAN PERGERAKAN KAS | H15: KINERJA BULANAN — LABA USAHA, PEMBAGIAN PARTNER, DAN PERGERAKAN KAS | I15: KINERJA BULANAN — LABA USAHA, PEMBAGIAN PARTNER, DAN PERGERAKAN KAS | J15: KINERJA BULANAN — LABA USAHA, PEMBAGIAN PARTNER, DAN PERGERAKAN KAS | K15: KINERJA BULANAN — LABA USAHA, PEMBAGIAN PARTNER, DAN PERGERAKAN KAS | L15: KINERJA BULANAN — LABA USAHA, PEMBAGIAN PARTNER, DAN PERGERAKAN KAS | M15: KINERJA BULANAN — LABA USAHA, PEMBAGIAN PARTNER, DAN PERGERAKAN KAS | N15: KINERJA BULANAN — LABA USAHA, PEMBAGIAN PARTNER, DAN PERGERAKAN KAS
A16: Bulan | B16: Pendapatan Jasa | C16: Beban Operasional | D16: Laba / (Rugi) Bulan | E16: Laba Usaha Kumulatif | F16: Kas Awal Bulan | G16: Kas Masuk Operasional | H16: Biaya + Gaji + Kewajiban | I16: Reimburse Dibayar | J16: Pembagian Partner / Prive | K16: Pengembalian Talangan | L16: Pendanaan / Mutasi Lain | M16: Kas Akhir Bulan | N16: Selisih Kontrol
A17: Jan | B17: =IF(ROW()-16>MASTER!$AF$15,"",SUMIFS(PEMASUKAN!$H$5:$H$204,PEMASUKAN!$C$5:$C$204,TEXT(DATE($B$4,ROW()-16,1),"yyyy-mm"),PEMASUKAN!$M$5:$M$204,"Pendapatan Operasional")) -> 0 | C17: =IF(ROW()-16>MASTER!$AF$15,"",SUMIFS(PENGELUARAN!$K$5:$K$204,PENGELUARAN!$C$5:$C$204,TEXT(DATE($B$4,ROW()-16,1),"yyyy-mm"),PENGELUARAN!$L$5:$L$204,"Kantor")+SUMIFS(GAJI!$Q$5:$Q$124,GAJI!$B$5:$B$124,">="&DATE($B$4,ROW()-16,1),GAJI!$B$5:$B$124,"<"&DATE($B$4,ROW()-15,1))) -> 0 | D17: =IF(ROW()-16>MASTER!$AF$15,"",B17-C17) -> 0 | E17: =IF(ROW()-16>MASTER!$AF$15,"",SUM($D$17:D17)) -> 0 | F17: =IF(ROW()-16>MASTER!$AF$15,"",IF(ROW()=17,SUMIFS(KAS_BANK!$B$5:$B$10,KAS_BANK!$A$5:$A$10,"<>Bank Dana Klien")+MAX(-KAS_BANK!$B$7,0)+MAX(-KAS_BANK!$B$8,0)+MAX(-KAS_BANK!$B$9,0),M16)) -> 0 | G17: =IF(ROW()-16>MASTER!$AF$15,"",SUMIFS(PEMASUKAN!$J$5:$J$204,PEMASUKAN!$C$5:$C$204,TEXT(DATE($B$4,ROW()-16,1),"yyyy-mm"),PEMASUKAN!$M$5:$M$204,"Pendapatan Operasional")+SUMIFS(PEMASUKAN!$J$5:$J$204,PEMASUKAN!$C$5:$C$204,TEXT(DATE($B$4,ROW()-16,1),"yyyy-mm"),PEMASUKAN!$M$5:$M$204,"Penggantian Biaya")) -> 0 | H17: =IF(ROW()-16>MASTER!$AF$15,"",SUMIFS(PENGELUARAN!$K$5:$K$204,PENGELUARAN!$C$5:$C$204,TEXT(DATE($B$4,ROW()-16,1),"yyyy-mm"),PENGELUARAN!$I$5:$I$204,"<>",PENGELUARAN!$I$5:$I$204,"<>Bank Dana Klien")+SUMIFS(GAJI!$P$5:$P$124,GAJI!$S$5:$S$124,">="&DATE($B$4,ROW()-16,1),GAJI!$S$5:$S$124,"<"&DATE($B$4,ROW()-15,1),GAJI!$R$5:$R$124,"Dibayar")+SUMIFS(KEWAJIBAN!$F$5:$F$124,KEWAJIBAN!$I$5:$I$124,">="&DATE($B$4,ROW()-16,1),KEWAJIBAN!$I$5:$I$124,"<"&DATE($B$4,ROW()-15,1))) -> 0 | I17: =IF(ROW()-16>MASTER!$AF$15,"",SUMIFS(REIMBURSE!$J$5:$J$124,REIMBURSE!$N$5:$N$124,">="&DATE($B$4,ROW()-16,1),REIMBURSE!$N$5:$N$124,"<"&DATE($B$4,ROW()-15,1))) -> 0 | J17: =IF(ROW()-16>MASTER!$AF$15,"",SUMIFS(PARTNER!$I$5:$I$124,PARTNER!$E$5:$E$124,MASTER!$Y$7,PARTNER!$V$5:$V$124,">="&DATE($B$4,ROW()-16,1),PARTNER!$V$5:$V$124,"<"&DATE($B$4,ROW()-15,1))+SUMIFS(PARTNER!$I$5:$I$124,PARTNER!$E$5:$E$124,MASTER!$Y$8,PARTNER!$V$5:$V$124,">="&DATE($B$4,ROW()-16,1),PARTNER!$V$5:$V$124,"<"&DATE($B$4,ROW()-15,1))) -> 0 | K17: =IF(ROW()-16>MASTER!$AF$15,"",SUMIFS(PARTNER!$I$5:$I$124,PARTNER!$E$5:$E$124,MASTER!$Y$9,PARTNER!$V$5:$V$124,">="&DATE($B$4,ROW()-16,1),PARTNER!$V$5:$V$124,"<"&DATE($B$4,ROW()-15,1))) -> 0 | L17: {=IF(ROW()-16>MASTER!$AF$15,"",INDEX(ARUS_KAS!$B$24:$M$24,1,ROW()-16)+INDEX(ARUS_KAS!$B$26:$M$26,1,ROW()-16)+INDEX(ARUS_KAS!$B$28:$M$28,1,ROW()-16))} -> 0 | M17: {=IF(ROW()-16>MASTER!$AF$15,"",F17+INDEX(ARUS_KAS!$B$8:$M$8,1,ROW()-16)+INDEX(ARUS_KAS!$B$9:$M$9,1,ROW()-16)-INDEX(ARUS_KAS!$B$12:$M$12,1,ROW()-16)-INDEX(ARUS_KAS!$B$13:$M$13,1,ROW()-16)-INDEX(ARUS_KAS!$B$14:$M$14,1,ROW()-16)-INDEX(ARUS_KAS!$B$15:$M$15,1,ROW()-16)+INDEX(ARUS_KAS!$B$24:$M$24,1,ROW()-16)-INDEX(ARUS_KAS!$B$25:$M$25,1,ROW()-16)+INDEX(ARUS_KAS!$B$26:$M$26,1,ROW()-16)+INDEX(ARUS_KAS!$B$28:$M$28,1,ROW()-16))} -> 0 | N17: =IF(ROW()-16>MASTER!$AF$15,"",ABS(F17+G17-H17-I17-J17-K17+L17-M17)) -> 0
A18: Feb | B18: =IF(ROW()-16>MASTER!$AF$15,"",SUMIFS(PEMASUKAN!$H$5:$H$204,PEMASUKAN!$C$5:$C$204,TEXT(DATE($B$4,ROW()-16,1),"yyyy-mm"),PEMASUKAN!$M$5:$M$204,"Pendapatan Operasional")) -> 0 | C18: =IF(ROW()-16>MASTER!$AF$15,"",SUMIFS(PENGELUARAN!$K$5:$K$204,PENGELUARAN!$C$5:$C$204,TEXT(DATE($B$4,ROW()-16,1),"yyyy-mm"),PENGELUARAN!$L$5:$L$204,"Kantor")+SUMIFS(GAJI!$Q$5:$Q$124,GAJI!$B$5:$B$124,">="&DATE($B$4,ROW()-16,1),GAJI!$B$5:$B$124,"<"&DATE($B$4,ROW()-15,1))) -> 0 | D18: =IF(ROW()-16>MASTER!$AF$15,"",B18-C18) -> 0 | E18: =IF(ROW()-16>MASTER!$AF$15,"",SUM($D$17:D18)) -> 0 | F18: =IF(ROW()-16>MASTER!$AF$15,"",IF(ROW()=17,SUMIFS(KAS_BANK!$B$5:$B$10,KAS_BANK!$A$5:$A$10,"<>Bank Dana Klien")+MAX(-KAS_BANK!$B$7,0)+MAX(-KAS_BANK!$B$8,0)+MAX(-KAS_BANK!$B$9,0),M17)) -> 0 | G18: =IF(ROW()-16>MASTER!$AF$15,"",SUMIFS(PEMASUKAN!$J$5:$J$204,PEMASUKAN!$C$5:$C$204,TEXT(DATE($B$4,ROW()-16,1),"yyyy-mm"),PEMASUKAN!$M$5:$M$204,"Pendapatan Operasional")+SUMIFS(PEMASUKAN!$J$5:$J$204,PEMASUKAN!$C$5:$C$204,TEXT(DATE($B$4,ROW()-16,1),"yyyy-mm"),PEMASUKAN!$M$5:$M$204,"Penggantian Biaya")) -> 0 | H18: =IF(ROW()-16>MASTER!$AF$15,"",SUMIFS(PENGELUARAN!$K$5:$K$204,PENGELUARAN!$C$5:$C$204,TEXT(DATE($B$4,ROW()-16,1),"yyyy-mm"),PENGELUARAN!$I$5:$I$204,"<>",PENGELUARAN!$I$5:$I$204,"<>Bank Dana Klien")+SUMIFS(GAJI!$P$5:$P$124,GAJI!$S$5:$S$124,">="&DATE($B$4,ROW()-16,1),GAJI!$S$5:$S$124,"<"&DATE($B$4,ROW()-15,1),GAJI!$R$5:$R$124,"Dibayar")+SUMIFS(KEWAJIBAN!$F$5:$F$124,KEWAJIBAN!$I$5:$I$124,">="&DATE($B$4,ROW()-16,1),KEWAJIBAN!$I$5:$I$124,"<"&DATE($B$4,ROW()-15,1))) -> 0 | I18: =IF(ROW()-16>MASTER!$AF$15,"",SUMIFS(REIMBURSE!$J$5:$J$124,REIMBURSE!$N$5:$N$124,">="&DATE($B$4,ROW()-16,1),REIMBURSE!$N$5:$N$124,"<"&DATE($B$4,ROW()-15,1))) -> 0 | J18: =IF(ROW()-16>MASTER!$AF$15,"",SUMIFS(PARTNER!$I$5:$I$124,PARTNER!$E$5:$E$124,MASTER!$Y$7,PARTNER!$V$5:$V$124,">="&DATE($B$4,ROW()-16,1),PARTNER!$V$5:$V$124,"<"&DATE($B$4,ROW()-15,1))+SUMIFS(PARTNER!$I$5:$I$124,PARTNER!$E$5:$E$124,MASTER!$Y$8,PARTNER!$V$5:$V$124,">="&DATE($B$4,ROW()-16,1),PARTNER!$V$5:$V$124,"<"&DATE($B$4,ROW()-15,1))) -> 0 | K18: =IF(ROW()-16>MASTER!$AF$15,"",SUMIFS(PARTNER!$I$5:$I$124,PARTNER!$E$5:$E$124,MASTER!$Y$9,PARTNER!$V$5:$V$124,">="&DATE($B$4,ROW()-16,1),PARTNER!$V$5:$V$124,"<"&DATE($B$4,ROW()-15,1))) -> 0 | L18: {=IF(ROW()-16>MASTER!$AF$15,"",INDEX(ARUS_KAS!$B$24:$M$24,1,ROW()-16)+INDEX(ARUS_KAS!$B$26:$M$26,1,ROW()-16)+INDEX(ARUS_KAS!$B$28:$M$28,1,ROW()-16))} -> 0 | M18: {=IF(ROW()-16>MASTER!$AF$15,"",F18+INDEX(ARUS_KAS!$B$8:$M$8,1,ROW()-16)+INDEX(ARUS_KAS!$B$9:$M$9,1,ROW()-16)-INDEX(ARUS_KAS!$B$12:$M$12,1,ROW()-16)-INDEX(ARUS_KAS!$B$13:$M$13,1,ROW()-16)-INDEX(ARUS_KAS!$B$14:$M$14,1,ROW()-16)-INDEX(ARUS_KAS!$B$15:$M$15,1,ROW()-16)+INDEX(ARUS_KAS!$B$24:$M$24,1,ROW()-16)-INDEX(ARUS_KAS!$B$25:$M$25,1,ROW()-16)+INDEX(ARUS_KAS!$B$26:$M$26,1,ROW()-16)+INDEX(ARUS_KAS!$B$28:$M$28,1,ROW()-16))} -> 0 | N18: =IF(ROW()-16>MASTER!$AF$15,"",ABS(F18+G18-H18-I18-J18-K18+L18-M18)) -> 0
A19: Mar | B19: =IF(ROW()-16>MASTER!$AF$15,"",SUMIFS(PEMASUKAN!$H$5:$H$204,PEMASUKAN!$C$5:$C$204,TEXT(DATE($B$4,ROW()-16,1),"yyyy-mm"),PEMASUKAN!$M$5:$M$204,"Pendapatan Operasional")) -> 0 | C19: =IF(ROW()-16>MASTER!$AF$15,"",SUMIFS(PENGELUARAN!$K$5:$K$204,PENGELUARAN!$C$5:$C$204,TEXT(DATE($B$4,ROW()-16,1),"yyyy-mm"),PENGELUARAN!$L$5:$L$204,"Kantor")+SUMIFS(GAJI!$Q$5:$Q$124,GAJI!$B$5:$B$124,">="&DATE($B$4,ROW()-16,1),GAJI!$B$5:$B$124,"<"&DATE($B$4,ROW()-15,1))) -> 0 | D19: =IF(ROW()-16>MASTER!$AF$15,"",B19-C19) -> 0 | E19: =IF(ROW()-16>MASTER!$AF$15,"",SUM($D$17:D19)) -> 0 | F19: =IF(ROW()-16>MASTER!$AF$15,"",IF(ROW()=17,SUMIFS(KAS_BANK!$B$5:$B$10,KAS_BANK!$A$5:$A$10,"<>Bank Dana Klien")+MAX(-KAS_BANK!$B$7,0)+MAX(-KAS_BANK!$B$8,0)+MAX(-KAS_BANK!$B$9,0),M18)) -> 0 | G19: =IF(ROW()-16>MASTER!$AF$15,"",SUMIFS(PEMASUKAN!$J$5:$J$204,PEMASUKAN!$C$5:$C$204,TEXT(DATE($B$4,ROW()-16,1),"yyyy-mm"),PEMASUKAN!$M$5:$M$204,"Pendapatan Operasional")+SUMIFS(PEMASUKAN!$J$5:$J$204,PEMASUKAN!$C$5:$C$204,TEXT(DATE($B$4,ROW()-16,1),"yyyy-mm"),PEMASUKAN!$M$5:$M$204,"Penggantian Biaya")) -> 0 | H19: =IF(ROW()-16>MASTER!$AF$15,"",SUMIFS(PENGELUARAN!$K$5:$K$204,PENGELUARAN!$C$5:$C$204,TEXT(DATE($B$4,ROW()-16,1),"yyyy-mm"),PENGELUARAN!$I$5:$I$204,"<>",PENGELUARAN!$I$5:$I$204,"<>Bank Dana Klien")+SUMIFS(GAJI!$P$5:$P$124,GAJI!$S$5:$S$124,">="&DATE($B$4,ROW()-16,1),GAJI!$S$5:$S$124,"<"&DATE($B$4,ROW()-15,1),GAJI!$R$5:$R$124,"Dibayar")+SUMIFS(KEWAJIBAN!$F$5:$F$124,KEWAJIBAN!$I$5:$I$124,">="&DATE($B$4,ROW()-16,1),KEWAJIBAN!$I$5:$I$124,"<"&DATE($B$4,ROW()-15,1))) -> 0 | I19: =IF(ROW()-16>MASTER!$AF$15,"",SUMIFS(REIMBURSE!$J$5:$J$124,REIMBURSE!$N$5:$N$124,">="&DATE($B$4,ROW()-16,1),REIMBURSE!$N$5:$N$124,"<"&DATE($B$4,ROW()-15,1))) -> 0 | J19: =IF(ROW()-16>MASTER!$AF$15,"",SUMIFS(PARTNER!$I$5:$I$124,PARTNER!$E$5:$E$124,MASTER!$Y$7,PARTNER!$V$5:$V$124,">="&DATE($B$4,ROW()-16,1),PARTNER!$V$5:$V$124,"<"&DATE($B$4,ROW()-15,1))+SUMIFS(PARTNER!$I$5:$I$124,PARTNER!$E$5:$E$124,MASTER!$Y$8,PARTNER!$V$5:$V$124,">="&DATE($B$4,ROW()-16,1),PARTNER!$V$5:$V$124,"<"&DATE($B$4,ROW()-15,1))) -> 0 | K19: =IF(ROW()-16>MASTER!$AF$15,"",SUMIFS(PARTNER!$I$5:$I$124,PARTNER!$E$5:$E$124,MASTER!$Y$9,PARTNER!$V$5:$V$124,">="&DATE($B$4,ROW()-16,1),PARTNER!$V$5:$V$124,"<"&DATE($B$4,ROW()-15,1))) -> 0 | L19: {=IF(ROW()-16>MASTER!$AF$15,"",INDEX(ARUS_KAS!$B$24:$M$24,1,ROW()-16)+INDEX(ARUS_KAS!$B$26:$M$26,1,ROW()-16)+INDEX(ARUS_KAS!$B$28:$M$28,1,ROW()-16))} -> 0 | M19: {=IF(ROW()-16>MASTER!$AF$15,"",F19+INDEX(ARUS_KAS!$B$8:$M$8,1,ROW()-16)+INDEX(ARUS_KAS!$B$9:$M$9,1,ROW()-16)-INDEX(ARUS_KAS!$B$12:$M$12,1,ROW()-16)-INDEX(ARUS_KAS!$B$13:$M$13,1,ROW()-16)-INDEX(ARUS_KAS!$B$14:$M$14,1,ROW()-16)-INDEX(ARUS_KAS!$B$15:$M$15,1,ROW()-16)+INDEX(ARUS_KAS!$B$24:$M$24,1,ROW()-16)-INDEX(ARUS_KAS!$B$25:$M$25,1,ROW()-16)+INDEX(ARUS_KAS!$B$26:$M$26,1,ROW()-16)+INDEX(ARUS_KAS!$B$28:$M$28,1,ROW()-16))} -> 0 | N19: =IF(ROW()-16>MASTER!$AF$15,"",ABS(F19+G19-H19-I19-J19-K19+L19-M19)) -> 0
A20: Apr | B20: =IF(ROW()-16>MASTER!$AF$15,"",SUMIFS(PEMASUKAN!$H$5:$H$204,PEMASUKAN!$C$5:$C$204,TEXT(DATE($B$4,ROW()-16,1),"yyyy-mm"),PEMASUKAN!$M$5:$M$204,"Pendapatan Operasional")) -> 0 | C20: =IF(ROW()-16>MASTER!$AF$15,"",SUMIFS(PENGELUARAN!$K$5:$K$204,PENGELUARAN!$C$5:$C$204,TEXT(DATE($B$4,ROW()-16,1),"yyyy-mm"),PENGELUARAN!$L$5:$L$204,"Kantor")+SUMIFS(GAJI!$Q$5:$Q$124,GAJI!$B$5:$B$124,">="&DATE($B$4,ROW()-16,1),GAJI!$B$5:$B$124,"<"&DATE($B$4,ROW()-15,1))) -> 0 | D20: =IF(ROW()-16>MASTER!$AF$15,"",B20-C20) -> 0 | E20: =IF(ROW()-16>MASTER!$AF$15,"",SUM($D$17:D20)) -> 0 | F20: =IF(ROW()-16>MASTER!$AF$15,"",IF(ROW()=17,SUMIFS(KAS_BANK!$B$5:$B$10,KAS_BANK!$A$5:$A$10,"<>Bank Dana Klien")+MAX(-KAS_BANK!$B$7,0)+MAX(-KAS_BANK!$B$8,0)+MAX(-KAS_BANK!$B$9,0),M19)) -> 0 | G20: =IF(ROW()-16>MASTER!$AF$15,"",SUMIFS(PEMASUKAN!$J$5:$J$204,PEMASUKAN!$C$5:$C$204,TEXT(DATE($B$4,ROW()-16,1),"yyyy-mm"),PEMASUKAN!$M$5:$M$204,"Pendapatan Operasional")+SUMIFS(PEMASUKAN!$J$5:$J$204,PEMASUKAN!$C$5:$C$204,TEXT(DATE($B$4,ROW()-16,1),"yyyy-mm"),PEMASUKAN!$M$5:$M$204,"Penggantian Biaya")) -> 0 | H20: =IF(ROW()-16>MASTER!$AF$15,"",SUMIFS(PENGELUARAN!$K$5:$K$204,PENGELUARAN!$C$5:$C$204,TEXT(DATE($B$4,ROW()-16,1),"yyyy-mm"),PENGELUARAN!$I$5:$I$204,"<>",PENGELUARAN!$I$5:$I$204,"<>Bank Dana Klien")+SUMIFS(GAJI!$P$5:$P$124,GAJI!$S$5:$S$124,">="&DATE($B$4,ROW()-16,1),GAJI!$S$5:$S$124,"<"&DATE($B$4,ROW()-15,1),GAJI!$R$5:$R$124,"Dibayar")+SUMIFS(KEWAJIBAN!$F$5:$F$124,KEWAJIBAN!$I$5:$I$124,">="&DATE($B$4,ROW()-16,1),KEWAJIBAN!$I$5:$I$124,"<"&DATE($B$4,ROW()-15,1))) -> 0 | I20: =IF(ROW()-16>MASTER!$AF$15,"",SUMIFS(REIMBURSE!$J$5:$J$124,REIMBURSE!$N$5:$N$124,">="&DATE($B$4,ROW()-16,1),REIMBURSE!$N$5:$N$124,"<"&DATE($B$4,ROW()-15,1))) -> 0 | J20: =IF(ROW()-16>MASTER!$AF$15,"",SUMIFS(PARTNER!$I$5:$I$124,PARTNER!$E$5:$E$124,MASTER!$Y$7,PARTNER!$V$5:$V$124,">="&DATE($B$4,ROW()-16,1),PARTNER!$V$5:$V$124,"<"&DATE($B$4,ROW()-15,1))+SUMIFS(PARTNER!$I$5:$I$124,PARTNER!$E$5:$E$124,MASTER!$Y$8,PARTNER!$V$5:$V$124,">="&DATE($B$4,ROW()-16,1),PARTNER!$V$5:$V$124,"<"&DATE($B$4,ROW()-15,1))) -> 0 | K20: =IF(ROW()-16>MASTER!$AF$15,"",SUMIFS(PARTNER!$I$5:$I$124,PARTNER!$E$5:$E$124,MASTER!$Y$9,PARTNER!$V$5:$V$124,">="&DATE($B$4,ROW()-16,1),PARTNER!$V$5:$V$124,"<"&DATE($B$4,ROW()-15,1))) -> 0 | L20: {=IF(ROW()-16>MASTER!$AF$15,"",INDEX(ARUS_KAS!$B$24:$M$24,1,ROW()-16)+INDEX(ARUS_KAS!$B$26:$M$26,1,ROW()-16)+INDEX(ARUS_KAS!$B$28:$M$28,1,ROW()-16))} -> 0 | M20: {=IF(ROW()-16>MASTER!$AF$15,"",F20+INDEX(ARUS_KAS!$B$8:$M$8,1,ROW()-16)+INDEX(ARUS_KAS!$B$9:$M$9,1,ROW()-16)-INDEX(ARUS_KAS!$B$12:$M$12,1,ROW()-16)-INDEX(ARUS_KAS!$B$13:$M$13,1,ROW()-16)-INDEX(ARUS_KAS!$B$14:$M$14,1,ROW()-16)-INDEX(ARUS_KAS!$B$15:$M$15,1,ROW()-16)+INDEX(ARUS_KAS!$B$24:$M$24,1,ROW()-16)-INDEX(ARUS_KAS!$B$25:$M$25,1,ROW()-16)+INDEX(ARUS_KAS!$B$26:$M$26,1,ROW()-16)+INDEX(ARUS_KAS!$B$28:$M$28,1,ROW()-16))} -> 0 | N20: =IF(ROW()-16>MASTER!$AF$15,"",ABS(F20+G20-H20-I20-J20-K20+L20-M20)) -> 0
A21: Mei | B21: =IF(ROW()-16>MASTER!$AF$15,"",SUMIFS(PEMASUKAN!$H$5:$H$204,PEMASUKAN!$C$5:$C$204,TEXT(DATE($B$4,ROW()-16,1),"yyyy-mm"),PEMASUKAN!$M$5:$M$204,"Pendapatan Operasional")) -> 0 | C21: =IF(ROW()-16>MASTER!$AF$15,"",SUMIFS(PENGELUARAN!$K$5:$K$204,PENGELUARAN!$C$5:$C$204,TEXT(DATE($B$4,ROW()-16,1),"yyyy-mm"),PENGELUARAN!$L$5:$L$204,"Kantor")+SUMIFS(GAJI!$Q$5:$Q$124,GAJI!$B$5:$B$124,">="&DATE($B$4,ROW()-16,1),GAJI!$B$5:$B$124,"<"&DATE($B$4,ROW()-15,1))) -> 0 | D21: =IF(ROW()-16>MASTER!$AF$15,"",B21-C21) -> 0 | E21: =IF(ROW()-16>MASTER!$AF$15,"",SUM($D$17:D21)) -> 0 | F21: =IF(ROW()-16>MASTER!$AF$15,"",IF(ROW()=17,SUMIFS(KAS_BANK!$B$5:$B$10,KAS_BANK!$A$5:$A$10,"<>Bank Dana Klien")+MAX(-KAS_BANK!$B$7,0)+MAX(-KAS_BANK!$B$8,0)+MAX(-KAS_BANK!$B$9,0),M20)) -> 0 | G21: =IF(ROW()-16>MASTER!$AF$15,"",SUMIFS(PEMASUKAN!$J$5:$J$204,PEMASUKAN!$C$5:$C$204,TEXT(DATE($B$4,ROW()-16,1),"yyyy-mm"),PEMASUKAN!$M$5:$M$204,"Pendapatan Operasional")+SUMIFS(PEMASUKAN!$J$5:$J$204,PEMASUKAN!$C$5:$C$204,TEXT(DATE($B$4,ROW()-16,1),"yyyy-mm"),PEMASUKAN!$M$5:$M$204,"Penggantian Biaya")) -> 0 | H21: =IF(ROW()-16>MASTER!$AF$15,"",SUMIFS(PENGELUARAN!$K$5:$K$204,PENGELUARAN!$C$5:$C$204,TEXT(DATE($B$4,ROW()-16,1),"yyyy-mm"),PENGELUARAN!$I$5:$I$204,"<>",PENGELUARAN!$I$5:$I$204,"<>Bank Dana Klien")+SUMIFS(GAJI!$P$5:$P$124,GAJI!$S$5:$S$124,">="&DATE($B$4,ROW()-16,1),GAJI!$S$5:$S$124,"<"&DATE($B$4,ROW()-15,1),GAJI!$R$5:$R$124,"Dibayar")+SUMIFS(KEWAJIBAN!$F$5:$F$124,KEWAJIBAN!$I$5:$I$124,">="&DATE($B$4,ROW()-16,1),KEWAJIBAN!$I$5:$I$124,"<"&DATE($B$4,ROW()-15,1))) -> 0 | I21: =IF(ROW()-16>MASTER!$AF$15,"",SUMIFS(REIMBURSE!$J$5:$J$124,REIMBURSE!$N$5:$N$124,">="&DATE($B$4,ROW()-16,1),REIMBURSE!$N$5:$N$124,"<"&DATE($B$4,ROW()-15,1))) -> 0 | J21: =IF(ROW()-16>MASTER!$AF$15,"",SUMIFS(PARTNER!$I$5:$I$124,PARTNER!$E$5:$E$124,MASTER!$Y$7,PARTNER!$V$5:$V$124,">="&DATE($B$4,ROW()-16,1),PARTNER!$V$5:$V$124,"<"&DATE($B$4,ROW()-15,1))+SUMIFS(PARTNER!$I$5:$I$124,PARTNER!$E$5:$E$124,MASTER!$Y$8,PARTNER!$V$5:$V$124,">="&DATE($B$4,ROW()-16,1),PARTNER!$V$5:$V$124,"<"&DATE($B$4,ROW()-15,1))) -> 0 | K21: =IF(ROW()-16>MASTER!$AF$15,"",SUMIFS(PARTNER!$I$5:$I$124,PARTNER!$E$5:$E$124,MASTER!$Y$9,PARTNER!$V$5:$V$124,">="&DATE($B$4,ROW()-16,1),PARTNER!$V$5:$V$124,"<"&DATE($B$4,ROW()-15,1))) -> 0 | L21: {=IF(ROW()-16>MASTER!$AF$15,"",INDEX(ARUS_KAS!$B$24:$M$24,1,ROW()-16)+INDEX(ARUS_KAS!$B$26:$M$26,1,ROW()-16)+INDEX(ARUS_KAS!$B$28:$M$28,1,ROW()-16))} -> 0 | M21: {=IF(ROW()-16>MASTER!$AF$15,"",F21+INDEX(ARUS_KAS!$B$8:$M$8,1,ROW()-16)+INDEX(ARUS_KAS!$B$9:$M$9,1,ROW()-16)-INDEX(ARUS_KAS!$B$12:$M$12,1,ROW()-16)-INDEX(ARUS_KAS!$B$13:$M$13,1,ROW()-16)-INDEX(ARUS_KAS!$B$14:$M$14,1,ROW()-16)-INDEX(ARUS_KAS!$B$15:$M$15,1,ROW()-16)+INDEX(ARUS_KAS!$B$24:$M$24,1,ROW()-16)-INDEX(ARUS_KAS!$B$25:$M$25,1,ROW()-16)+INDEX(ARUS_KAS!$B$26:$M$26,1,ROW()-16)+INDEX(ARUS_KAS!$B$28:$M$28,1,ROW()-16))} -> 0 | N21: =IF(ROW()-16>MASTER!$AF$15,"",ABS(F21+G21-H21-I21-J21-K21+L21-M21)) -> 0
A22: Jun | B22: =IF(ROW()-16>MASTER!$AF$15,"",SUMIFS(PEMASUKAN!$H$5:$H$204,PEMASUKAN!$C$5:$C$204,TEXT(DATE($B$4,ROW()-16,1),"yyyy-mm"),PEMASUKAN!$M$5:$M$204,"Pendapatan Operasional")) -> 0 | C22: =IF(ROW()-16>MASTER!$AF$15,"",SUMIFS(PENGELUARAN!$K$5:$K$204,PENGELUARAN!$C$5:$C$204,TEXT(DATE($B$4,ROW()-16,1),"yyyy-mm"),PENGELUARAN!$L$5:$L$204,"Kantor")+SUMIFS(GAJI!$Q$5:$Q$124,GAJI!$B$5:$B$124,">="&DATE($B$4,ROW()-16,1),GAJI!$B$5:$B$124,"<"&DATE($B$4,ROW()-15,1))) -> 0 | D22: =IF(ROW()-16>MASTER!$AF$15,"",B22-C22) -> 0 | E22: =IF(ROW()-16>MASTER!$AF$15,"",SUM($D$17:D22)) -> 0 | F22: =IF(ROW()-16>MASTER!$AF$15,"",IF(ROW()=17,SUMIFS(KAS_BANK!$B$5:$B$10,KAS_BANK!$A$5:$A$10,"<>Bank Dana Klien")+MAX(-KAS_BANK!$B$7,0)+MAX(-KAS_BANK!$B$8,0)+MAX(-KAS_BANK!$B$9,0),M21)) -> 0 | G22: =IF(ROW()-16>MASTER!$AF$15,"",SUMIFS(PEMASUKAN!$J$5:$J$204,PEMASUKAN!$C$5:$C$204,TEXT(DATE($B$4,ROW()-16,1),"yyyy-mm"),PEMASUKAN!$M$5:$M$204,"Pendapatan Operasional")+SUMIFS(PEMASUKAN!$J$5:$J$204,PEMASUKAN!$C$5:$C$204,TEXT(DATE($B$4,ROW()-16,1),"yyyy-mm"),PEMASUKAN!$M$5:$M$204,"Penggantian Biaya")) -> 0 | H22: =IF(ROW()-16>MASTER!$AF$15,"",SUMIFS(PENGELUARAN!$K$5:$K$204,PENGELUARAN!$C$5:$C$204,TEXT(DATE($B$4,ROW()-16,1),"yyyy-mm"),PENGELUARAN!$I$5:$I$204,"<>",PENGELUARAN!$I$5:$I$204,"<>Bank Dana Klien")+SUMIFS(GAJI!$P$5:$P$124,GAJI!$S$5:$S$124,">="&DATE($B$4,ROW()-16,1),GAJI!$S$5:$S$124,"<"&DATE($B$4,ROW()-15,1),GAJI!$R$5:$R$124,"Dibayar")+SUMIFS(KEWAJIBAN!$F$5:$F$124,KEWAJIBAN!$I$5:$I$124,">="&DATE($B$4,ROW()-16,1),KEWAJIBAN!$I$5:$I$124,"<"&DATE($B$4,ROW()-15,1))) -> 0 | I22: =IF(ROW()-16>MASTER!$AF$15,"",SUMIFS(REIMBURSE!$J$5:$J$124,REIMBURSE!$N$5:$N$124,">="&DATE($B$4,ROW()-16,1),REIMBURSE!$N$5:$N$124,"<"&DATE($B$4,ROW()-15,1))) -> 0 | J22: =IF(ROW()-16>MASTER!$AF$15,"",SUMIFS(PARTNER!$I$5:$I$124,PARTNER!$E$5:$E$124,MASTER!$Y$7,PARTNER!$V$5:$V$124,">="&DATE($B$4,ROW()-16,1),PARTNER!$V$5:$V$124,"<"&DATE($B$4,ROW()-15,1))+SUMIFS(PARTNER!$I$5:$I$124,PARTNER!$E$5:$E$124,MASTER!$Y$8,PARTNER!$V$5:$V$124,">="&DATE($B$4,ROW()-16,1),PARTNER!$V$5:$V$124,"<"&DATE($B$4,ROW()-15,1))) -> 0 | K22: =IF(ROW()-16>MASTER!$AF$15,"",SUMIFS(PARTNER!$I$5:$I$124,PARTNER!$E$5:$E$124,MASTER!$Y$9,PARTNER!$V$5:$V$124,">="&DATE($B$4,ROW()-16,1),PARTNER!$V$5:$V$124,"<"&DATE($B$4,ROW()-15,1))) -> 0 | L22: {=IF(ROW()-16>MASTER!$AF$15,"",INDEX(ARUS_KAS!$B$24:$M$24,1,ROW()-16)+INDEX(ARUS_KAS!$B$26:$M$26,1,ROW()-16)+INDEX(ARUS_KAS!$B$28:$M$28,1,ROW()-16))} -> 0 | M22: {=IF(ROW()-16>MASTER!$AF$15,"",F22+INDEX(ARUS_KAS!$B$8:$M$8,1,ROW()-16)+INDEX(ARUS_KAS!$B$9:$M$9,1,ROW()-16)-INDEX(ARUS_KAS!$B$12:$M$12,1,ROW()-16)-INDEX(ARUS_KAS!$B$13:$M$13,1,ROW()-16)-INDEX(ARUS_KAS!$B$14:$M$14,1,ROW()-16)-INDEX(ARUS_KAS!$B$15:$M$15,1,ROW()-16)+INDEX(ARUS_KAS!$B$24:$M$24,1,ROW()-16)-INDEX(ARUS_KAS!$B$25:$M$25,1,ROW()-16)+INDEX(ARUS_KAS!$B$26:$M$26,1,ROW()-16)+INDEX(ARUS_KAS!$B$28:$M$28,1,ROW()-16))} -> 0 | N22: =IF(ROW()-16>MASTER!$AF$15,"",ABS(F22+G22-H22-I22-J22-K22+L22-M22)) -> 0
A23: Jul | B23: =IF(ROW()-16>MASTER!$AF$15,"",SUMIFS(PEMASUKAN!$H$5:$H$204,PEMASUKAN!$C$5:$C$204,TEXT(DATE($B$4,ROW()-16,1),"yyyy-mm"),PEMASUKAN!$M$5:$M$204,"Pendapatan Operasional")) -> 16000000 | C23: =IF(ROW()-16>MASTER!$AF$15,"",SUMIFS(PENGELUARAN!$K$5:$K$204,PENGELUARAN!$C$5:$C$204,TEXT(DATE($B$4,ROW()-16,1),"yyyy-mm"),PENGELUARAN!$L$5:$L$204,"Kantor")+SUMIFS(GAJI!$Q$5:$Q$124,GAJI!$B$5:$B$124,">="&DATE($B$4,ROW()-16,1),GAJI!$B$5:$B$124,"<"&DATE($B$4,ROW()-15,1))) -> 3390600 | D23: =IF(ROW()-16>MASTER!$AF$15,"",B23-C23) -> 12609400 | E23: =IF(ROW()-16>MASTER!$AF$15,"",SUM($D$17:D23)) -> 12609400 | F23: =IF(ROW()-16>MASTER!$AF$15,"",IF(ROW()=17,SUMIFS(KAS_BANK!$B$5:$B$10,KAS_BANK!$A$5:$A$10,"<>Bank Dana Klien")+MAX(-KAS_BANK!$B$7,0)+MAX(-KAS_BANK!$B$8,0)+MAX(-KAS_BANK!$B$9,0),M22)) -> 0 | G23: =IF(ROW()-16>MASTER!$AF$15,"",SUMIFS(PEMASUKAN!$J$5:$J$204,PEMASUKAN!$C$5:$C$204,TEXT(DATE($B$4,ROW()-16,1),"yyyy-mm"),PEMASUKAN!$M$5:$M$204,"Pendapatan Operasional")+SUMIFS(PEMASUKAN!$J$5:$J$204,PEMASUKAN!$C$5:$C$204,TEXT(DATE($B$4,ROW()-16,1),"yyyy-mm"),PEMASUKAN!$M$5:$M$204,"Penggantian Biaya")) -> 16000000 | H23: =IF(ROW()-16>MASTER!$AF$15,"",SUMIFS(PENGELUARAN!$K$5:$K$204,PENGELUARAN!$C$5:$C$204,TEXT(DATE($B$4,ROW()-16,1),"yyyy-mm"),PENGELUARAN!$I$5:$I$204,"<>",PENGELUARAN!$I$5:$I$204,"<>Bank Dana Klien")+SUMIFS(GAJI!$P$5:$P$124,GAJI!$S$5:$S$124,">="&DATE($B$4,ROW()-16,1),GAJI!$S$5:$S$124,"<"&DATE($B$4,ROW()-15,1),GAJI!$R$5:$R$124,"Dibayar")+SUMIFS(KEWAJIBAN!$F$5:$F$124,KEWAJIBAN!$I$5:$I$124,">="&DATE($B$4,ROW()-16,1),KEWAJIBAN!$I$5:$I$124,"<"&DATE($B$4,ROW()-15,1))) -> 3390600 | I23: =IF(ROW()-16>MASTER!$AF$15,"",SUMIFS(REIMBURSE!$J$5:$J$124,REIMBURSE!$N$5:$N$124,">="&DATE($B$4,ROW()-16,1),REIMBURSE!$N$5:$N$124,"<"&DATE($B$4,ROW()-15,1))) -> 0 | J23: =IF(ROW()-16>MASTER!$AF$15,"",SUMIFS(PARTNER!$I$5:$I$124,PARTNER!$E$5:$E$124,MASTER!$Y$7,PARTNER!$V$5:$V$124,">="&DATE($B$4,ROW()-16,1),PARTNER!$V$5:$V$124,"<"&DATE($B$4,ROW()-15,1))+SUMIFS(PARTNER!$I$5:$I$124,PARTNER!$E$5:$E$124,MASTER!$Y$8,PARTNER!$V$5:$V$124,">="&DATE($B$4,ROW()-16,1),PARTNER!$V$5:$V$124,"<"&DATE($B$4,ROW()-15,1))) -> 9000000 | K23: =IF(ROW()-16>MASTER!$AF$15,"",SUMIFS(PARTNER!$I$5:$I$124,PARTNER!$E$5:$E$124,MASTER!$Y$9,PARTNER!$V$5:$V$124,">="&DATE($B$4,ROW()-16,1),PARTNER!$V$5:$V$124,"<"&DATE($B$4,ROW()-15,1))) -> 0 | L23: {=IF(ROW()-16>MASTER!$AF$15,"",INDEX(ARUS_KAS!$B$24:$M$24,1,ROW()-16)+INDEX(ARUS_KAS!$B$26:$M$26,1,ROW()-16)+INDEX(ARUS_KAS!$B$28:$M$28,1,ROW()-16))} -> 1000000 | M23: {=IF(ROW()-16>MASTER!$AF$15,"",F23+INDEX(ARUS_KAS!$B$8:$M$8,1,ROW()-16)+INDEX(ARUS_KAS!$B$9:$M$9,1,ROW()-16)-INDEX(ARUS_KAS!$B$12:$M$12,1,ROW()-16)-INDEX(ARUS_KAS!$B$13:$M$13,1,ROW()-16)-INDEX(ARUS_KAS!$B$14:$M$14,1,ROW()-16)-INDEX(ARUS_KAS!$B$15:$M$15,1,ROW()-16)+INDEX(ARUS_KAS!$B$24:$M$24,1,ROW()-16)-INDEX(ARUS_KAS!$B$25:$M$25,1,ROW()-16)+INDEX(ARUS_KAS!$B$26:$M$26,1,ROW()-16)+INDEX(ARUS_KAS!$B$28:$M$28,1,ROW()-16))} -> 4609400 | N23: =IF(ROW()-16>MASTER!$AF$15,"",ABS(F23+G23-H23-I23-J23-K23+L23-M23)) -> 0
A24: Agu | B24: =IF(ROW()-16>MASTER!$AF$15,"",SUMIFS(PEMASUKAN!$H$5:$H$204,PEMASUKAN!$C$5:$C$204,TEXT(DATE($B$4,ROW()-16,1),"yyyy-mm"),PEMASUKAN!$M$5:$M$204,"Pendapatan Operasional")) -> 0 | C24: =IF(ROW()-16>MASTER!$AF$15,"",SUMIFS(PENGELUARAN!$K$5:$K$204,PENGELUARAN!$C$5:$C$204,TEXT(DATE($B$4,ROW()-16,1),"yyyy-mm"),PENGELUARAN!$L$5:$L$204,"Kantor")+SUMIFS(GAJI!$Q$5:$Q$124,GAJI!$B$5:$B$124,">="&DATE($B$4,ROW()-16,1),GAJI!$B$5:$B$124,"<"&DATE($B$4,ROW()-15,1))) -> 4705308 | D24: =IF(ROW()-16>MASTER!$AF$15,"",B24-C24) -> -4705308 | E24: =IF(ROW()-16>MASTER!$AF$15,"",SUM($D$17:D24)) -> 7904092 | F24: =IF(ROW()-16>MASTER!$AF$15,"",IF(ROW()=17,SUMIFS(KAS_BANK!$B$5:$B$10,KAS_BANK!$A$5:$A$10,"<>Bank Dana Klien")+MAX(-KAS_BANK!$B$7,0)+MAX(-KAS_BANK!$B$8,0)+MAX(-KAS_BANK!$B$9,0),M23)) -> 4609400 | G24: =IF(ROW()-16>MASTER!$AF$15,"",SUMIFS(PEMASUKAN!$J$5:$J$204,PEMASUKAN!$C$5:$C$204,TEXT(DATE($B$4,ROW()-16,1),"yyyy-mm"),PEMASUKAN!$M$5:$M$204,"Pendapatan Operasional")+SUMIFS(PEMASUKAN!$J$5:$J$204,PEMASUKAN!$C$5:$C$204,TEXT(DATE($B$4,ROW()-16,1),"yyyy-mm"),PEMASUKAN!$M$5:$M$204,"Penggantian Biaya")) -> 0 | H24: =IF(ROW()-16>MASTER!$AF$15,"",SUMIFS(PENGELUARAN!$K$5:$K$204,PENGELUARAN!$C$5:$C$204,TEXT(DATE($B$4,ROW()-16,1),"yyyy-mm"),PENGELUARAN!$I$5:$I$204,"<>",PENGELUARAN!$I$5:$I$204,"<>Bank Dana Klien")+SUMIFS(GAJI!$P$5:$P$124,GAJI!$S$5:$S$124,">="&DATE($B$4,ROW()-16,1),GAJI!$S$5:$S$124,"<"&DATE($B$4,ROW()-15,1),GAJI!$R$5:$R$124,"Dibayar")+SUMIFS(KEWAJIBAN!$F$5:$F$124,KEWAJIBAN!$I$5:$I$124,">="&DATE($B$4,ROW()-16,1),KEWAJIBAN!$I$5:$I$124,"<"&DATE($B$4,ROW()-15,1))) -> 1705308 | I24: =IF(ROW()-16>MASTER!$AF$15,"",SUMIFS(REIMBURSE!$J$5:$J$124,REIMBURSE!$N$5:$N$124,">="&DATE($B$4,ROW()-16,1),REIMBURSE!$N$5:$N$124,"<"&DATE($B$4,ROW()-15,1))) -> 0 | J24: =IF(ROW()-16>MASTER!$AF$15,"",SUMIFS(PARTNER!$I$5:$I$124,PARTNER!$E$5:$E$124,MASTER!$Y$7,PARTNER!$V$5:$V$124,">="&DATE($B$4,ROW()-16,1),PARTNER!$V$5:$V$124,"<"&DATE($B$4,ROW()-15,1))+SUMIFS(PARTNER!$I$5:$I$124,PARTNER!$E$5:$E$124,MASTER!$Y$8,PARTNER!$V$5:$V$124,">="&DATE($B$4,ROW()-16,1),PARTNER!$V$5:$V$124,"<"&DATE($B$4,ROW()-15,1))) -> 0 | K24: =IF(ROW()-16>MASTER!$AF$15,"",SUMIFS(PARTNER!$I$5:$I$124,PARTNER!$E$5:$E$124,MASTER!$Y$9,PARTNER!$V$5:$V$124,">="&DATE($B$4,ROW()-16,1),PARTNER!$V$5:$V$124,"<"&DATE($B$4,ROW()-15,1))) -> 0 | L24: {=IF(ROW()-16>MASTER!$AF$15,"",INDEX(ARUS_KAS!$B$24:$M$24,1,ROW()-16)+INDEX(ARUS_KAS!$B$26:$M$26,1,ROW()-16)+INDEX(ARUS_KAS!$B$28:$M$28,1,ROW()-16))} -> 0 | M24: {=IF(ROW()-16>MASTER!$AF$15,"",F24+INDEX(ARUS_KAS!$B$8:$M$8,1,ROW()-16)+INDEX(ARUS_KAS!$B$9:$M$9,1,ROW()-16)-INDEX(ARUS_KAS!$B$12:$M$12,1,ROW()-16)-INDEX(ARUS_KAS!$B$13:$M$13,1,ROW()-16)-INDEX(ARUS_KAS!$B$14:$M$14,1,ROW()-16)-INDEX(ARUS_KAS!$B$15:$M$15,1,ROW()-16)+INDEX(ARUS_KAS!$B$24:$M$24,1,ROW()-16)-INDEX(ARUS_KAS!$B$25:$M$25,1,ROW()-16)+INDEX(ARUS_KAS!$B$26:$M$26,1,ROW()-16)+INDEX(ARUS_KAS!$B$28:$M$28,1,ROW()-16))} -> 2904092 | N24: =IF(ROW()-16>MASTER!$AF$15,"",ABS(F24+G24-H24-I24-J24-K24+L24-M24)) -> 0
A25: Sep | B25: =IF(ROW()-16>MASTER!$AF$15,"",SUMIFS(PEMASUKAN!$H$5:$H$204,PEMASUKAN!$C$5:$C$204,TEXT(DATE($B$4,ROW()-16,1),"yyyy-mm"),PEMASUKAN!$M$5:$M$204,"Pendapatan Operasional")) | C25: =IF(ROW()-16>MASTER!$AF$15,"",SUMIFS(PENGELUARAN!$K$5:$K$204,PENGELUARAN!$C$5:$C$204,TEXT(DATE($B$4,ROW()-16,1),"yyyy-mm"),PENGELUARAN!$L$5:$L$204,"Kantor")+SUMIFS(GAJI!$Q$5:$Q$124,GAJI!$B$5:$B$124,">="&DATE($B$4,ROW()-16,1),GAJI!$B$5:$B$124,"<"&DATE($B$4,ROW()-15,1))) | D25: =IF(ROW()-16>MASTER!$AF$15,"",B25-C25) | E25: =IF(ROW()-16>MASTER!$AF$15,"",SUM($D$17:D25)) | F25: =IF(ROW()-16>MASTER!$AF$15,"",IF(ROW()=17,SUMIFS(KAS_BANK!$B$5:$B$10,KAS_BANK!$A$5:$A$10,"<>Bank Dana Klien")+MAX(-KAS_BANK!$B$7,0)+MAX(-KAS_BANK!$B$8,0)+MAX(-KAS_BANK!$B$9,0),M24)) | G25: =IF(ROW()-16>MASTER!$AF$15,"",SUMIFS(PEMASUKAN!$J$5:$J$204,PEMASUKAN!$C$5:$C$204,TEXT(DATE($B$4,ROW()-16,1),"yyyy-mm"),PEMASUKAN!$M$5:$M$204,"Pendapatan Operasional")+SUMIFS(PEMASUKAN!$J$5:$J$204,PEMASUKAN!$C$5:$C$204,TEXT(DATE($B$4,ROW()-16,1),"yyyy-mm"),PEMASUKAN!$M$5:$M$204,"Penggantian Biaya")) | H25: =IF(ROW()-16>MASTER!$AF$15,"",SUMIFS(PENGELUARAN!$K$5:$K$204,PENGELUARAN!$C$5:$C$204,TEXT(DATE($B$4,ROW()-16,1),"yyyy-mm"),PENGELUARAN!$I$5:$I$204,"<>",PENGELUARAN!$I$5:$I$204,"<>Bank Dana Klien")+SUMIFS(GAJI!$P$5:$P$124,GAJI!$S$5:$S$124,">="&DATE($B$4,ROW()-16,1),GAJI!$S$5:$S$124,"<"&DATE($B$4,ROW()-15,1),GAJI!$R$5:$R$124,"Dibayar")+SUMIFS(KEWAJIBAN!$F$5:$F$124,KEWAJIBAN!$I$5:$I$124,">="&DATE($B$4,ROW()-16,1),KEWAJIBAN!$I$5:$I$124,"<"&DATE($B$4,ROW()-15,1))) | I25: =IF(ROW()-16>MASTER!$AF$15,"",SUMIFS(REIMBURSE!$J$5:$J$124,REIMBURSE!$N$5:$N$124,">="&DATE($B$4,ROW()-16,1),REIMBURSE!$N$5:$N$124,"<"&DATE($B$4,ROW()-15,1))) | J25: =IF(ROW()-16>MASTER!$AF$15,"",SUMIFS(PARTNER!$I$5:$I$124,PARTNER!$E$5:$E$124,MASTER!$Y$7,PARTNER!$V$5:$V$124,">="&DATE($B$4,ROW()-16,1),PARTNER!$V$5:$V$124,"<"&DATE($B$4,ROW()-15,1))+SUMIFS(PARTNER!$I$5:$I$124,PARTNER!$E$5:$E$124,MASTER!$Y$8,PARTNER!$V$5:$V$124,">="&DATE($B$4,ROW()-16,1),PARTNER!$V$5:$V$124,"<"&DATE($B$4,ROW()-15,1))) | K25: =IF(ROW()-16>MASTER!$AF$15,"",SUMIFS(PARTNER!$I$5:$I$124,PARTNER!$E$5:$E$124,MASTER!$Y$9,PARTNER!$V$5:$V$124,">="&DATE($B$4,ROW()-16,1),PARTNER!$V$5:$V$124,"<"&DATE($B$4,ROW()-15,1))) | L25: {=IF(ROW()-16>MASTER!$AF$15,"",INDEX(ARUS_KAS!$B$24:$M$24,1,ROW()-16)+INDEX(ARUS_KAS!$B$26:$M$26,1,ROW()-16)+INDEX(ARUS_KAS!$B$28:$M$28,1,ROW()-16))} | M25: {=IF(ROW()-16>MASTER!$AF$15,"",F25+INDEX(ARUS_KAS!$B$8:$M$8,1,ROW()-16)+INDEX(ARUS_KAS!$B$9:$M$9,1,ROW()-16)-INDEX(ARUS_KAS!$B$12:$M$12,1,ROW()-16)-INDEX(ARUS_KAS!$B$13:$M$13,1,ROW()-16)-INDEX(ARUS_KAS!$B$14:$M$14,1,ROW()-16)-INDEX(ARUS_KAS!$B$15:$M$15,1,ROW()-16)+INDEX(ARUS_KAS!$B$24:$M$24,1,ROW()-16)-INDEX(ARUS_KAS!$B$25:$M$25,1,ROW()-16)+INDEX(ARUS_KAS!$B$26:$M$26,1,ROW()-16)+INDEX(ARUS_KAS!$B$28:$M$28,1,ROW()-16))} | N25: =IF(ROW()-16>MASTER!$AF$15,"",ABS(F25+G25-H25-I25-J25-K25+L25-M25))
A26: Okt | B26: =IF(ROW()-16>MASTER!$AF$15,"",SUMIFS(PEMASUKAN!$H$5:$H$204,PEMASUKAN!$C$5:$C$204,TEXT(DATE($B$4,ROW()-16,1),"yyyy-mm"),PEMASUKAN!$M$5:$M$204,"Pendapatan Operasional")) | C26: =IF(ROW()-16>MASTER!$AF$15,"",SUMIFS(PENGELUARAN!$K$5:$K$204,PENGELUARAN!$C$5:$C$204,TEXT(DATE($B$4,ROW()-16,1),"yyyy-mm"),PENGELUARAN!$L$5:$L$204,"Kantor")+SUMIFS(GAJI!$Q$5:$Q$124,GAJI!$B$5:$B$124,">="&DATE($B$4,ROW()-16,1),GAJI!$B$5:$B$124,"<"&DATE($B$4,ROW()-15,1))) | D26: =IF(ROW()-16>MASTER!$AF$15,"",B26-C26) | E26: =IF(ROW()-16>MASTER!$AF$15,"",SUM($D$17:D26)) | F26: =IF(ROW()-16>MASTER!$AF$15,"",IF(ROW()=17,SUMIFS(KAS_BANK!$B$5:$B$10,KAS_BANK!$A$5:$A$10,"<>Bank Dana Klien")+MAX(-KAS_BANK!$B$7,0)+MAX(-KAS_BANK!$B$8,0)+MAX(-KAS_BANK!$B$9,0),M25)) | G26: =IF(ROW()-16>MASTER!$AF$15,"",SUMIFS(PEMASUKAN!$J$5:$J$204,PEMASUKAN!$C$5:$C$204,TEXT(DATE($B$4,ROW()-16,1),"yyyy-mm"),PEMASUKAN!$M$5:$M$204,"Pendapatan Operasional")+SUMIFS(PEMASUKAN!$J$5:$J$204,PEMASUKAN!$C$5:$C$204,TEXT(DATE($B$4,ROW()-16,1),"yyyy-mm"),PEMASUKAN!$M$5:$M$204,"Penggantian Biaya")) | H26: =IF(ROW()-16>MASTER!$AF$15,"",SUMIFS(PENGELUARAN!$K$5:$K$204,PENGELUARAN!$C$5:$C$204,TEXT(DATE($B$4,ROW()-16,1),"yyyy-mm"),PENGELUARAN!$I$5:$I$204,"<>",PENGELUARAN!$I$5:$I$204,"<>Bank Dana Klien")+SUMIFS(GAJI!$P$5:$P$124,GAJI!$S$5:$S$124,">="&DATE($B$4,ROW()-16,1),GAJI!$S$5:$S$124,"<"&DATE($B$4,ROW()-15,1),GAJI!$R$5:$R$124,"Dibayar")+SUMIFS(KEWAJIBAN!$F$5:$F$124,KEWAJIBAN!$I$5:$I$124,">="&DATE($B$4,ROW()-16,1),KEWAJIBAN!$I$5:$I$124,"<"&DATE($B$4,ROW()-15,1))) | I26: =IF(ROW()-16>MASTER!$AF$15,"",SUMIFS(REIMBURSE!$J$5:$J$124,REIMBURSE!$N$5:$N$124,">="&DATE($B$4,ROW()-16,1),REIMBURSE!$N$5:$N$124,"<"&DATE($B$4,ROW()-15,1))) | J26: =IF(ROW()-16>MASTER!$AF$15,"",SUMIFS(PARTNER!$I$5:$I$124,PARTNER!$E$5:$E$124,MASTER!$Y$7,PARTNER!$V$5:$V$124,">="&DATE($B$4,ROW()-16,1),PARTNER!$V$5:$V$124,"<"&DATE($B$4,ROW()-15,1))+SUMIFS(PARTNER!$I$5:$I$124,PARTNER!$E$5:$E$124,MASTER!$Y$8,PARTNER!$V$5:$V$124,">="&DATE($B$4,ROW()-16,1),PARTNER!$V$5:$V$124,"<"&DATE($B$4,ROW()-15,1))) | K26: =IF(ROW()-16>MASTER!$AF$15,"",SUMIFS(PARTNER!$I$5:$I$124,PARTNER!$E$5:$E$124,MASTER!$Y$9,PARTNER!$V$5:$V$124,">="&DATE($B$4,ROW()-16,1),PARTNER!$V$5:$V$124,"<"&DATE($B$4,ROW()-15,1))) | L26: {=IF(ROW()-16>MASTER!$AF$15,"",INDEX(ARUS_KAS!$B$24:$M$24,1,ROW()-16)+INDEX(ARUS_KAS!$B$26:$M$26,1,ROW()-16)+INDEX(ARUS_KAS!$B$28:$M$28,1,ROW()-16))} | M26: {=IF(ROW()-16>MASTER!$AF$15,"",F26+INDEX(ARUS_KAS!$B$8:$M$8,1,ROW()-16)+INDEX(ARUS_KAS!$B$9:$M$9,1,ROW()-16)-INDEX(ARUS_KAS!$B$12:$M$12,1,ROW()-16)-INDEX(ARUS_KAS!$B$13:$M$13,1,ROW()-16)-INDEX(ARUS_KAS!$B$14:$M$14,1,ROW()-16)-INDEX(ARUS_KAS!$B$15:$M$15,1,ROW()-16)+INDEX(ARUS_KAS!$B$24:$M$24,1,ROW()-16)-INDEX(ARUS_KAS!$B$25:$M$25,1,ROW()-16)+INDEX(ARUS_KAS!$B$26:$M$26,1,ROW()-16)+INDEX(ARUS_KAS!$B$28:$M$28,1,ROW()-16))} | N26: =IF(ROW()-16>MASTER!$AF$15,"",ABS(F26+G26-H26-I26-J26-K26+L26-M26))
A27: Nov | B27: =IF(ROW()-16>MASTER!$AF$15,"",SUMIFS(PEMASUKAN!$H$5:$H$204,PEMASUKAN!$C$5:$C$204,TEXT(DATE($B$4,ROW()-16,1),"yyyy-mm"),PEMASUKAN!$M$5:$M$204,"Pendapatan Operasional")) | C27: =IF(ROW()-16>MASTER!$AF$15,"",SUMIFS(PENGELUARAN!$K$5:$K$204,PENGELUARAN!$C$5:$C$204,TEXT(DATE($B$4,ROW()-16,1),"yyyy-mm"),PENGELUARAN!$L$5:$L$204,"Kantor")+SUMIFS(GAJI!$Q$5:$Q$124,GAJI!$B$5:$B$124,">="&DATE($B$4,ROW()-16,1),GAJI!$B$5:$B$124,"<"&DATE($B$4,ROW()-15,1))) | D27: =IF(ROW()-16>MASTER!$AF$15,"",B27-C27) | E27: =IF(ROW()-16>MASTER!$AF$15,"",SUM($D$17:D27)) | F27: =IF(ROW()-16>MASTER!$AF$15,"",IF(ROW()=17,SUMIFS(KAS_BANK!$B$5:$B$10,KAS_BANK!$A$5:$A$10,"<>Bank Dana Klien")+MAX(-KAS_BANK!$B$7,0)+MAX(-KAS_BANK!$B$8,0)+MAX(-KAS_BANK!$B$9,0),M26)) | G27: =IF(ROW()-16>MASTER!$AF$15,"",SUMIFS(PEMASUKAN!$J$5:$J$204,PEMASUKAN!$C$5:$C$204,TEXT(DATE($B$4,ROW()-16,1),"yyyy-mm"),PEMASUKAN!$M$5:$M$204,"Pendapatan Operasional")+SUMIFS(PEMASUKAN!$J$5:$J$204,PEMASUKAN!$C$5:$C$204,TEXT(DATE($B$4,ROW()-16,1),"yyyy-mm"),PEMASUKAN!$M$5:$M$204,"Penggantian Biaya")) | H27: =IF(ROW()-16>MASTER!$AF$15,"",SUMIFS(PENGELUARAN!$K$5:$K$204,PENGELUARAN!$C$5:$C$204,TEXT(DATE($B$4,ROW()-16,1),"yyyy-mm"),PENGELUARAN!$I$5:$I$204,"<>",PENGELUARAN!$I$5:$I$204,"<>Bank Dana Klien")+SUMIFS(GAJI!$P$5:$P$124,GAJI!$S$5:$S$124,">="&DATE($B$4,ROW()-16,1),GAJI!$S$5:$S$124,"<"&DATE($B$4,ROW()-15,1),GAJI!$R$5:$R$124,"Dibayar")+SUMIFS(KEWAJIBAN!$F$5:$F$124,KEWAJIBAN!$I$5:$I$124,">="&DATE($B$4,ROW()-16,1),KEWAJIBAN!$I$5:$I$124,"<"&DATE($B$4,ROW()-15,1))) | I27: =IF(ROW()-16>MASTER!$AF$15,"",SUMIFS(REIMBURSE!$J$5:$J$124,REIMBURSE!$N$5:$N$124,">="&DATE($B$4,ROW()-16,1),REIMBURSE!$N$5:$N$124,"<"&DATE($B$4,ROW()-15,1))) | J27: =IF(ROW()-16>MASTER!$AF$15,"",SUMIFS(PARTNER!$I$5:$I$124,PARTNER!$E$5:$E$124,MASTER!$Y$7,PARTNER!$V$5:$V$124,">="&DATE($B$4,ROW()-16,1),PARTNER!$V$5:$V$124,"<"&DATE($B$4,ROW()-15,1))+SUMIFS(PARTNER!$I$5:$I$124,PARTNER!$E$5:$E$124,MASTER!$Y$8,PARTNER!$V$5:$V$124,">="&DATE($B$4,ROW()-16,1),PARTNER!$V$5:$V$124,"<"&DATE($B$4,ROW()-15,1))) | K27: =IF(ROW()-16>MASTER!$AF$15,"",SUMIFS(PARTNER!$I$5:$I$124,PARTNER!$E$5:$E$124,MASTER!$Y$9,PARTNER!$V$5:$V$124,">="&DATE($B$4,ROW()-16,1),PARTNER!$V$5:$V$124,"<"&DATE($B$4,ROW()-15,1))) | L27: {=IF(ROW()-16>MASTER!$AF$15,"",INDEX(ARUS_KAS!$B$24:$M$24,1,ROW()-16)+INDEX(ARUS_KAS!$B$26:$M$26,1,ROW()-16)+INDEX(ARUS_KAS!$B$28:$M$28,1,ROW()-16))} | M27: {=IF(ROW()-16>MASTER!$AF$15,"",F27+INDEX(ARUS_KAS!$B$8:$M$8,1,ROW()-16)+INDEX(ARUS_KAS!$B$9:$M$9,1,ROW()-16)-INDEX(ARUS_KAS!$B$12:$M$12,1,ROW()-16)-INDEX(ARUS_KAS!$B$13:$M$13,1,ROW()-16)-INDEX(ARUS_KAS!$B$14:$M$14,1,ROW()-16)-INDEX(ARUS_KAS!$B$15:$M$15,1,ROW()-16)+INDEX(ARUS_KAS!$B$24:$M$24,1,ROW()-16)-INDEX(ARUS_KAS!$B$25:$M$25,1,ROW()-16)+INDEX(ARUS_KAS!$B$26:$M$26,1,ROW()-16)+INDEX(ARUS_KAS!$B$28:$M$28,1,ROW()-16))} | N27: =IF(ROW()-16>MASTER!$AF$15,"",ABS(F27+G27-H27-I27-J27-K27+L27-M27))
A28: Des | B28: =IF(ROW()-16>MASTER!$AF$15,"",SUMIFS(PEMASUKAN!$H$5:$H$204,PEMASUKAN!$C$5:$C$204,TEXT(DATE($B$4,ROW()-16,1),"yyyy-mm"),PEMASUKAN!$M$5:$M$204,"Pendapatan Operasional")) | C28: =IF(ROW()-16>MASTER!$AF$15,"",SUMIFS(PENGELUARAN!$K$5:$K$204,PENGELUARAN!$C$5:$C$204,TEXT(DATE($B$4,ROW()-16,1),"yyyy-mm"),PENGELUARAN!$L$5:$L$204,"Kantor")+SUMIFS(GAJI!$Q$5:$Q$124,GAJI!$B$5:$B$124,">="&DATE($B$4,ROW()-16,1),GAJI!$B$5:$B$124,"<"&DATE($B$4,ROW()-15,1))) | D28: =IF(ROW()-16>MASTER!$AF$15,"",B28-C28) | E28: =IF(ROW()-16>MASTER!$AF$15,"",SUM($D$17:D28)) | F28: =IF(ROW()-16>MASTER!$AF$15,"",IF(ROW()=17,SUMIFS(KAS_BANK!$B$5:$B$10,KAS_BANK!$A$5:$A$10,"<>Bank Dana Klien")+MAX(-KAS_BANK!$B$7,0)+MAX(-KAS_BANK!$B$8,0)+MAX(-KAS_BANK!$B$9,0),M27)) | G28: =IF(ROW()-16>MASTER!$AF$15,"",SUMIFS(PEMASUKAN!$J$5:$J$204,PEMASUKAN!$C$5:$C$204,TEXT(DATE($B$4,ROW()-16,1),"yyyy-mm"),PEMASUKAN!$M$5:$M$204,"Pendapatan Operasional")+SUMIFS(PEMASUKAN!$J$5:$J$204,PEMASUKAN!$C$5:$C$204,TEXT(DATE($B$4,ROW()-16,1),"yyyy-mm"),PEMASUKAN!$M$5:$M$204,"Penggantian Biaya")) | H28: =IF(ROW()-16>MASTER!$AF$15,"",SUMIFS(PENGELUARAN!$K$5:$K$204,PENGELUARAN!$C$5:$C$204,TEXT(DATE($B$4,ROW()-16,1),"yyyy-mm"),PENGELUARAN!$I$5:$I$204,"<>",PENGELUARAN!$I$5:$I$204,"<>Bank Dana Klien")+SUMIFS(GAJI!$P$5:$P$124,GAJI!$S$5:$S$124,">="&DATE($B$4,ROW()-16,1),GAJI!$S$5:$S$124,"<"&DATE($B$4,ROW()-15,1),GAJI!$R$5:$R$124,"Dibayar")+SUMIFS(KEWAJIBAN!$F$5:$F$124,KEWAJIBAN!$I$5:$I$124,">="&DATE($B$4,ROW()-16,1),KEWAJIBAN!$I$5:$I$124,"<"&DATE($B$4,ROW()-15,1))) | I28: =IF(ROW()-16>MASTER!$AF$15,"",SUMIFS(REIMBURSE!$J$5:$J$124,REIMBURSE!$N$5:$N$124,">="&DATE($B$4,ROW()-16,1),REIMBURSE!$N$5:$N$124,"<"&DATE($B$4,ROW()-15,1))) | J28: =IF(ROW()-16>MASTER!$AF$15,"",SUMIFS(PARTNER!$I$5:$I$124,PARTNER!$E$5:$E$124,MASTER!$Y$7,PARTNER!$V$5:$V$124,">="&DATE($B$4,ROW()-16,1),PARTNER!$V$5:$V$124,"<"&DATE($B$4,ROW()-15,1))+SUMIFS(PARTNER!$I$5:$I$124,PARTNER!$E$5:$E$124,MASTER!$Y$8,PARTNER!$V$5:$V$124,">="&DATE($B$4,ROW()-16,1),PARTNER!$V$5:$V$124,"<"&DATE($B$4,ROW()-15,1))) | K28: =IF(ROW()-16>MASTER!$AF$15,"",SUMIFS(PARTNER!$I$5:$I$124,PARTNER!$E$5:$E$124,MASTER!$Y$9,PARTNER!$V$5:$V$124,">="&DATE($B$4,ROW()-16,1),PARTNER!$V$5:$V$124,"<"&DATE($B$4,ROW()-15,1))) | L28: {=IF(ROW()-16>MASTER!$AF$15,"",INDEX(ARUS_KAS!$B$24:$M$24,1,ROW()-16)+INDEX(ARUS_KAS!$B$26:$M$26,1,ROW()-16)+INDEX(ARUS_KAS!$B$28:$M$28,1,ROW()-16))} | M28: {=IF(ROW()-16>MASTER!$AF$15,"",F28+INDEX(ARUS_KAS!$B$8:$M$8,1,ROW()-16)+INDEX(ARUS_KAS!$B$9:$M$9,1,ROW()-16)-INDEX(ARUS_KAS!$B$12:$M$12,1,ROW()-16)-INDEX(ARUS_KAS!$B$13:$M$13,1,ROW()-16)-INDEX(ARUS_KAS!$B$14:$M$14,1,ROW()-16)-INDEX(ARUS_KAS!$B$15:$M$15,1,ROW()-16)+INDEX(ARUS_KAS!$B$24:$M$24,1,ROW()-16)-INDEX(ARUS_KAS!$B$25:$M$25,1,ROW()-16)+INDEX(ARUS_KAS!$B$26:$M$26,1,ROW()-16)+INDEX(ARUS_KAS!$B$28:$M$28,1,ROW()-16))} | N28: =IF(ROW()-16>MASTER!$AF$15,"",ABS(F28+G28-H28-I28-J28-K28+L28-M28))
A29: TOTAL / AKHIR | B29: =SUM(B17:B28) -> 16000000 | C29: =SUM(C17:C28) -> 8095908 | D29: =SUM(D17:D28) -> 7904092 | E29: {=IFERROR(INDEX(E17:E28,MASTER!$AF$15),0)} -> 7904092 | F29: {=IFERROR(INDEX(F17:F28,MASTER!$AF$15),"")} -> 4609400 | G29: =SUM(G17:G28) -> 16000000 | H29: =SUM(H17:H28) -> 5095908 | I29: =SUM(I17:I28) -> 0 | J29: =SUM(J17:J28) -> 9000000 | K29: =SUM(K17:K28) -> 0 | L29: =SUM(L17:L28) -> 1000000 | M29: {=IFERROR(INDEX(M17:M28,MASTER!$AF$15),0)} -> 2904092 | N29: =SUM(N17:N28) -> 0
A31: Kas awal berasal dari saldo bulan sebelumnya dan BUKAN pendapatan. Pembagian laba / prive mengurangi kas serta ekuitas. Pengembalian talangan mengurangi kas serta utang partner. Pendanaan / mutasi lain mencakup modal, pinjaman, talangan baru, dan perpindahan dana. | B31: Kas awal berasal dari saldo bulan sebelumnya dan BUKAN pendapatan. Pembagian laba / prive mengurangi kas serta ekuitas. Pengembalian talangan mengurangi kas serta utang partner. Pendanaan / mutasi lain mencakup modal, pinjaman, talangan baru, dan perpindahan dana. | C31: Kas awal berasal dari saldo bulan sebelumnya dan BUKAN pendapatan. Pembagian laba / prive mengurangi kas serta ekuitas. Pengembalian talangan mengurangi kas serta utang partner. Pendanaan / mutasi lain mencakup modal, pinjaman, talangan baru, dan perpindahan dana. | D31: Kas awal berasal dari saldo bulan sebelumnya dan BUKAN pendapatan. Pembagian laba / prive mengurangi kas serta ekuitas. Pengembalian talangan mengurangi kas serta utang partner. Pendanaan / mutasi lain mencakup modal, pinjaman, talangan baru, dan perpindahan dana. | E31: Kas awal berasal dari saldo bulan sebelumnya dan BUKAN pendapatan. Pembagian laba / prive mengurangi kas serta ekuitas. Pengembalian talangan mengurangi kas serta utang partner. Pendanaan / mutasi lain mencakup modal, pinjaman, talangan baru, dan perpindahan dana. | F31: Kas awal berasal dari saldo bulan sebelumnya dan BUKAN pendapatan. Pembagian laba / prive mengurangi kas serta ekuitas. Pengembalian talangan mengurangi kas serta utang partner. Pendanaan / mutasi lain mencakup modal, pinjaman, talangan baru, dan perpindahan dana. | G31: Kas awal berasal dari saldo bulan sebelumnya dan BUKAN pendapatan. Pembagian laba / prive mengurangi kas serta ekuitas. Pengembalian talangan mengurangi kas serta utang partner. Pendanaan / mutasi lain mencakup modal, pinjaman, talangan baru, dan perpindahan dana. | H31: Kas awal berasal dari saldo bulan sebelumnya dan BUKAN pendapatan. Pembagian laba / prive mengurangi kas serta ekuitas. Pengembalian talangan mengurangi kas serta utang partner. Pendanaan / mutasi lain mencakup modal, pinjaman, talangan baru, dan perpindahan dana. | I31: Kas awal berasal dari saldo bulan sebelumnya dan BUKAN pendapatan. Pembagian laba / prive mengurangi kas serta ekuitas. Pengembalian talangan mengurangi kas serta utang partner. Pendanaan / mutasi lain mencakup modal, pinjaman, talangan baru, dan perpindahan dana. | J31: Kas awal berasal dari saldo bulan sebelumnya dan BUKAN pendapatan. Pembagian laba / prive mengurangi kas serta ekuitas. Pengembalian talangan mengurangi kas serta utang partner. Pendanaan / mutasi lain mencakup modal, pinjaman, talangan baru, dan perpindahan dana. | K31: Kas awal berasal dari saldo bulan sebelumnya dan BUKAN pendapatan. Pembagian laba / prive mengurangi kas serta ekuitas. Pengembalian talangan mengurangi kas serta utang partner. Pendanaan / mutasi lain mencakup modal, pinjaman, talangan baru, dan perpindahan dana. | L31: Kas awal berasal dari saldo bulan sebelumnya dan BUKAN pendapatan. Pembagian laba / prive mengurangi kas serta ekuitas. Pengembalian talangan mengurangi kas serta utang partner. Pendanaan / mutasi lain mencakup modal, pinjaman, talangan baru, dan perpindahan dana. | M31: Kas awal berasal dari saldo bulan sebelumnya dan BUKAN pendapatan. Pembagian laba / prive mengurangi kas serta ekuitas. Pengembalian talangan mengurangi kas serta utang partner. Pendanaan / mutasi lain mencakup modal, pinjaman, talangan baru, dan perpindahan dana. | N31: Kas awal berasal dari saldo bulan sebelumnya dan BUKAN pendapatan. Pembagian laba / prive mengurangi kas serta ekuitas. Pengembalian talangan mengurangi kas serta utang partner. Pendanaan / mutasi lain mencakup modal, pinjaman, talangan baru, dan perpindahan dana.
A33: RINCIAN ARUS KAS BULAN YANG DIPILIH | B33: RINCIAN ARUS KAS BULAN YANG DIPILIH | C33: RINCIAN ARUS KAS BULAN YANG DIPILIH | D33: RINCIAN ARUS KAS BULAN YANG DIPILIH | E33: RINCIAN ARUS KAS BULAN YANG DIPILIH | F33: RINCIAN ARUS KAS BULAN YANG DIPILIH | G33: RINCIAN ARUS KAS BULAN YANG DIPILIH | H33: LABA, EKUITAS, DAN KONTROL BULAN TERPILIH | I33: LABA, EKUITAS, DAN KONTROL BULAN TERPILIH | J33: LABA, EKUITAS, DAN KONTROL BULAN TERPILIH | K33: LABA, EKUITAS, DAN KONTROL BULAN TERPILIH | L33: LABA, EKUITAS, DAN KONTROL BULAN TERPILIH | M33: LABA, EKUITAS, DAN KONTROL BULAN TERPILIH | N33: LABA, EKUITAS, DAN KONTROL BULAN TERPILIH
A35: Saldo awal dari bulan sebelumnya | B35: Saldo awal dari bulan sebelumnya | C35: Saldo awal dari bulan sebelumnya | D35: Saldo awal dari bulan sebelumnya | E35: =INDEX($F$17:$F$28,MASTER!$AF$15) -> 4609400 | H35: Laba / rugi bulan berjalan | I35: Laba / rugi bulan berjalan | J35: Laba / rugi bulan berjalan | K35: Laba / rugi bulan berjalan | L35: =INDEX($D$17:$D$28,MASTER!$AF$15) -> -4705308
A36: (+) Kas masuk operasional | B36: (+) Kas masuk operasional | C36: (+) Kas masuk operasional | D36: (+) Kas masuk operasional | E36: =INDEX($G$17:$G$28,MASTER!$AF$15) -> 0 | H36: Laba usaha kumulatif | I36: Laba usaha kumulatif | J36: Laba usaha kumulatif | K36: Laba usaha kumulatif | L36: =INDEX($E$17:$E$28,MASTER!$AF$15) -> 7904092
A37: (-) Biaya, gaji, dan kewajiban | B37: (-) Biaya, gaji, dan kewajiban | C37: (-) Biaya, gaji, dan kewajiban | D37: (-) Biaya, gaji, dan kewajiban | E37: =INDEX($H$17:$H$28,MASTER!$AF$15) -> 1705308 | H37: Pembagian partner bulan ini | I37: Pembagian partner bulan ini | J37: Pembagian partner bulan ini | K37: Pembagian partner bulan ini | L37: =INDEX($J$17:$J$28,MASTER!$AF$15) -> 0
A38: (-) Reimburse dibayarkan | B38: (-) Reimburse dibayarkan | C38: (-) Reimburse dibayarkan | D38: (-) Reimburse dibayarkan | E38: =INDEX($I$17:$I$28,MASTER!$AF$15) -> 0 | H38: Utang / talangan partner berjalan | I38: Utang / talangan partner berjalan | J38: Utang / talangan partner berjalan | K38: Utang / talangan partner berjalan | L38: =TALANGAN_PARTNER!I9 -> 1000000
A39: (-) Pembagian partner / prive | B39: (-) Pembagian partner / prive | C39: (-) Pembagian partner / prive | D39: (-) Pembagian partner / prive | E39: =INDEX($J$17:$J$28,MASTER!$AF$15) -> 0 | H39: Ekuitas setelah pembagian | I39: Ekuitas setelah pembagian | J39: Ekuitas setelah pembagian | K39: Ekuitas setelah pembagian | L39: =EKUITAS!N8 -> -9000000
A40: (-) Pengembalian talangan partner | B40: (-) Pengembalian talangan partner | C40: (-) Pengembalian talangan partner | D40: (-) Pengembalian talangan partner | E40: =INDEX($K$17:$K$28,MASTER!$AF$15) -> 0 | H40: Piutang klien belum dibayar | I40: Piutang klien belum dibayar | J40: Piutang klien belum dibayar | K40: Piutang klien belum dibayar | L40: =SUM(INVOICE_PIUTANG!$L$5:$L$151) -> 33500000
A41: (+/-) Pendanaan dan mutasi lain | B41: (+/-) Pendanaan dan mutasi lain | C41: (+/-) Pendanaan dan mutasi lain | D41: (+/-) Pendanaan dan mutasi lain | E41: =INDEX($L$17:$L$28,MASTER!$AF$15) -> 0 | H41: Selisih jembatan kas bulan ini | I41: Selisih jembatan kas bulan ini | J41: Selisih jembatan kas bulan ini | K41: Selisih jembatan kas bulan ini | L41: =INDEX($N$17:$N$28,MASTER!$AF$15) -> 0
A42: SALDO KAS AKHIR BULAN | B42: SALDO KAS AKHIR BULAN | C42: SALDO KAS AKHIR BULAN | D42: SALDO KAS AKHIR BULAN | E42: =INDEX($M$17:$M$28,MASTER!$AF$15) -> 2904092 | H42: STATUS MODEL KEUANGAN | I42: STATUS MODEL KEUANGAN | J42: STATUS MODEL KEUANGAN | K42: STATUS MODEL KEUANGAN | L42: =KONTROL!A68 -> PERIKSA — ADA TEMUAN KRITIS / TINGGI
A44: RINGKASAN PARTNER — PEMBAGIAN LABA, REIMBURSE, DAN TALANGAN | B44: RINGKASAN PARTNER — PEMBAGIAN LABA, REIMBURSE, DAN TALANGAN | C44: RINGKASAN PARTNER — PEMBAGIAN LABA, REIMBURSE, DAN TALANGAN | D44: RINGKASAN PARTNER — PEMBAGIAN LABA, REIMBURSE, DAN TALANGAN | E44: RINGKASAN PARTNER — PEMBAGIAN LABA, REIMBURSE, DAN TALANGAN | F44: RINGKASAN PARTNER — PEMBAGIAN LABA, REIMBURSE, DAN TALANGAN | G44: RINGKASAN PARTNER — PEMBAGIAN LABA, REIMBURSE, DAN TALANGAN | H44: RINGKASAN PARTNER — PEMBAGIAN LABA, REIMBURSE, DAN TALANGAN | I44: RINGKASAN PARTNER — PEMBAGIAN LABA, REIMBURSE, DAN TALANGAN | J44: RINGKASAN PARTNER — PEMBAGIAN LABA, REIMBURSE, DAN TALANGAN | K44: RINGKASAN PARTNER — PEMBAGIAN LABA, REIMBURSE, DAN TALANGAN | L44: RINGKASAN PARTNER — PEMBAGIAN LABA, REIMBURSE, DAN TALANGAN | M44: RINGKASAN PARTNER — PEMBAGIAN LABA, REIMBURSE, DAN TALANGAN | N44: RINGKASAN PARTNER — PEMBAGIAN LABA, REIMBURSE, DAN TALANGAN
A45: Partner | B45: Partner | C45: Alokasi Hak / Laba | D45: Alokasi Hak / Laba | E45: Prive / Bagi Hasil | F45: Prive / Bagi Hasil | G45: Pengembalian Talangan | H45: Pengembalian Talangan | I45: Reimburse Dibayar | J45: Reimburse Dibayar | K45: Utang Talangan Tersisa | L45: Utang Talangan Tersisa | M45: Saldo Hak Partner | N45: Saldo Hak Partner
A46: =MASTER!A5 -> Fajar Roni | C46: =SUMIFS(PARTNER!$H$5:$H$124,PARTNER!$D$5:$D$124,$A46,PARTNER!$E$5:$E$124,MASTER!$Y$6) -> 0 | E46: =SUMIFS(PARTNER!$I$5:$I$124,PARTNER!$D$5:$D$124,$A46,PARTNER!$E$5:$E$124,MASTER!$Y$7)+SUMIFS(PARTNER!$I$5:$I$124,PARTNER!$D$5:$D$124,$A46,PARTNER!$E$5:$E$124,MASTER!$Y$8) -> 9000000 | G46: =SUMIFS(PARTNER!$I$5:$I$124,PARTNER!$D$5:$D$124,$A46,PARTNER!$E$5:$E$124,MASTER!$Y$9) -> 0 | I46: =SUMIFS(REIMBURSE!$J$5:$J$124,REIMBURSE!$C$5:$C$124,$A46) -> 0 | K46: =SUMIFS(TALANGAN_PARTNER!$I$6:$I$8,TALANGAN_PARTNER!$A$6:$A$8,$A46) -> 1000000 | M46: =SUMIFS(PARTNER!$H$5:$H$124,PARTNER!$D$5:$D$124,$A46)-SUMIFS(PARTNER!$I$5:$I$124,PARTNER!$D$5:$D$124,$A46)+SUMIFS(PARTNER!$I$5:$I$124,PARTNER!$D$5:$D$124,$A46,PARTNER!$E$5:$E$124,MASTER!$Y$9) -> 0
A47: =MASTER!A6 -> Reza Evaldo Kusumah | C47: =SUMIFS(PARTNER!$H$5:$H$124,PARTNER!$D$5:$D$124,$A47,PARTNER!$E$5:$E$124,MASTER!$Y$6) -> 0 | E47: =SUMIFS(PARTNER!$I$5:$I$124,PARTNER!$D$5:$D$124,$A47,PARTNER!$E$5:$E$124,MASTER!$Y$7)+SUMIFS(PARTNER!$I$5:$I$124,PARTNER!$D$5:$D$124,$A47,PARTNER!$E$5:$E$124,MASTER!$Y$8) -> 0 | G47: =SUMIFS(PARTNER!$I$5:$I$124,PARTNER!$D$5:$D$124,$A47,PARTNER!$E$5:$E$124,MASTER!$Y$9) -> 0 | I47: =SUMIFS(REIMBURSE!$J$5:$J$124,REIMBURSE!$C$5:$C$124,$A47) -> 0 | K47: =SUMIFS(TALANGAN_PARTNER!$I$6:$I$8,TALANGAN_PARTNER!$A$6:$A$8,$A47) -> 0 | M47: =SUMIFS(PARTNER!$H$5:$H$124,PARTNER!$D$5:$D$124,$A47)-SUMIFS(PARTNER!$I$5:$I$124,PARTNER!$D$5:$D$124,$A47)+SUMIFS(PARTNER!$I$5:$I$124,PARTNER!$D$5:$D$124,$A47,PARTNER!$E$5:$E$124,MASTER!$Y$9) -> 0
A48: =MASTER!A7 -> Anggara Putra | C48: =SUMIFS(PARTNER!$H$5:$H$124,PARTNER!$D$5:$D$124,$A48,PARTNER!$E$5:$E$124,MASTER!$Y$6) -> 0 | E48: =SUMIFS(PARTNER!$I$5:$I$124,PARTNER!$D$5:$D$124,$A48,PARTNER!$E$5:$E$124,MASTER!$Y$7)+SUMIFS(PARTNER!$I$5:$I$124,PARTNER!$D$5:$D$124,$A48,PARTNER!$E$5:$E$124,MASTER!$Y$8) -> 0 | G48: =SUMIFS(PARTNER!$I$5:$I$124,PARTNER!$D$5:$D$124,$A48,PARTNER!$E$5:$E$124,MASTER!$Y$9) -> 0 | I48: =SUMIFS(REIMBURSE!$J$5:$J$124,REIMBURSE!$C$5:$C$124,$A48) -> 0 | K48: =SUMIFS(TALANGAN_PARTNER!$I$6:$I$8,TALANGAN_PARTNER!$A$6:$A$8,$A48) -> 0 | M48: =SUMIFS(PARTNER!$H$5:$H$124,PARTNER!$D$5:$D$124,$A48)-SUMIFS(PARTNER!$I$5:$I$124,PARTNER!$D$5:$D$124,$A48)+SUMIFS(PARTNER!$I$5:$I$124,PARTNER!$D$5:$D$124,$A48,PARTNER!$E$5:$E$124,MASTER!$Y$9) -> 0
A49: TOTAL PARTNER | B49: TOTAL PARTNER | C49: =SUM(C46:C48) -> 0 | E49: =SUM(E46:E48) -> 9000000 | G49: =SUM(G46:G48) -> 0 | I49: =SUM(I46:I48) -> 0 | K49: =SUM(K46:K48) -> 1000000 | M49: =SUM(M46:M48) -> 0
A51: PERINGATAN PENGENDALIAN & REKONSILIASI | B51: PERINGATAN PENGENDALIAN & REKONSILIASI | C51: PERINGATAN PENGENDALIAN & REKONSILIASI | D51: PERINGATAN PENGENDALIAN & REKONSILIASI | E51: PERINGATAN PENGENDALIAN & REKONSILIASI | F51: PERINGATAN PENGENDALIAN & REKONSILIASI | G51: PERINGATAN PENGENDALIAN & REKONSILIASI | H51: PERINGATAN PENGENDALIAN & REKONSILIASI | I51: PERINGATAN PENGENDALIAN & REKONSILIASI | J51: PERINGATAN PENGENDALIAN & REKONSILIASI | K51: PERINGATAN PENGENDALIAN & REKONSILIASI | L51: PERINGATAN PENGENDALIAN & REKONSILIASI | M51: PERINGATAN PENGENDALIAN & REKONSILIASI | N51: PERINGATAN PENGENDALIAN & REKONSILIASI
A52: Temuan kontrol kritis | B52: Temuan kontrol kritis | C52: Temuan kontrol kritis | D52: Temuan kontrol kritis | E52: Temuan kontrol kritis | F52: =SUMIFS(KONTROL!$B$5:$B$65,KONTROL!$D$5:$D$65,"Kritis") -> 7808184 | H52: Temuan kontrol prioritas tinggi | I52: Temuan kontrol prioritas tinggi | J52: Temuan kontrol prioritas tinggi | K52: Temuan kontrol prioritas tinggi | L52: Temuan kontrol prioritas tinggi | M52: =SUMIFS(KONTROL!$B$5:$B$65,KONTROL!$D$5:$D$65,"Tinggi") -> 18000003
A53: Data administratif perlu dilengkapi | B53: Data administratif perlu dilengkapi | C53: Data administratif perlu dilengkapi | D53: Data administratif perlu dilengkapi | E53: Data administratif perlu dilengkapi | F53: =SUMIFS(KONTROL!$B$5:$B$65,KONTROL!$D$5:$D$65,"Sedang") -> 8 | H53: Akun kas aktif belum direkonsiliasi | I53: Akun kas aktif belum direkonsiliasi | J53: Akun kas aktif belum direkonsiliasi | K53: Akun kas aktif belum direkonsiliasi | L53: Akun kas aktif belum direkonsiliasi | M53: =KONTROL!B36 -> 1
A54: Pembayaran tanpa tanggal lengkap | B54: Pembayaran tanpa tanggal lengkap | C54: Pembayaran tanpa tanggal lengkap | D54: Pembayaran tanpa tanggal lengkap | E54: Pembayaran tanpa tanggal lengkap | F54: =SUM(KONTROL!B58:B60) -> 0 | H54: Partner menggunakan tanggal transaksi | I54: Partner menggunakan tanggal transaksi | J54: Partner menggunakan tanggal transaksi | K54: Partner menggunakan tanggal transaksi | L54: Partner menggunakan tanggal transaksi | M54: =KONTROL!B64 -> 0
A55: Total selisih jembatan kas setahun | B55: Total selisih jembatan kas setahun | C55: Total selisih jembatan kas setahun | D55: Total selisih jembatan kas setahun | E55: Total selisih jembatan kas setahun | F55: =KONTROL!B61 -> 0 | H55: Selisih distribusi vs ekuitas | I55: Selisih distribusi vs ekuitas | J55: Selisih distribusi vs ekuitas | K55: Selisih distribusi vs ekuitas | L55: Selisih distribusi vs ekuitas | M55: =KONTROL!B65 -> 0
A57: =KONTROL!A68 -> PERIKSA — ADA TEMUAN KRITIS / TINGGI
A60: Persetujuan transaksi dan identitas penyetuju selalu diisi manual. Kolom hijau adalah rumus otomatis; kategori partner harus dibedakan antara pembagian laba / prive dan pengembalian talangan. | B60: Persetujuan transaksi dan identitas penyetuju selalu diisi manual. Kolom hijau adalah rumus otomatis; kategori partner harus dibedakan antara pembagian laba / prive dan pengembalian talangan. | C60: Persetujuan transaksi dan identitas penyetuju selalu diisi manual. Kolom hijau adalah rumus otomatis; kategori partner harus dibedakan antara pembagian laba / prive dan pengembalian talangan. | D60: Persetujuan transaksi dan identitas penyetuju selalu diisi manual. Kolom hijau adalah rumus otomatis; kategori partner harus dibedakan antara pembagian laba / prive dan pengembalian talangan. | E60: Persetujuan transaksi dan identitas penyetuju selalu diisi manual. Kolom hijau adalah rumus otomatis; kategori partner harus dibedakan antara pembagian laba / prive dan pengembalian talangan. | F60: Persetujuan transaksi dan identitas penyetuju selalu diisi manual. Kolom hijau adalah rumus otomatis; kategori partner harus dibedakan antara pembagian laba / prive dan pengembalian talangan. | G60: Persetujuan transaksi dan identitas penyetuju selalu diisi manual. Kolom hijau adalah rumus otomatis; kategori partner harus dibedakan antara pembagian laba / prive dan pengembalian talangan. | H60: Persetujuan transaksi dan identitas penyetuju selalu diisi manual. Kolom hijau adalah rumus otomatis; kategori partner harus dibedakan antara pembagian laba / prive dan pengembalian talangan. | I60: Persetujuan transaksi dan identitas penyetuju selalu diisi manual. Kolom hijau adalah rumus otomatis; kategori partner harus dibedakan antara pembagian laba / prive dan pengembalian talangan. | J60: Persetujuan transaksi dan identitas penyetuju selalu diisi manual. Kolom hijau adalah rumus otomatis; kategori partner harus dibedakan antara pembagian laba / prive dan pengembalian talangan. | K60: Persetujuan transaksi dan identitas penyetuju selalu diisi manual. Kolom hijau adalah rumus otomatis; kategori partner harus dibedakan antara pembagian laba / prive dan pengembalian talangan. | L60: Persetujuan transaksi dan identitas penyetuju selalu diisi manual. Kolom hijau adalah rumus otomatis; kategori partner harus dibedakan antara pembagian laba / prive dan pengembalian talangan. | M60: Persetujuan transaksi dan identitas penyetuju selalu diisi manual. Kolom hijau adalah rumus otomatis; kategori partner harus dibedakan antara pembagian laba / prive dan pengembalian talangan. | N60: Persetujuan transaksi dan identitas penyetuju selalu diisi manual. Kolom hijau adalah rumus otomatis; kategori partner harus dibedakan antara pembagian laba / prive dan pengembalian talangan.
A62: VISUAL KINERJA — PENDAPATAN, BEBAN, LABA, DAN KAS
A83: Grafik mengikuti Bulan Analisis; bulan setelah periode tersebut dikosongkan otomatis.

Sheet PERKARA
A1: R | P | K MASTER & PROFITABILITAS PERKARA | B1: R | P | K MASTER & PROFITABILITAS PERKARA | C1: R | P | K MASTER & PROFITABILITAS PERKARA | D1: R | P | K MASTER & PROFITABILITAS PERKARA | E1: R | P | K MASTER & PROFITABILITAS PERKARA | F1: R | P | K MASTER & PROFITABILITAS PERKARA | G1: R | P | K MASTER & PROFITABILITAS PERKARA | H1: R | P | K MASTER & PROFITABILITAS PERKARA | I1: R | P | K MASTER & PROFITABILITAS PERKARA | J1: R | P | K MASTER & PROFITABILITAS PERKARA | K1: R | P | K MASTER & PROFITABILITAS PERKARA | L1: R | P | K MASTER & PROFITABILITAS PERKARA | M1: R | P | K MASTER & PROFITABILITAS PERKARA | N1: R | P | K MASTER & PROFITABILITAS PERKARA | O1: R | P | K MASTER & PROFITABILITAS PERKARA | P1: R | P | K MASTER & PROFITABILITAS PERKARA | Q1: R | P | K MASTER & PROFITABILITAS PERKARA | R1: R | P | K MASTER & PROFITABILITAS PERKARA
A2: R | P | K MASTER & PROFITABILITAS PERKARA | B2: R | P | K MASTER & PROFITABILITAS PERKARA | C2: R | P | K MASTER & PROFITABILITAS PERKARA | D2: R | P | K MASTER & PROFITABILITAS PERKARA | E2: R | P | K MASTER & PROFITABILITAS PERKARA | F2: R | P | K MASTER & PROFITABILITAS PERKARA | G2: R | P | K MASTER & PROFITABILITAS PERKARA | H2: R | P | K MASTER & PROFITABILITAS PERKARA | I2: R | P | K MASTER & PROFITABILITAS PERKARA | J2: R | P | K MASTER & PROFITABILITAS PERKARA | K2: R | P | K MASTER & PROFITABILITAS PERKARA | L2: R | P | K MASTER & PROFITABILITAS PERKARA | M2: R | P | K MASTER & PROFITABILITAS PERKARA | N2: R | P | K MASTER & PROFITABILITAS PERKARA | O2: R | P | K MASTER & PROFITABILITAS PERKARA | P2: R | P | K MASTER & PROFITABILITAS PERKARA | Q2: R | P | K MASTER & PROFITABILITAS PERKARA | R2: R | P | K MASTER & PROFITABILITAS PERKARA
A3: MASTER PERKARA: isi ID/kode perkara dan nama klien satu kali; pilih ID yang sama pada pemasukan, pengeluaran, reimburse, invoice, dana klien, dan partner. | B3: MASTER PERKARA: isi ID/kode perkara dan nama klien satu kali; pilih ID yang sama pada pemasukan, pengeluaran, reimburse, invoice, dana klien, dan partner. | C3: MASTER PERKARA: isi ID/kode perkara dan nama klien satu kali; pilih ID yang sama pada pemasukan, pengeluaran, reimburse, invoice, dana klien, dan partner. | D3: MASTER PERKARA: isi ID/kode perkara dan nama klien satu kali; pilih ID yang sama pada pemasukan, pengeluaran, reimburse, invoice, dana klien, dan partner. | E3: MASTER PERKARA: isi ID/kode perkara dan nama klien satu kali; pilih ID yang sama pada pemasukan, pengeluaran, reimburse, invoice, dana klien, dan partner. | F3: MASTER PERKARA: isi ID/kode perkara dan nama klien satu kali; pilih ID yang sama pada pemasukan, pengeluaran, reimburse, invoice, dana klien, dan partner. | G3: MASTER PERKARA: isi ID/kode perkara dan nama klien satu kali; pilih ID yang sama pada pemasukan, pengeluaran, reimburse, invoice, dana klien, dan partner. | H3: MASTER PERKARA: isi ID/kode perkara dan nama klien satu kali; pilih ID yang sama pada pemasukan, pengeluaran, reimburse, invoice, dana klien, dan partner. | I3: MASTER PERKARA: isi ID/kode perkara dan nama klien satu kali; pilih ID yang sama pada pemasukan, pengeluaran, reimburse, invoice, dana klien, dan partner. | J3: MASTER PERKARA: isi ID/kode perkara dan nama klien satu kali; pilih ID yang sama pada pemasukan, pengeluaran, reimburse, invoice, dana klien, dan partner. | K3: MASTER PERKARA: isi ID/kode perkara dan nama klien satu kali; pilih ID yang sama pada pemasukan, pengeluaran, reimburse, invoice, dana klien, dan partner. | L3: MASTER PERKARA: isi ID/kode perkara dan nama klien satu kali; pilih ID yang sama pada pemasukan, pengeluaran, reimburse, invoice, dana klien, dan partner. | M3: MASTER PERKARA: isi ID/kode perkara dan nama klien satu kali; pilih ID yang sama pada pemasukan, pengeluaran, reimburse, invoice, dana klien, dan partner. | N3: MASTER PERKARA: isi ID/kode perkara dan nama klien satu kali; pilih ID yang sama pada pemasukan, pengeluaran, reimburse, invoice, dana klien, dan partner. | O3: MASTER PERKARA: isi ID/kode perkara dan nama klien satu kali; pilih ID yang sama pada pemasukan, pengeluaran, reimburse, invoice, dana klien, dan partner. | P3: MASTER PERKARA: isi ID/kode perkara dan nama klien satu kali; pilih ID yang sama pada pemasukan, pengeluaran, reimburse, invoice, dana klien, dan partner. | Q3: MASTER PERKARA: isi ID/kode perkara dan nama klien satu kali; pilih ID yang sama pada pemasukan, pengeluaran, reimburse, invoice, dana klien, dan partner. | R3: MASTER PERKARA: isi ID/kode perkara dan nama klien satu kali; pilih ID yang sama pada pemasukan, pengeluaran, reimburse, invoice, dana klien, dan partner.
A4: Kode Perkara | B4: Nama Klien | C4: Nama / Jenis Penugasan | D4: Partner Penanggung Jawab | E4: Tanggal Mulai | F4: Status Perkara | G4: Nilai Kontrak Jasa | H4: Invoice Diterbitkan | I4: Honorarium Diterima | J4: Sisa Nilai Kontrak | K4: Biaya Beban Kantor | L4: Biaya Dibebankan Klien | M4: Reimburse dari Klien | N4: Kontribusi Perkara | O4: Margin Kontribusi | P4: Piutang Invoice | Q4: Tanggal Review | R4: Catatan | S4: Kontak Klien | T4: Alamat Penagihan | U4: Email Klien | V4: NPWP Klien | W4: Gaji Dialokasikan | X4: Laba Setelah Gaji | Y4: Sisa Kontrak Belum Ditagihkan | Z4: Status Master
A5: 001/2026 | B5: PT KKG | C5: Pendampingan Hukum Korporasi dan Penyelesaian Sengketa Internal PT Kembang Kembar Grup | D5: Fajar Roni | E5: 46232 | F5: Aktif | G5: 165000000 | H5: =IF(A5="","",SUMIFS(INVOICE_PIUTANG!$G$5:$G$151,INVOICE_PIUTANG!$D$5:$D$151,A5)) -> 49500000 | I5: =IF(A5="","",SUMIFS(PEMASUKAN!$H$5:$H$204,PEMASUKAN!$D$5:$D$204,A5,PEMASUKAN!$M$5:$M$204,"Pendapatan Operasional")) -> 16000000 | J5: =IF(A5="","",MAX(G5-I5,0)) -> 149000000 | K5: =IF(A5="","",SUMIFS(SALDO_AWAL_2026!$F$33:$F$132,SALDO_AWAL_2026!$A$33:$A$132,A5)+SUMIFS(PENGELUARAN!$K$5:$K$204,PENGELUARAN!$D$5:$D$204,A5,PENGELUARAN!$L$5:$L$204,"Kantor")) -> 8191816 | L5: =IF(A5="","",SUMIFS(PENGELUARAN!$K$5:$K$204,PENGELUARAN!$D$5:$D$204,A5,PENGELUARAN!$L$5:$L$204,"Klien")) -> 0 | M5: =IF(A5="","",SUMIFS(PEMASUKAN!$H$5:$H$204,PEMASUKAN!$D$5:$D$204,A5,PEMASUKAN!$M$5:$M$204,"Penggantian Biaya")) -> 0 | N5: =IF(A5="","",I5-K5) -> 7808184 | O5: =IF(A5="","",IF(I5=0,0,N5/I5)) -> 0.4880115 | P5: =IF(A5="","",SUMIFS(INVOICE_PIUTANG!$L$5:$L$151,INVOICE_PIUTANG!$D$5:$D$151,A5)) -> 33500000 | W5: =IF(A5="","",SUMIFS(SALDO_AWAL_2026!$G$33:$G$132,SALDO_AWAL_2026!$A$33:$A$132,A5)+SUMIFS(GAJI!$Q$5:$Q$124,GAJI!$X$5:$X$124,A5)) -> 4000000 | X5: =IF(A5="","",N5-W5) -> 3808184 | Y5: =IF(A5="","",MAX(G5-H5,0)) -> 115500000 | Z5: =IF(A5="","",IF(COUNTIF($A$5:$A$104,A5)>1,"ID PERKARA DUPLIKAT",IF(B5="","NAMA KLIEN BELUM DIISI",IF(D5="","PIC PARTNER BELUM DIISI","OK")))) -> OK
H6: =IF(A6="","",SUMIFS(INVOICE_PIUTANG!$G$5:$G$151,INVOICE_PIUTANG!$D$5:$D$151,A6)) | I6: =IF(A6="","",SUMIFS(PEMASUKAN!$H$5:$H$204,PEMASUKAN!$D$5:$D$204,A6,PEMASUKAN!$M$5:$M$204,"Pendapatan Operasional")) | J6: =IF(A6="","",MAX(G6-I6,0)) | K6: =IF(A6="","",SUMIFS(SALDO_AWAL_2026!$F$33:$F$132,SALDO_AWAL_2026!$A$33:$A$132,A6)+SUMIFS(PENGELUARAN!$K$5:$K$204,PENGELUARAN!$D$5:$D$204,A6,PENGELUARAN!$L$5:$L$204,"Kantor")) | L6: =IF(A6="","",SUMIFS(PENGELUARAN!$K$5:$K$204,PENGELUARAN!$D$5:$D$204,A6,PENGELUARAN!$L$5:$L$204,"Klien")) | M6: =IF(A6="","",SUMIFS(PEMASUKAN!$H$5:$H$204,PEMASUKAN!$D$5:$D$204,A6,PEMASUKAN!$M$5:$M$204,"Penggantian Biaya")) | N6: =IF(A6="","",I6-K6) | O6: =IF(A6="","",IF(I6=0,0,N6/I6)) | P6: =IF(A6="","",SUMIFS(INVOICE_PIUTANG!$L$5:$L$151,INVOICE_PIUTANG!$D$5:$D$151,A6)) | W6: =IF(A6="","",SUMIFS(SALDO_AWAL_2026!$G$33:$G$132,SALDO_AWAL_2026!$A$33:$A$132,A6)+SUMIFS(GAJI!$Q$5:$Q$124,GAJI!$X$5:$X$124,A6)) | X6: =IF(A6="","",N6-W6) | Y6: =IF(A6="","",MAX(G6-H6,0)) | Z6: =IF(A6="","",IF(COUNTIF($A$5:$A$104,A6)>1,"ID PERKARA DUPLIKAT",IF(B6="","NAMA KLIEN BELUM DIISI",IF(D6="","PIC PARTNER BELUM DIISI","OK"))))
H7: =IF(A7="","",SUMIFS(INVOICE_PIUTANG!$G$5:$G$151,INVOICE_PIUTANG!$D$5:$D$151,A7)) | I7: =IF(A7="","",SUMIFS(PEMASUKAN!$H$5:$H$204,PEMASUKAN!$D$5:$D$204,A7,PEMASUKAN!$M$5:$M$204,"Pendapatan Operasional")) | J7: =IF(A7="","",MAX(G7-I7,0)) | K7: =IF(A7="","",SUMIFS(SALDO_AWAL_2026!$F$33:$F$132,SALDO_AWAL_2026!$A$33:$A$132,A7)+SUMIFS(PENGELUARAN!$K$5:$K$204,PENGELUARAN!$D$5:$D$204,A7,PENGELUARAN!$L$5:$L$204,"Kantor")) | L7: =IF(A7="","",SUMIFS(PENGELUARAN!$K$5:$K$204,PENGELUARAN!$D$5:$D$204,A7,PENGELUARAN!$L$5:$L$204,"Klien")) | M7: =IF(A7="","",SUMIFS(PEMASUKAN!$H$5:$H$204,PEMASUKAN!$D$5:$D$204,A7,PEMASUKAN!$M$5:$M$204,"Penggantian Biaya")) | N7: =IF(A7="","",I7-K7) | O7: =IF(A7="","",IF(I7=0,0,N7/I7)) | P7: =IF(A7="","",SUMIFS(INVOICE_PIUTANG!$L$5:$L$151,INVOICE_PIUTANG!$D$5:$D$151,A7)) | W7: =IF(A7="","",SUMIFS(SALDO_AWAL_2026!$G$33:$G$132,SALDO_AWAL_2026!$A$33:$A$132,A7)+SUMIFS(GAJI!$Q$5:$Q$124,GAJI!$X$5:$X$124,A7)) | X7: =IF(A7="","",N7-W7) | Y7: =IF(A7="","",MAX(G7-H7,0)) | Z7: =IF(A7="","",IF(COUNTIF($A$5:$A$104,A7)>1,"ID PERKARA DUPLIKAT",IF(B7="","NAMA KLIEN BELUM DIISI",IF(D7="","PIC PARTNER BELUM DIISI","OK"))))
H8: =IF(A8="","",SUMIFS(INVOICE_PIUTANG!$G$5:$G$151,INVOICE_PIUTANG!$D$5:$D$151,A8)) | I8: =IF(A8="","",SUMIFS(PEMASUKAN!$H$5:$H$204,PEMASUKAN!$D$5:$D$204,A8,PEMASUKAN!$M$5:$M$204,"Pendapatan Operasional")) | J8: =IF(A8="","",MAX(G8-I8,0)) | K8: =IF(A8="","",SUMIFS(SALDO_AWAL_2026!$F$33:$F$132,SALDO_AWAL_2026!$A$33:$A$132,A8)+SUMIFS(PENGELUARAN!$K$5:$K$204,PENGELUARAN!$D$5:$D$204,A8,PENGELUARAN!$L$5:$L$204,"Kantor")) | L8: =IF(A8="","",SUMIFS(PENGELUARAN!$K$5:$K$204,PENGELUARAN!$D$5:$D$204,A8,PENGELUARAN!$L$5:$L$204,"Klien")) | M8: =IF(A8="","",SUMIFS(PEMASUKAN!$H$5:$H$204,PEMASUKAN!$D$5:$D$204,A8,PEMASUKAN!$M$5:$M$204,"Penggantian Biaya")) | N8: =IF(A8="","",I8-K8) | O8: =IF(A8="","",IF(I8=0,0,N8/I8)) | P8: =IF(A8="","",SUMIFS(INVOICE_PIUTANG!$L$5:$L$151,INVOICE_PIUTANG!$D$5:$D$151,A8)) | W8: =IF(A8="","",SUMIFS(SALDO_AWAL_2026!$G$33:$G$132,SALDO_AWAL_2026!$A$33:$A$132,A8)+SUMIFS(GAJI!$Q$5:$Q$124,GAJI!$X$5:$X$124,A8)) | X8: =IF(A8="","",N8-W8) | Y8: =IF(A8="","",MAX(G8-H8,0)) | Z8: =IF(A8="","",IF(COUNTIF($A$5:$A$104,A8)>1,"ID PERKARA DUPLIKAT",IF(B8="","NAMA KLIEN BELUM DIISI",IF(D8="","PIC PARTNER BELUM DIISI","OK"))))
H9: =IF(A9="","",SUMIFS(INVOICE_PIUTANG!$G$5:$G$151,INVOICE_PIUTANG!$D$5:$D$151,A9)) | I9: =IF(A9="","",SUMIFS(PEMASUKAN!$H$5:$H$204,PEMASUKAN!$D$5:$D$204,A9,PEMASUKAN!$M$5:$M$204,"Pendapatan Operasional")) | J9: =IF(A9="","",MAX(G9-I9,0)) | K9: =IF(A9="","",SUMIFS(SALDO_AWAL_2026!$F$33:$F$132,SALDO_AWAL_2026!$A$33:$A$132,A9)+SUMIFS(PENGELUARAN!$K$5:$K$204,PENGELUARAN!$D$5:$D$204,A9,PENGELUARAN!$L$5:$L$204,"Kantor")) | L9: =IF(A9="","",SUMIFS(PENGELUARAN!$K$5:$K$204,PENGELUARAN!$D$5:$D$204,A9,PENGELUARAN!$L$5:$L$204,"Klien")) | M9: =IF(A9="","",SUMIFS(PEMASUKAN!$H$5:$H$204,PEMASUKAN!$D$5:$D$204,A9,PEMASUKAN!$M$5:$M$204,"Penggantian Biaya")) | N9: =IF(A9="","",I9-K9) | O9: =IF(A9="","",IF(I9=0,0,N9/I9)) | P9: =IF(A9="","",SUMIFS(INVOICE_PIUTANG!$L$5:$L$151,INVOICE_PIUTANG!$D$5:$D$151,A9)) | W9: =IF(A9="","",SUMIFS(SALDO_AWAL_2026!$G$33:$G$132,SALDO_AWAL_2026!$A$33:$A$132,A9)+SUMIFS(GAJI!$Q$5:$Q$124,GAJI!$X$5:$X$124,A9)) | X9: =IF(A9="","",N9-W9) | Y9: =IF(A9="","",MAX(G9-H9,0)) | Z9: =IF(A9="","",IF(COUNTIF($A$5:$A$104,A9)>1,"ID PERKARA DUPLIKAT",IF(B9="","NAMA KLIEN BELUM DIISI",IF(D9="","PIC PARTNER BELUM DIISI","OK"))))
H10: =IF(A10="","",SUMIFS(INVOICE_PIUTANG!$G$5:$G$151,INVOICE_PIUTANG!$D$5:$D$151,A10)) | I10: =IF(A10="","",SUMIFS(PEMASUKAN!$H$5:$H$204,PEMASUKAN!$D$5:$D$204,A10,PEMASUKAN!$M$5:$M$204,"Pendapatan Operasional")) | J10: =IF(A10="","",MAX(G10-I10,0)) | K10: =IF(A10="","",SUMIFS(SALDO_AWAL_2026!$F$33:$F$132,SALDO_AWAL_2026!$A$33:$A$132,A10)+SUMIFS(PENGELUARAN!$K$5:$K$204,PENGELUARAN!$D$5:$D$204,A10,PENGELUARAN!$L$5:$L$204,"Kantor")) | L10: =IF(A10="","",SUMIFS(PENGELUARAN!$K$5:$K$204,PENGELUARAN!$D$5:$D$204,A10,PENGELUARAN!$L$5:$L$204,"Klien")) | M10: =IF(A10="","",SUMIFS(PEMASUKAN!$H$5:$H$204,PEMASUKAN!$D$5:$D$204,A10,PEMASUKAN!$M$5:$M$204,"Penggantian Biaya")) | N10: =IF(A10="","",I10-K10) | O10: =IF(A10="","",IF(I10=0,0,N10/I10)) | P10: =IF(A10="","",SUMIFS(INVOICE_PIUTANG!$L$5:$L$151,INVOICE_PIUTANG!$D$5:$D$151,A10)) | W10: =IF(A10="","",SUMIFS(SALDO_AWAL_2026!$G$33:$G$132,SALDO_AWAL_2026!$A$33:$A$132,A10)+SUMIFS(GAJI!$Q$5:$Q$124,GAJI!$X$5:$X$124,A10)) | X10: =IF(A10="","",N10-W10) | Y10: =IF(A10="","",MAX(G10-H10,0)) | Z10: =IF(A10="","",IF(COUNTIF($A$5:$A$104,A10)>1,"ID PERKARA DUPLIKAT",IF(B10="","NAMA KLIEN BELUM DIISI",IF(D10="","PIC PARTNER BELUM DIISI","OK"))))
H11: =IF(A11="","",SUMIFS(INVOICE_PIUTANG!$G$5:$G$151,INVOICE_PIUTANG!$D$5:$D$151,A11)) | I11: =IF(A11="","",SUMIFS(PEMASUKAN!$H$5:$H$204,PEMASUKAN!$D$5:$D$204,A11,PEMASUKAN!$M$5:$M$204,"Pendapatan Operasional")) | J11: =IF(A11="","",MAX(G11-I11,0)) | K11: =IF(A11="","",SUMIFS(SALDO_AWAL_2026!$F$33:$F$132,SALDO_AWAL_2026!$A$33:$A$132,A11)+SUMIFS(PENGELUARAN!$K$5:$K$204,PENGELUARAN!$D$5:$D$204,A11,PENGELUARAN!$L$5:$L$204,"Kantor")) | L11: =IF(A11="","",SUMIFS(PENGELUARAN!$K$5:$K$204,PENGELUARAN!$D$5:$D$204,A11,PENGELUARAN!$L$5:$L$204,"Klien")) | M11: =IF(A11="","",SUMIFS(PEMASUKAN!$H$5:$H$204,PEMASUKAN!$D$5:$D$204,A11,PEMASUKAN!$M$5:$M$204,"Penggantian Biaya")) | N11: =IF(A11="","",I11-K11) | O11: =IF(A11="","",IF(I11=0,0,N11/I11)) | P11: =IF(A11="","",SUMIFS(INVOICE_PIUTANG!$L$5:$L$151,INVOICE_PIUTANG!$D$5:$D$151,A11)) | W11: =IF(A11="","",SUMIFS(SALDO_AWAL_2026!$G$33:$G$132,SALDO_AWAL_2026!$A$33:$A$132,A11)+SUMIFS(GAJI!$Q$5:$Q$124,GAJI!$X$5:$X$124,A11)) | X11: =IF(A11="","",N11-W11) | Y11: =IF(A11="","",MAX(G11-H11,0)) | Z11: =IF(A11="","",IF(COUNTIF($A$5:$A$104,A11)>1,"ID PERKARA DUPLIKAT",IF(B11="","NAMA KLIEN BELUM DIISI",IF(D11="","PIC PARTNER BELUM DIISI","OK"))))
H12: =IF(A12="","",SUMIFS(INVOICE_PIUTANG!$G$5:$G$151,INVOICE_PIUTANG!$D$5:$D$151,A12)) | I12: =IF(A12="","",SUMIFS(PEMASUKAN!$H$5:$H$204,PEMASUKAN!$D$5:$D$204,A12,PEMASUKAN!$M$5:$M$204,"Pendapatan Operasional")) | J12: =IF(A12="","",MAX(G12-I12,0)) | K12: =IF(A12="","",SUMIFS(SALDO_AWAL_2026!$F$33:$F$132,SALDO_AWAL_2026!$A$33:$A$132,A12)+SUMIFS(PENGELUARAN!$K$5:$K$204,PENGELUARAN!$D$5:$D$204,A12,PENGELUARAN!$L$5:$L$204,"Kantor")) | L12: =IF(A12="","",SUMIFS(PENGELUARAN!$K$5:$K$204,PENGELUARAN!$D$5:$D$204,A12,PENGELUARAN!$L$5:$L$204,"Klien")) | M12: =IF(A12="","",SUMIFS(PEMASUKAN!$H$5:$H$204,PEMASUKAN!$D$5:$D$204,A12,PEMASUKAN!$M$5:$M$204,"Penggantian Biaya")) | N12: =IF(A12="","",I12-K12) | O12: =IF(A12="","",IF(I12=0,0,N12/I12)) | P12: =IF(A12="","",SUMIFS(INVOICE_PIUTANG!$L$5:$L$151,INVOICE_PIUTANG!$D$5:$D$151,A12)) | W12: =IF(A12="","",SUMIFS(SALDO_AWAL_2026!$G$33:$G$132,SALDO_AWAL_2026!$A$33:$A$132,A12)+SUMIFS(GAJI!$Q$5:$Q$124,GAJI!$X$5:$X$124,A12)) | X12: =IF(A12="","",N12-W12) | Y12: =IF(A12="","",MAX(G12-H12,0)) | Z12: =IF(A12="","",IF(COUNTIF($A$5:$A$104,A12)>1,"ID PERKARA DUPLIKAT",IF(B12="","NAMA KLIEN BELUM DIISI",IF(D12="","PIC PARTNER BELUM DIISI","OK"))))
H13: =IF(A13="","",SUMIFS(INVOICE_PIUTANG!$G$5:$G$151,INVOICE_PIUTANG!$D$5:$D$151,A13)) | I13: =IF(A13="","",SUMIFS(PEMASUKAN!$H$5:$H$204,PEMASUKAN!$D$5:$D$204,A13,PEMASUKAN!$M$5:$M$204,"Pendapatan Operasional")) | J13: =IF(A13="","",MAX(G13-I13,0)) | K13: =IF(A13="","",SUMIFS(SALDO_AWAL_2026!$F$33:$F$132,SALDO_AWAL_2026!$A$33:$A$132,A13)+SUMIFS(PENGELUARAN!$K$5:$K$204,PENGELUARAN!$D$5:$D$204,A13,PENGELUARAN!$L$5:$L$204,"Kantor")) | L13: =IF(A13="","",SUMIFS(PENGELUARAN!$K$5:$K$204,PENGELUARAN!$D$5:$D$204,A13,PENGELUARAN!$L$5:$L$204,"Klien")) | M13: =IF(A13="","",SUMIFS(PEMASUKAN!$H$5:$H$204,PEMASUKAN!$D$5:$D$204,A13,PEMASUKAN!$M$5:$M$204,"Penggantian Biaya")) | N13: =IF(A13="","",I13-K13) | O13: =IF(A13="","",IF(I13=0,0,N13/I13)) | P13: =IF(A13="","",SUMIFS(INVOICE_PIUTANG!$L$5:$L$151,INVOICE_PIUTANG!$D$5:$D$151,A13)) | W13: =IF(A13="","",SUMIFS(SALDO_AWAL_2026!$G$33:$G$132,SALDO_AWAL_2026!$A$33:$A$132,A13)+SUMIFS(GAJI!$Q$5:$Q$124,GAJI!$X$5:$X$124,A13)) | X13: =IF(A13="","",N13-W13) | Y13: =IF(A13="","",MAX(G13-H13,0)) | Z13: =IF(A13="","",IF(COUNTIF($A$5:$A$104,A13)>1,"ID PERKARA DUPLIKAT",IF(B13="","NAMA KLIEN BELUM DIISI",IF(D13="","PIC PARTNER BELUM DIISI","OK"))))
H14: =IF(A14="","",SUMIFS(INVOICE_PIUTANG!$G$5:$G$151,INVOICE_PIUTANG!$D$5:$D$151,A14)) | I14: =IF(A14="","",SUMIFS(PEMASUKAN!$H$5:$H$204,PEMASUKAN!$D$5:$D$204,A14,PEMASUKAN!$M$5:$M$204,"Pendapatan Operasional")) | J14: =IF(A14="","",MAX(G14-I14,0)) | K14: =IF(A14="","",SUMIFS(SALDO_AWAL_2026!$F$33:$F$132,SALDO_AWAL_2026!$A$33:$A$132,A14)+SUMIFS(PENGELUARAN!$K$5:$K$204,PENGELUARAN!$D$5:$D$204,A14,PENGELUARAN!$L$5:$L$204,"Kantor")) | L14: =IF(A14="","",SUMIFS(PENGELUARAN!$K$5:$K$204,PENGELUARAN!$D$5:$D$204,A14,PENGELUARAN!$L$5:$L$204,"Klien")) | M14: =IF(A14="","",SUMIFS(PEMASUKAN!$H$5:$H$204,PEMASUKAN!$D$5:$D$204,A14,PEMASUKAN!$M$5:$M$204,"Penggantian Biaya")) | N14: =IF(A14="","",I14-K14) | O14: =IF(A14="","",IF(I14=0,0,N14/I14)) | P14: =IF(A14="","",SUMIFS(INVOICE_PIUTANG!$L$5:$L$151,INVOICE_PIUTANG!$D$5:$D$151,A14)) | W14: =IF(A14="","",SUMIFS(SALDO_AWAL_2026!$G$33:$G$132,SALDO_AWAL_2026!$A$33:$A$132,A14)+SUMIFS(GAJI!$Q$5:$Q$124,GAJI!$X$5:$X$124,A14)) | X14: =IF(A14="","",N14-W14) | Y14: =IF(A14="","",MAX(G14-H14,0)) | Z14: =IF(A14="","",IF(COUNTIF($A$5:$A$104,A14)>1,"ID PERKARA DUPLIKAT",IF(B14="","NAMA KLIEN BELUM DIISI",IF(D14="","PIC PARTNER BELUM DIISI","OK"))))
H15: =IF(A15="","",SUMIFS(INVOICE_PIUTANG!$G$5:$G$151,INVOICE_PIUTANG!$D$5:$D$151,A15)) | I15: =IF(A15="","",SUMIFS(PEMASUKAN!$H$5:$H$204,PEMASUKAN!$D$5:$D$204,A15,PEMASUKAN!$M$5:$M$204,"Pendapatan Operasional")) | J15: =IF(A15="","",MAX(G15-I15,0)) | K15: =IF(A15="","",SUMIFS(SALDO_AWAL_2026!$F$33:$F$132,SALDO_AWAL_2026!$A$33:$A$132,A15)+SUMIFS(PENGELUARAN!$K$5:$K$204,PENGELUARAN!$D$5:$D$204,A15,PENGELUARAN!$L$5:$L$204,"Kantor")) | L15: =IF(A15="","",SUMIFS(PENGELUARAN!$K$5:$K$204,PENGELUARAN!$D$5:$D$204,A15,PENGELUARAN!$L$5:$L$204,"Klien")) | M15: =IF(A15="","",SUMIFS(PEMASUKAN!$H$5:$H$204,PEMASUKAN!$D$5:$D$204,A15,PEMASUKAN!$M$5:$M$204,"Penggantian Biaya")) | N15: =IF(A15="","",I15-K15) | O15: =IF(A15="","",IF(I15=0,0,N15/I15)) | P15: =IF(A15="","",SUMIFS(INVOICE_PIUTANG!$L$5:$L$151,INVOICE_PIUTANG!$D$5:$D$151,A15)) | W15: =IF(A15="","",SUMIFS(SALDO_AWAL_2026!$G$33:$G$132,SALDO_AWAL_2026!$A$33:$A$132,A15)+SUMIFS(GAJI!$Q$5:$Q$124,GAJI!$X$5:$X$124,A15)) | X15: =IF(A15="","",N15-W15) | Y15: =IF(A15="","",MAX(G15-H15,0)) | Z15: =IF(A15="","",IF(COUNTIF($A$5:$A$104,A15)>1,"ID PERKARA DUPLIKAT",IF(B15="","NAMA KLIEN BELUM DIISI",IF(D15="","PIC PARTNER BELUM DIISI","OK"))))
H16: =IF(A16="","",SUMIFS(INVOICE_PIUTANG!$G$5:$G$151,INVOICE_PIUTANG!$D$5:$D$151,A16)) | I16: =IF(A16="","",SUMIFS(PEMASUKAN!$H$5:$H$204,PEMASUKAN!$D$5:$D$204,A16,PEMASUKAN!$M$5:$M$204,"Pendapatan Operasional")) | J16: =IF(A16="","",MAX(G16-I16,0)) | K16: =IF(A16="","",SUMIFS(SALDO_AWAL_2026!$F$33:$F$132,SALDO_AWAL_2026!$A$33:$A$132,A16)+SUMIFS(PENGELUARAN!$K$5:$K$204,PENGELUARAN!$D$5:$D$204,A16,PENGELUARAN!$L$5:$L$204,"Kantor")) | L16: =IF(A16="","",SUMIFS(PENGELUARAN!$K$5:$K$204,PENGELUARAN!$D$5:$D$204,A16,PENGELUARAN!$L$5:$L$204,"Klien")) | M16: =IF(A16="","",SUMIFS(PEMASUKAN!$H$5:$H$204,PEMASUKAN!$D$5:$D$204,A16,PEMASUKAN!$M$5:$M$204,"Penggantian Biaya")) | N16: =IF(A16="","",I16-K16) | O16: =IF(A16="","",IF(I16=0,0,N16/I16)) | P16: =IF(A16="","",SUMIFS(INVOICE_PIUTANG!$L$5:$L$151,INVOICE_PIUTANG!$D$5:$D$151,A16)) | W16: =IF(A16="","",SUMIFS(SALDO_AWAL_2026!$G$33:$G$132,SALDO_AWAL_2026!$A$33:$A$132,A16)+SUMIFS(GAJI!$Q$5:$Q$124,GAJI!$X$5:$X$124,A16)) | X16: =IF(A16="","",N16-W16) | Y16: =IF(A16="","",MAX(G16-H16,0)) | Z16: =IF(A16="","",IF(COUNTIF($A$5:$A$104,A16)>1,"ID PERKARA DUPLIKAT",IF(B16="","NAMA KLIEN BELUM DIISI",IF(D16="","PIC PARTNER BELUM DIISI","OK"))))
H17: =IF(A17="","",SUMIFS(INVOICE_PIUTANG!$G$5:$G$151,INVOICE_PIUTANG!$D$5:$D$151,A17)) | I17: =IF(A17="","",SUMIFS(PEMASUKAN!$H$5:$H$204,PEMASUKAN!$D$5:$D$204,A17,PEMASUKAN!$M$5:$M$204,"Pendapatan Operasional")) | J17: =IF(A17="","",MAX(G17-I17,0)) | K17: =IF(A17="","",SUMIFS(SALDO_AWAL_2026!$F$33:$F$132,SALDO_AWAL_2026!$A$33:$A$132,A17)+SUMIFS(PENGELUARAN!$K$5:$K$204,PENGELUARAN!$D$5:$D$204,A17,PENGELUARAN!$L$5:$L$204,"Kantor")) | L17: =IF(A17="","",SUMIFS(PENGELUARAN!$K$5:$K$204,PENGELUARAN!$D$5:$D$204,A17,PENGELUARAN!$L$5:$L$204,"Klien")) | M17: =IF(A17="","",SUMIFS(PEMASUKAN!$H$5:$H$204,PEMASUKAN!$D$5:$D$204,A17,PEMASUKAN!$M$5:$M$204,"Penggantian Biaya")) | N17: =IF(A17="","",I17-K17) | O17: =IF(A17="","",IF(I17=0,0,N17/I17)) | P17: =IF(A17="","",SUMIFS(INVOICE_PIUTANG!$L$5:$L$151,INVOICE_PIUTANG!$D$5:$D$151,A17)) | W17: =IF(A17="","",SUMIFS(SALDO_AWAL_2026!$G$33:$G$132,SALDO_AWAL_2026!$A$33:$A$132,A17)+SUMIFS(GAJI!$Q$5:$Q$124,GAJI!$X$5:$X$124,A17)) | X17: =IF(A17="","",N17-W17) | Y17: =IF(A17="","",MAX(G17-H17,0)) | Z17: =IF(A17="","",IF(COUNTIF($A$5:$A$104,A17)>1,"ID PERKARA DUPLIKAT",IF(B17="","NAMA KLIEN BELUM DIISI",IF(D17="","PIC PARTNER BELUM DIISI","OK"))))
... H104: =IF(A104="","",SUMIFS(INVOICE_PIUTANG!$G$5:$G$151,INVOICE_PIUTANG!$D$5:$D$151,A104)) | I104: =IF(A104="","",SUMIFS(PEMASUKAN!$H$5:$H$204,PEMASUKAN!$D$5:$D$204,A104,PEMASUKAN!$M$5:$M$204,"Pendapatan Operasional")) | J104: =IF(A104="","",MAX(G104-I104,0)) | K104: =IF(A104="","",SUMIFS(SALDO_AWAL_2026!$F$33:$F$132,SALDO_AWAL_2026!$A$33:$A$132,A104)+SUMIFS(PENGELUARAN!$K$5:$K$204,PENGELUARAN!$D$5:$D$204,A104,PENGELUARAN!$L$5:$L$204,"Kantor")) | L104: =IF(A104="","",SUMIFS(PENGELUARAN!$K$5:$K$204,PENGELUARAN!$D$5:$D$204,A104,PENGELUARAN!$L$5:$L$204,"Klien")) | M104: =IF(A104="","",SUMIFS(PEMASUKAN!$H$5:$H$204,PEMASUKAN!$D$5:$D$204,A104,PEMASUKAN!$M$5:$M$204,"Penggantian Biaya")) | N104: =IF(A104="","",I104-K104) | O104: =IF(A104="","",IF(I104=0,0,N104/I104)) | P104: =IF(A104="","",SUMIFS(INVOICE_PIUTANG!$L$5:$L$151,INVOICE_PIUTANG!$D$5:$D$151,A104)) | W104: =IF(A104="","",SUMIFS(SALDO_AWAL_2026!$G$33:$G$132,SALDO_AWAL_2026!$A$33:$A$132,A104)+SUMIFS(GAJI!$Q$5:$Q$124,GAJI!$X$5:$X$124,A104)) | X104: =IF(A104="","",N104-W104) | Y104: =IF(A104="","",MAX(G104-H104,0)) | Z104: =IF(A104="","",IF(COUNTIF($A$5:$A$104,A104)>1,"ID PERKARA DUPLIKAT",IF(B104="","NAMA KLIEN BELUM DIISI",IF(D104="","PIC PARTNER BELUM DIISI","OK"))))

Sheet PEMASUKAN
A1: R | P | K REGISTER PEMASUKAN | B1: R | P | K REGISTER PEMASUKAN | C1: R | P | K REGISTER PEMASUKAN | D1: R | P | K REGISTER PEMASUKAN | E1: R | P | K REGISTER PEMASUKAN | F1: R | P | K REGISTER PEMASUKAN | G1: R | P | K REGISTER PEMASUKAN | H1: R | P | K REGISTER PEMASUKAN | I1: R | P | K REGISTER PEMASUKAN | J1: R | P | K REGISTER PEMASUKAN | K1: R | P | K REGISTER PEMASUKAN | L1: R | P | K REGISTER PEMASUKAN | M1: R | P | K REGISTER PEMASUKAN | N1: R | P | K REGISTER PEMASUKAN | O1: R | P | K REGISTER PEMASUKAN | P1: R | P | K REGISTER PEMASUKAN | Q1: R | P | K REGISTER PEMASUKAN
A2: R | P | K REGISTER PEMASUKAN | B2: R | P | K REGISTER PEMASUKAN | C2: R | P | K REGISTER PEMASUKAN | D2: R | P | K REGISTER PEMASUKAN | E2: R | P | K REGISTER PEMASUKAN | F2: R | P | K REGISTER PEMASUKAN | G2: R | P | K REGISTER PEMASUKAN | H2: R | P | K REGISTER PEMASUKAN | I2: R | P | K REGISTER PEMASUKAN | J2: R | P | K REGISTER PEMASUKAN | K2: R | P | K REGISTER PEMASUKAN | L2: R | P | K REGISTER PEMASUKAN | M2: R | P | K REGISTER PEMASUKAN | N2: R | P | K REGISTER PEMASUKAN | O2: R | P | K REGISTER PEMASUKAN | P2: R | P | K REGISTER PEMASUKAN | Q2: R | P | K REGISTER PEMASUKAN
A3: Tanggal, akun, dan nilai menunjukkan uang yang benar-benar diterima. Status konfirmasi serta nama pemeriksa harus dipilih manual; rumus hanya merangkum keputusan tersebut. | B3: Catat uang benar-benar diterima. Dana titipan, reimburse klien, setoran modal dan pinjaman dipisahkan otomatis dari pendapatan jasa hukum. | C3: Catat uang benar-benar diterima. Dana titipan, reimburse klien, setoran modal dan pinjaman dipisahkan otomatis dari pendapatan jasa hukum. | D3: Catat uang benar-benar diterima. Dana titipan, reimburse klien, setoran modal dan pinjaman dipisahkan otomatis dari pendapatan jasa hukum. | E3: Catat uang benar-benar diterima. Dana titipan, reimburse klien, setoran modal dan pinjaman dipisahkan otomatis dari pendapatan jasa hukum. | F3: Catat uang benar-benar diterima. Dana titipan, reimburse klien, setoran modal dan pinjaman dipisahkan otomatis dari pendapatan jasa hukum. | G3: Catat uang benar-benar diterima. Dana titipan, reimburse klien, setoran modal dan pinjaman dipisahkan otomatis dari pendapatan jasa hukum. | H3: Catat uang benar-benar diterima. Dana titipan, reimburse klien, setoran modal dan pinjaman dipisahkan otomatis dari pendapatan jasa hukum. | I3: Catat uang benar-benar diterima. Dana titipan, reimburse klien, setoran modal dan pinjaman dipisahkan otomatis dari pendapatan jasa hukum. | J3: Catat uang benar-benar diterima. Dana titipan, reimburse klien, setoran modal dan pinjaman dipisahkan otomatis dari pendapatan jasa hukum. | K3: Catat uang benar-benar diterima. Dana titipan, reimburse klien, setoran modal dan pinjaman dipisahkan otomatis dari pendapatan jasa hukum. | L3: Catat uang benar-benar diterima. Dana titipan, reimburse klien, setoran modal dan pinjaman dipisahkan otomatis dari pendapatan jasa hukum. | M3: Catat uang benar-benar diterima. Dana titipan, reimburse klien, setoran modal dan pinjaman dipisahkan otomatis dari pendapatan jasa hukum. | N3: Catat uang benar-benar diterima. Dana titipan, reimburse klien, setoran modal dan pinjaman dipisahkan otomatis dari pendapatan jasa hukum. | O3: Catat uang benar-benar diterima. Dana titipan, reimburse klien, setoran modal dan pinjaman dipisahkan otomatis dari pendapatan jasa hukum. | P3: Catat uang benar-benar diterima. Dana titipan, reimburse klien, setoran modal dan pinjaman dipisahkan otomatis dari pendapatan jasa hukum. | Q3: Catat uang benar-benar diterima. Dana titipan, reimburse klien, setoran modal dan pinjaman dipisahkan otomatis dari pendapatan jasa hukum.
A4: ID Pemasukan | B4: Tanggal Terima | C4: Periode | D4: Kode Perkara | E4: Nama Klien/Pembayar | F4: Jenis Pemasukan | G4: No. Invoice | H4: Nilai Bruto | I4: Pajak Dipotong Klien | J4: Kas Bersih Diterima | K4: Akun Penerima | L4: Metode Bayar | M4: Klasifikasi Akuntansi | N4: Bukti Pembayaran | O4: Status Bukti | P4: Dikonfirmasi Oleh (Manual) | Q4: Catatan | R4: Status Validasi | S4: Status Konfirmasi (Manual) | T4: Tanggal Konfirmasi | U4: Catatan Konfirmasi | V4: Status Otorisasi
A5: =IF(B5="","",IFERROR("INC-"&TEXT(B5,"yyyymmdd")&"-"&TEXT(ROW()-4,"000"),"TANGGAL TIDAK VALID")) -> INC-20260729-001 | B5: 46232 | C5: =IF(B5="","",IFERROR(TEXT(B5,"yyyy-mm"),"TANGGAL TIDAK VALID")) -> 2026-07 | D5: 001/2026 | E5: =IF(D5="","",IFERROR(INDEX(PERKARA!$B$5:$B$104,MATCH(D5,PERKARA!$A$5:$A$104,0)),"ID TIDAK TERDAFTAR")) -> PT KKG | F5: Honorarium | G5: RPK-INV-2026-001 | H5: 16000000 | I5: 0 | J5: =IF(B5="","",MAX(H5-I5,0)) -> 16000000 | K5: Kas Kantor | L5: Transfer | M5: =IF(F5="","",IF(F5="Reimburse dari Klien","Penggantian Biaya",IF(F5="Dana Titipan Klien","Dana Klien",IF(F5="Setoran Modal Partner","Modal Partner",IF(F5="Pinjaman","Pinjaman","Pendapatan Operasional"))))) -> Pendapatan Operasional | O5: Lengkap | P5: Fajar Roni | R5: =IF(B5="","",IF(AND(G5<>"",COUNTIF(INVOICE_PIUTANG!$A$5:$A$151,G5)=0),"INVOICE BELUM TERDAFTAR",IF(AND(D5<>"",E5="ID TIDAK TERDAFTAR"),"PERKARA TIDAK VALID",IF(K5="","AKUN BELUM DIISI",IF(AND(G5<>"",D5<>IFERROR(INDEX(INVOICE_PIUTANG!$D$5:$D$151,MATCH(G5,INVOICE_PIUTANG!$A$5:$A$151,0)),"")),"PERKARA TIDAK SESUAI INVOICE",IF(V5<>"LENGKAP","PENERIMAAN BELUM DIKONFIRMASI","OK")))))) -> OK | S5: Dikonfirmasi | T5: 46231 | V5: =IF(B5="","",IF(S5="Ditolak","DITOLAK",IF(AND(S5="Dikonfirmasi",P5<>""),"LENGKAP",IF(S5="Dikonfirmasi","NAMA PENYETUJU BELUM DIISI","MENUNGGU KONFIRMASI MANUAL")))) -> LENGKAP
A6: =IF(B6="","",IFERROR("INC-"&TEXT(B6,"yyyymmdd")&"-"&TEXT(ROW()-4,"000"),"TANGGAL TIDAK VALID")) | C6: =IF(B6="","",IFERROR(TEXT(B6,"yyyy-mm"),"TANGGAL TIDAK VALID")) | D6: =IF(G6="","",IFERROR(INDEX(INVOICE_PIUTANG!$D$5:$D$151,MATCH(G6,INVOICE_PIUTANG!$A$5:$A$151,0)),"")) | E6: =IF(D6="","",IFERROR(INDEX(PERKARA!$B$5:$B$104,MATCH(D6,PERKARA!$A$5:$A$104,0)),"ID TIDAK TERDAFTAR")) | J6: =IF(B6="","",MAX(H6-I6,0)) | M6: =IF(F6="","",IF(F6="Reimburse dari Klien","Penggantian Biaya",IF(F6="Dana Titipan Klien","Dana Klien",IF(F6="Setoran Modal Partner","Modal Partner",IF(F6="Pinjaman","Pinjaman","Pendapatan Operasional"))))) | R6: =IF(B6="","",IF(AND(G6<>"",COUNTIF(INVOICE_PIUTANG!$A$5:$A$151,G6)=0),"INVOICE BELUM TERDAFTAR",IF(AND(D6<>"",E6="ID TIDAK TERDAFTAR"),"PERKARA TIDAK VALID",IF(K6="","AKUN BELUM DIISI",IF(AND(G6<>"",D6<>IFERROR(INDEX(INVOICE_PIUTANG!$D$5:$D$151,MATCH(G6,INVOICE_PIUTANG!$A$5:$A$151,0)),"")),"PERKARA TIDAK SESUAI INVOICE",IF(V6<>"LENGKAP","PENERIMAAN BELUM DIKONFIRMASI","OK")))))) | V6: =IF(B6="","",IF(S6="Ditolak","DITOLAK",IF(AND(S6="Dikonfirmasi",P6<>""),"LENGKAP",IF(S6="Dikonfirmasi","NAMA PENYETUJU BELUM DIISI","MENUNGGU KONFIRMASI MANUAL"))))
A7: =IF(B7="","",IFERROR("INC-"&TEXT(B7,"yyyymmdd")&"-"&TEXT(ROW()-4,"000"),"TANGGAL TIDAK VALID")) | C7: =IF(B7="","",IFERROR(TEXT(B7,"yyyy-mm"),"TANGGAL TIDAK VALID")) | D7: =IF(G7="","",IFERROR(INDEX(INVOICE_PIUTANG!$D$5:$D$151,MATCH(G7,INVOICE_PIUTANG!$A$5:$A$151,0)),"")) | E7: =IF(D7="","",IFERROR(INDEX(PERKARA!$B$5:$B$104,MATCH(D7,PERKARA!$A$5:$A$104,0)),"ID TIDAK TERDAFTAR")) | J7: =IF(B7="","",MAX(H7-I7,0)) | M7: =IF(F7="","",IF(F7="Reimburse dari Klien","Penggantian Biaya",IF(F7="Dana Titipan Klien","Dana Klien",IF(F7="Setoran Modal Partner","Modal Partner",IF(F7="Pinjaman","Pinjaman","Pendapatan Operasional"))))) | R7: =IF(B7="","",IF(AND(G7<>"",COUNTIF(INVOICE_PIUTANG!$A$5:$A$151,G7)=0),"INVOICE BELUM TERDAFTAR",IF(AND(D7<>"",E7="ID TIDAK TERDAFTAR"),"PERKARA TIDAK VALID",IF(K7="","AKUN BELUM DIISI",IF(AND(G7<>"",D7<>IFERROR(INDEX(INVOICE_PIUTANG!$D$5:$D$151,MATCH(G7,INVOICE_PIUTANG!$A$5:$A$151,0)),"")),"PERKARA TIDAK SESUAI INVOICE",IF(V7<>"LENGKAP","PENERIMAAN BELUM DIKONFIRMASI","OK")))))) | V7: =IF(B7="","",IF(S7="Ditolak","DITOLAK",IF(AND(S7="Dikonfirmasi",P7<>""),"LENGKAP",IF(S7="Dikonfirmasi","NAMA PENYETUJU BELUM DIISI","MENUNGGU KONFIRMASI MANUAL"))))
A8: =IF(B8="","",IFERROR("INC-"&TEXT(B8,"yyyymmdd")&"-"&TEXT(ROW()-4,"000"),"TANGGAL TIDAK VALID")) | C8: =IF(B8="","",IFERROR(TEXT(B8,"yyyy-mm"),"TANGGAL TIDAK VALID")) | D8: =IF(G8="","",IFERROR(INDEX(INVOICE_PIUTANG!$D$5:$D$151,MATCH(G8,INVOICE_PIUTANG!$A$5:$A$151,0)),"")) | E8: =IF(D8="","",IFERROR(INDEX(PERKARA!$B$5:$B$104,MATCH(D8,PERKARA!$A$5:$A$104,0)),"ID TIDAK TERDAFTAR")) | J8: =IF(B8="","",MAX(H8-I8,0)) | M8: =IF(F8="","",IF(F8="Reimburse dari Klien","Penggantian Biaya",IF(F8="Dana Titipan Klien","Dana Klien",IF(F8="Setoran Modal Partner","Modal Partner",IF(F8="Pinjaman","Pinjaman","Pendapatan Operasional"))))) | R8: =IF(B8="","",IF(AND(G8<>"",COUNTIF(INVOICE_PIUTANG!$A$5:$A$151,G8)=0),"INVOICE BELUM TERDAFTAR",IF(AND(D8<>"",E8="ID TIDAK TERDAFTAR"),"PERKARA TIDAK VALID",IF(K8="","AKUN BELUM DIISI",IF(AND(G8<>"",D8<>IFERROR(INDEX(INVOICE_PIUTANG!$D$5:$D$151,MATCH(G8,INVOICE_PIUTANG!$A$5:$A$151,0)),"")),"PERKARA TIDAK SESUAI INVOICE",IF(V8<>"LENGKAP","PENERIMAAN BELUM DIKONFIRMASI","OK")))))) | V8: =IF(B8="","",IF(S8="Ditolak","DITOLAK",IF(AND(S8="Dikonfirmasi",P8<>""),"LENGKAP",IF(S8="Dikonfirmasi","NAMA PENYETUJU BELUM DIISI","MENUNGGU KONFIRMASI MANUAL"))))
A9: =IF(B9="","",IFERROR("INC-"&TEXT(B9,"yyyymmdd")&"-"&TEXT(ROW()-4,"000"),"TANGGAL TIDAK VALID")) | C9: =IF(B9="","",IFERROR(TEXT(B9,"yyyy-mm"),"TANGGAL TIDAK VALID")) | D9: =IF(G9="","",IFERROR(INDEX(INVOICE_PIUTANG!$D$5:$D$151,MATCH(G9,INVOICE_PIUTANG!$A$5:$A$151,0)),"")) | E9: =IF(D9="","",IFERROR(INDEX(PERKARA!$B$5:$B$104,MATCH(D9,PERKARA!$A$5:$A$104,0)),"ID TIDAK TERDAFTAR")) | J9: =IF(B9="","",MAX(H9-I9,0)) | M9: =IF(F9="","",IF(F9="Reimburse dari Klien","Penggantian Biaya",IF(F9="Dana Titipan Klien","Dana Klien",IF(F9="Setoran Modal Partner","Modal Partner",IF(F9="Pinjaman","Pinjaman","Pendapatan Operasional"))))) | R9: =IF(B9="","",IF(AND(G9<>"",COUNTIF(INVOICE_PIUTANG!$A$5:$A$151,G9)=0),"INVOICE BELUM TERDAFTAR",IF(AND(D9<>"",E9="ID TIDAK TERDAFTAR"),"PERKARA TIDAK VALID",IF(K9="","AKUN BELUM DIISI",IF(AND(G9<>"",D9<>IFERROR(INDEX(INVOICE_PIUTANG!$D$5:$D$151,MATCH(G9,INVOICE_PIUTANG!$A$5:$A$151,0)),"")),"PERKARA TIDAK SESUAI INVOICE",IF(V9<>"LENGKAP","PENERIMAAN BELUM DIKONFIRMASI","OK")))))) | V9: =IF(B9="","",IF(S9="Ditolak","DITOLAK",IF(AND(S9="Dikonfirmasi",P9<>""),"LENGKAP",IF(S9="Dikonfirmasi","NAMA PENYETUJU BELUM DIISI","MENUNGGU KONFIRMASI MANUAL"))))
A10: =IF(B10="","",IFERROR("INC-"&TEXT(B10,"yyyymmdd")&"-"&TEXT(ROW()-4,"000"),"TANGGAL TIDAK VALID")) | C10: =IF(B10="","",IFERROR(TEXT(B10,"yyyy-mm"),"TANGGAL TIDAK VALID")) | D10: =IF(G10="","",IFERROR(INDEX(INVOICE_PIUTANG!$D$5:$D$151,MATCH(G10,INVOICE_PIUTANG!$A$5:$A$151,0)),"")) | E10: =IF(D10="","",IFERROR(INDEX(PERKARA!$B$5:$B$104,MATCH(D10,PERKARA!$A$5:$A$104,0)),"ID TIDAK TERDAFTAR")) | J10: =IF(B10="","",MAX(H10-I10,0)) | M10: =IF(F10="","",IF(F10="Reimburse dari Klien","Penggantian Biaya",IF(F10="Dana Titipan Klien","Dana Klien",IF(F10="Setoran Modal Partner","Modal Partner",IF(F10="Pinjaman","Pinjaman","Pendapatan Operasional"))))) | R10: =IF(B10="","",IF(AND(G10<>"",COUNTIF(INVOICE_PIUTANG!$A$5:$A$151,G10)=0),"INVOICE BELUM TERDAFTAR",IF(AND(D10<>"",E10="ID TIDAK TERDAFTAR"),"PERKARA TIDAK VALID",IF(K10="","AKUN BELUM DIISI",IF(AND(G10<>"",D10<>IFERROR(INDEX(INVOICE_PIUTANG!$D$5:$D$151,MATCH(G10,INVOICE_PIUTANG!$A$5:$A$151,0)),"")),"PERKARA TIDAK SESUAI INVOICE",IF(V10<>"LENGKAP","PENERIMAAN BELUM DIKONFIRMASI","OK")))))) | V10: =IF(B10="","",IF(S10="Ditolak","DITOLAK",IF(AND(S10="Dikonfirmasi",P10<>""),"LENGKAP",IF(S10="Dikonfirmasi","NAMA PENYETUJU BELUM DIISI","MENUNGGU KONFIRMASI MANUAL"))))
A11: =IF(B11="","",IFERROR("INC-"&TEXT(B11,"yyyymmdd")&"-"&TEXT(ROW()-4,"000"),"TANGGAL TIDAK VALID")) | C11: =IF(B11="","",IFERROR(TEXT(B11,"yyyy-mm"),"TANGGAL TIDAK VALID")) | D11: =IF(G11="","",IFERROR(INDEX(INVOICE_PIUTANG!$D$5:$D$151,MATCH(G11,INVOICE_PIUTANG!$A$5:$A$151,0)),"")) | E11: =IF(D11="","",IFERROR(INDEX(PERKARA!$B$5:$B$104,MATCH(D11,PERKARA!$A$5:$A$104,0)),"ID TIDAK TERDAFTAR")) | J11: =IF(B11="","",MAX(H11-I11,0)) | M11: =IF(F11="","",IF(F11="Reimburse dari Klien","Penggantian Biaya",IF(F11="Dana Titipan Klien","Dana Klien",IF(F11="Setoran Modal Partner","Modal Partner",IF(F11="Pinjaman","Pinjaman","Pendapatan Operasional"))))) | R11: =IF(B11="","",IF(AND(G11<>"",COUNTIF(INVOICE_PIUTANG!$A$5:$A$151,G11)=0),"INVOICE BELUM TERDAFTAR",IF(AND(D11<>"",E11="ID TIDAK TERDAFTAR"),"PERKARA TIDAK VALID",IF(K11="","AKUN BELUM DIISI",IF(AND(G11<>"",D11<>IFERROR(INDEX(INVOICE_PIUTANG!$D$5:$D$151,MATCH(G11,INVOICE_PIUTANG!$A$5:$A$151,0)),"")),"PERKARA TIDAK SESUAI INVOICE",IF(V11<>"LENGKAP","PENERIMAAN BELUM DIKONFIRMASI","OK")))))) | V11: =IF(B11="","",IF(S11="Ditolak","DITOLAK",IF(AND(S11="Dikonfirmasi",P11<>""),"LENGKAP",IF(S11="Dikonfirmasi","NAMA PENYETUJU BELUM DIISI","MENUNGGU KONFIRMASI MANUAL"))))
A12: =IF(B12="","",IFERROR("INC-"&TEXT(B12,"yyyymmdd")&"-"&TEXT(ROW()-4,"000"),"TANGGAL TIDAK VALID")) | C12: =IF(B12="","",IFERROR(TEXT(B12,"yyyy-mm"),"TANGGAL TIDAK VALID")) | D12: =IF(G12="","",IFERROR(INDEX(INVOICE_PIUTANG!$D$5:$D$151,MATCH(G12,INVOICE_PIUTANG!$A$5:$A$151,0)),"")) | E12: =IF(D12="","",IFERROR(INDEX(PERKARA!$B$5:$B$104,MATCH(D12,PERKARA!$A$5:$A$104,0)),"ID TIDAK TERDAFTAR")) | J12: =IF(B12="","",MAX(H12-I12,0)) | M12: =IF(F12="","",IF(F12="Reimburse dari Klien","Penggantian Biaya",IF(F12="Dana Titipan Klien","Dana Klien",IF(F12="Setoran Modal Partner","Modal Partner",IF(F12="Pinjaman","Pinjaman","Pendapatan Operasional"))))) | R12: =IF(B12="","",IF(AND(G12<>"",COUNTIF(INVOICE_PIUTANG!$A$5:$A$151,G12)=0),"INVOICE BELUM TERDAFTAR",IF(AND(D12<>"",E12="ID TIDAK TERDAFTAR"),"PERKARA TIDAK VALID",IF(K12="","AKUN BELUM DIISI",IF(AND(G12<>"",D12<>IFERROR(INDEX(INVOICE_PIUTANG!$D$5:$D$151,MATCH(G12,INVOICE_PIUTANG!$A$5:$A$151,0)),"")),"PERKARA TIDAK SESUAI INVOICE",IF(V12<>"LENGKAP","PENERIMAAN BELUM DIKONFIRMASI","OK")))))) | V12: =IF(B12="","",IF(S12="Ditolak","DITOLAK",IF(AND(S12="Dikonfirmasi",P12<>""),"LENGKAP",IF(S12="Dikonfirmasi","NAMA PENYETUJU BELUM DIISI","MENUNGGU KONFIRMASI MANUAL"))))
A13: =IF(B13="","",IFERROR("INC-"&TEXT(B13,"yyyymmdd")&"-"&TEXT(ROW()-4,"000"),"TANGGAL TIDAK VALID")) | C13: =IF(B13="","",IFERROR(TEXT(B13,"yyyy-mm"),"TANGGAL TIDAK VALID")) | D13: =IF(G13="","",IFERROR(INDEX(INVOICE_PIUTANG!$D$5:$D$151,MATCH(G13,INVOICE_PIUTANG!$A$5:$A$151,0)),"")) | E13: =IF(D13="","",IFERROR(INDEX(PERKARA!$B$5:$B$104,MATCH(D13,PERKARA!$A$5:$A$104,0)),"ID TIDAK TERDAFTAR")) | J13: =IF(B13="","",MAX(H13-I13,0)) | M13: =IF(F13="","",IF(F13="Reimburse dari Klien","Penggantian Biaya",IF(F13="Dana Titipan Klien","Dana Klien",IF(F13="Setoran Modal Partner","Modal Partner",IF(F13="Pinjaman","Pinjaman","Pendapatan Operasional"))))) | R13: =IF(B13="","",IF(AND(G13<>"",COUNTIF(INVOICE_PIUTANG!$A$5:$A$151,G13)=0),"INVOICE BELUM TERDAFTAR",IF(AND(D13<>"",E13="ID TIDAK TERDAFTAR"),"PERKARA TIDAK VALID",IF(K13="","AKUN BELUM DIISI",IF(AND(G13<>"",D13<>IFERROR(INDEX(INVOICE_PIUTANG!$D$5:$D$151,MATCH(G13,INVOICE_PIUTANG!$A$5:$A$151,0)),"")),"PERKARA TIDAK SESUAI INVOICE",IF(V13<>"LENGKAP","PENERIMAAN BELUM DIKONFIRMASI","OK")))))) | V13: =IF(B13="","",IF(S13="Ditolak","DITOLAK",IF(AND(S13="Dikonfirmasi",P13<>""),"LENGKAP",IF(S13="Dikonfirmasi","NAMA PENYETUJU BELUM DIISI","MENUNGGU KONFIRMASI MANUAL"))))
A14: =IF(B14="","",IFERROR("INC-"&TEXT(B14,"yyyymmdd")&"-"&TEXT(ROW()-4,"000"),"TANGGAL TIDAK VALID")) | C14: =IF(B14="","",IFERROR(TEXT(B14,"yyyy-mm"),"TANGGAL TIDAK VALID")) | D14: =IF(G14="","",IFERROR(INDEX(INVOICE_PIUTANG!$D$5:$D$151,MATCH(G14,INVOICE_PIUTANG!$A$5:$A$151,0)),"")) | E14: =IF(D14="","",IFERROR(INDEX(PERKARA!$B$5:$B$104,MATCH(D14,PERKARA!$A$5:$A$104,0)),"ID TIDAK TERDAFTAR")) | J14: =IF(B14="","",MAX(H14-I14,0)) | M14: =IF(F14="","",IF(F14="Reimburse dari Klien","Penggantian Biaya",IF(F14="Dana Titipan Klien","Dana Klien",IF(F14="Setoran Modal Partner","Modal Partner",IF(F14="Pinjaman","Pinjaman","Pendapatan Operasional"))))) | R14: =IF(B14="","",IF(AND(G14<>"",COUNTIF(INVOICE_PIUTANG!$A$5:$A$151,G14)=0),"INVOICE BELUM TERDAFTAR",IF(AND(D14<>"",E14="ID TIDAK TERDAFTAR"),"PERKARA TIDAK VALID",IF(K14="","AKUN BELUM DIISI",IF(AND(G14<>"",D14<>IFERROR(INDEX(INVOICE_PIUTANG!$D$5:$D$151,MATCH(G14,INVOICE_PIUTANG!$A$5:$A$151,0)),"")),"PERKARA TIDAK SESUAI INVOICE",IF(V14<>"LENGKAP","PENERIMAAN BELUM DIKONFIRMASI","OK")))))) | V14: =IF(B14="","",IF(S14="Ditolak","DITOLAK",IF(AND(S14="Dikonfirmasi",P14<>""),"LENGKAP",IF(S14="Dikonfirmasi","NAMA PENYETUJU BELUM DIISI","MENUNGGU KONFIRMASI MANUAL"))))
A15: =IF(B15="","",IFERROR("INC-"&TEXT(B15,"yyyymmdd")&"-"&TEXT(ROW()-4,"000"),"TANGGAL TIDAK VALID")) | C15: =IF(B15="","",IFERROR(TEXT(B15,"yyyy-mm"),"TANGGAL TIDAK VALID")) | D15: =IF(G15="","",IFERROR(INDEX(INVOICE_PIUTANG!$D$5:$D$151,MATCH(G15,INVOICE_PIUTANG!$A$5:$A$151,0)),"")) | E15: =IF(D15="","",IFERROR(INDEX(PERKARA!$B$5:$B$104,MATCH(D15,PERKARA!$A$5:$A$104,0)),"ID TIDAK TERDAFTAR")) | J15: =IF(B15="","",MAX(H15-I15,0)) | M15: =IF(F15="","",IF(F15="Reimburse dari Klien","Penggantian Biaya",IF(F15="Dana Titipan Klien","Dana Klien",IF(F15="Setoran Modal Partner","Modal Partner",IF(F15="Pinjaman","Pinjaman","Pendapatan Operasional"))))) | R15: =IF(B15="","",IF(AND(G15<>"",COUNTIF(INVOICE_PIUTANG!$A$5:$A$151,G15)=0),"INVOICE BELUM TERDAFTAR",IF(AND(D15<>"",E15="ID TIDAK TERDAFTAR"),"PERKARA TIDAK VALID",IF(K15="","AKUN BELUM DIISI",IF(AND(G15<>"",D15<>IFERROR(INDEX(INVOICE_PIUTANG!$D$5:$D$151,MATCH(G15,INVOICE_PIUTANG!$A$5:$A$151,0)),"")),"PERKARA TIDAK SESUAI INVOICE",IF(V15<>"LENGKAP","PENERIMAAN BELUM DIKONFIRMASI","OK")))))) | V15: =IF(B15="","",IF(S15="Ditolak","DITOLAK",IF(AND(S15="Dikonfirmasi",P15<>""),"LENGKAP",IF(S15="Dikonfirmasi","NAMA PENYETUJU BELUM DIISI","MENUNGGU KONFIRMASI MANUAL"))))
A16: =IF(B16="","",IFERROR("INC-"&TEXT(B16,"yyyymmdd")&"-"&TEXT(ROW()-4,"000"),"TANGGAL TIDAK VALID")) | C16: =IF(B16="","",IFERROR(TEXT(B16,"yyyy-mm"),"TANGGAL TIDAK VALID")) | D16: =IF(G16="","",IFERROR(INDEX(INVOICE_PIUTANG!$D$5:$D$151,MATCH(G16,INVOICE_PIUTANG!$A$5:$A$151,0)),"")) | E16: =IF(D16="","",IFERROR(INDEX(PERKARA!$B$5:$B$104,MATCH(D16,PERKARA!$A$5:$A$104,0)),"ID TIDAK TERDAFTAR")) | J16: =IF(B16="","",MAX(H16-I16,0)) | M16: =IF(F16="","",IF(F16="Reimburse dari Klien","Penggantian Biaya",IF(F16="Dana Titipan Klien","Dana Klien",IF(F16="Setoran Modal Partner","Modal Partner",IF(F16="Pinjaman","Pinjaman","Pendapatan Operasional"))))) | R16: =IF(B16="","",IF(AND(G16<>"",COUNTIF(INVOICE_PIUTANG!$A$5:$A$151,G16)=0),"INVOICE BELUM TERDAFTAR",IF(AND(D16<>"",E16="ID TIDAK TERDAFTAR"),"PERKARA TIDAK VALID",IF(K16="","AKUN BELUM DIISI",IF(AND(G16<>"",D16<>IFERROR(INDEX(INVOICE_PIUTANG!$D$5:$D$151,MATCH(G16,INVOICE_PIUTANG!$A$5:$A$151,0)),"")),"PERKARA TIDAK SESUAI INVOICE",IF(V16<>"LENGKAP","PENERIMAAN BELUM DIKONFIRMASI","OK")))))) | V16: =IF(B16="","",IF(S16="Ditolak","DITOLAK",IF(AND(S16="Dikonfirmasi",P16<>""),"LENGKAP",IF(S16="Dikonfirmasi","NAMA PENYETUJU BELUM DIISI","MENUNGGU KONFIRMASI MANUAL"))))
A17: =IF(B17="","",IFERROR("INC-"&TEXT(B17,"yyyymmdd")&"-"&TEXT(ROW()-4,"000"),"TANGGAL TIDAK VALID")) | C17: =IF(B17="","",IFERROR(TEXT(B17,"yyyy-mm"),"TANGGAL TIDAK VALID")) | D17: =IF(G17="","",IFERROR(INDEX(INVOICE_PIUTANG!$D$5:$D$151,MATCH(G17,INVOICE_PIUTANG!$A$5:$A$151,0)),"")) | E17: =IF(D17="","",IFERROR(INDEX(PERKARA!$B$5:$B$104,MATCH(D17,PERKARA!$A$5:$A$104,0)),"ID TIDAK TERDAFTAR")) | J17: =IF(B17="","",MAX(H17-I17,0)) | M17: =IF(F17="","",IF(F17="Reimburse dari Klien","Penggantian Biaya",IF(F17="Dana Titipan Klien","Dana Klien",IF(F17="Setoran Modal Partner","Modal Partner",IF(F17="Pinjaman","Pinjaman","Pendapatan Operasional"))))) | R17: =IF(B17="","",IF(AND(G17<>"",COUNTIF(INVOICE_PIUTANG!$A$5:$A$151,G17)=0),"INVOICE BELUM TERDAFTAR",IF(AND(D17<>"",E17="ID TIDAK TERDAFTAR"),"PERKARA TIDAK VALID",IF(K17="","AKUN BELUM DIISI",IF(AND(G17<>"",D17<>IFERROR(INDEX(INVOICE_PIUTANG!$D$5:$D$151,MATCH(G17,INVOICE_PIUTANG!$A$5:$A$151,0)),"")),"PERKARA TIDAK SESUAI INVOICE",IF(V17<>"LENGKAP","PENERIMAAN BELUM DIKONFIRMASI","OK")))))) | V17: =IF(B17="","",IF(S17="Ditolak","DITOLAK",IF(AND(S17="Dikonfirmasi",P17<>""),"LENGKAP",IF(S17="Dikonfirmasi","NAMA PENYETUJU BELUM DIISI","MENUNGGU KONFIRMASI MANUAL"))))
... A204: =IF(B204="","",IFERROR("INC-"&TEXT(B204,"yyyymmdd")&"-"&TEXT(ROW()-4,"000"),"TANGGAL TIDAK VALID")) | C204: =IF(B204="","",IFERROR(TEXT(B204,"yyyy-mm"),"TANGGAL TIDAK VALID")) | D204: =IF(G204="","",IFERROR(INDEX(INVOICE_PIUTANG!$D$5:$D$151,MATCH(G204,INVOICE_PIUTANG!$A$5:$A$151,0)),"")) | E204: =IF(D204="","",IFERROR(INDEX(PERKARA!$B$5:$B$104,MATCH(D204,PERKARA!$A$5:$A$104,0)),"ID TIDAK TERDAFTAR")) | J204: =IF(B204="","",MAX(H204-I204,0)) | M204: =IF(F204="","",IF(F204="Reimburse dari Klien","Penggantian Biaya",IF(F204="Dana Titipan Klien","Dana Klien",IF(F204="Setoran Modal Partner","Modal Partner",IF(F204="Pinjaman","Pinjaman","Pendapatan Operasional"))))) | R204: =IF(B204="","",IF(AND(G204<>"",COUNTIF(INVOICE_PIUTANG!$A$5:$A$151,G204)=0),"INVOICE BELUM TERDAFTAR",IF(AND(D204<>"",E204="ID TIDAK TERDAFTAR"),"PERKARA TIDAK VALID",IF(K204="","AKUN BELUM DIISI",IF(AND(G204<>"",D204<>IFERROR(INDEX(INVOICE_PIUTANG!$D$5:$D$151,MATCH(G204,INVOICE_PIUTANG!$A$5:$A$151,0)),"")),"PERKARA TIDAK SESUAI INVOICE",IF(V204<>"LENGKAP","PENERIMAAN BELUM DIKONFIRMASI","OK")))))) | V204: =IF(B204="","",IF(S204="Ditolak","DITOLAK",IF(AND(S204="Dikonfirmasi",P204<>""),"LENGKAP",IF(S204="Dikonfirmasi","NAMA PENYETUJU BELUM DIISI","MENUNGGU KONFIRMASI MANUAL"))))

Sheet PENGELUARAN
A1: R | P | K REGISTER PENGELUARAN | B1: R | P | K REGISTER PENGELUARAN | C1: R | P | K REGISTER PENGELUARAN | D1: R | P | K REGISTER PENGELUARAN | E1: R | P | K REGISTER PENGELUARAN | F1: R | P | K REGISTER PENGELUARAN | G1: R | P | K REGISTER PENGELUARAN | H1: R | P | K REGISTER PENGELUARAN | I1: R | P | K REGISTER PENGELUARAN | J1: R | P | K REGISTER PENGELUARAN | K1: R | P | K REGISTER PENGELUARAN | L1: R | P | K REGISTER PENGELUARAN | M1: R | P | K REGISTER PENGELUARAN | N1: R | P | K REGISTER PENGELUARAN | O1: R | P | K REGISTER PENGELUARAN | P1: R | P | K REGISTER PENGELUARAN | Q1: R | P | K REGISTER PENGELUARAN | R1: R | P | K REGISTER PENGELUARAN | S1: R | P | K REGISTER PENGELUARAN | T1: R | P | K REGISTER PENGELUARAN | U1: R | P | K REGISTER PENGELUARAN | V1: R | P | K REGISTER PENGELUARAN | W1: R | P | K REGISTER PENGELUARAN | X1: R | P | K REGISTER PENGELUARAN
A2: R | P | K REGISTER PENGELUARAN | B2: R | P | K REGISTER PENGELUARAN | C2: R | P | K REGISTER PENGELUARAN | D2: R | P | K REGISTER PENGELUARAN | E2: R | P | K REGISTER PENGELUARAN | F2: R | P | K REGISTER PENGELUARAN | G2: R | P | K REGISTER PENGELUARAN | H2: R | P | K REGISTER PENGELUARAN | I2: R | P | K REGISTER PENGELUARAN | J2: R | P | K REGISTER PENGELUARAN | K2: R | P | K REGISTER PENGELUARAN | L2: R | P | K REGISTER PENGELUARAN | M2: R | P | K REGISTER PENGELUARAN | N2: R | P | K REGISTER PENGELUARAN | O2: R | P | K REGISTER PENGELUARAN | P2: R | P | K REGISTER PENGELUARAN | Q2: R | P | K REGISTER PENGELUARAN | R2: R | P | K REGISTER PENGELUARAN | S2: R | P | K REGISTER PENGELUARAN | T2: R | P | K REGISTER PENGELUARAN | U2: R | P | K REGISTER PENGELUARAN | V2: R | P | K REGISTER PENGELUARAN | W2: R | P | K REGISTER PENGELUARAN | X2: R | P | K REGISTER PENGELUARAN
A3: Status, nominal disetujui, nama penyetuju, dan tanggal persetujuan merupakan input manual. Catatan historis tanpa identitas penyetuju diberi tanda untuk dilengkapi. | B3: Catat biaya dasar sekali. Gaji dicatat di GAJI; pembayaran kembali reimburse dicatat melalui REIMBURSE agar tidak terjadi penghitungan ganda. | C3: Catat biaya dasar sekali. Gaji dicatat di GAJI; pembayaran kembali reimburse dicatat melalui REIMBURSE agar tidak terjadi penghitungan ganda. | D3: Catat biaya dasar sekali. Gaji dicatat di GAJI; pembayaran kembali reimburse dicatat melalui REIMBURSE agar tidak terjadi penghitungan ganda. | E3: Catat biaya dasar sekali. Gaji dicatat di GAJI; pembayaran kembali reimburse dicatat melalui REIMBURSE agar tidak terjadi penghitungan ganda. | F3: Catat biaya dasar sekali. Gaji dicatat di GAJI; pembayaran kembali reimburse dicatat melalui REIMBURSE agar tidak terjadi penghitungan ganda. | G3: Catat biaya dasar sekali. Gaji dicatat di GAJI; pembayaran kembali reimburse dicatat melalui REIMBURSE agar tidak terjadi penghitungan ganda. | H3: Catat biaya dasar sekali. Gaji dicatat di GAJI; pembayaran kembali reimburse dicatat melalui REIMBURSE agar tidak terjadi penghitungan ganda. | I3: Catat biaya dasar sekali. Gaji dicatat di GAJI; pembayaran kembali reimburse dicatat melalui REIMBURSE agar tidak terjadi penghitungan ganda. | J3: Catat biaya dasar sekali. Gaji dicatat di GAJI; pembayaran kembali reimburse dicatat melalui REIMBURSE agar tidak terjadi penghitungan ganda. | K3: Catat biaya dasar sekali. Gaji dicatat di GAJI; pembayaran kembali reimburse dicatat melalui REIMBURSE agar tidak terjadi penghitungan ganda. | L3: Catat biaya dasar sekali. Gaji dicatat di GAJI; pembayaran kembali reimburse dicatat melalui REIMBURSE agar tidak terjadi penghitungan ganda. | M3: Catat biaya dasar sekali. Gaji dicatat di GAJI; pembayaran kembali reimburse dicatat melalui REIMBURSE agar tidak terjadi penghitungan ganda. | N3: Catat biaya dasar sekali. Gaji dicatat di GAJI; pembayaran kembali reimburse dicatat melalui REIMBURSE agar tidak terjadi penghitungan ganda. | O3: Catat biaya dasar sekali. Gaji dicatat di GAJI; pembayaran kembali reimburse dicatat melalui REIMBURSE agar tidak terjadi penghitungan ganda. | P3: Catat biaya dasar sekali. Gaji dicatat di GAJI; pembayaran kembali reimburse dicatat melalui REIMBURSE agar tidak terjadi penghitungan ganda. | Q3: Catat biaya dasar sekali. Gaji dicatat di GAJI; pembayaran kembali reimburse dicatat melalui REIMBURSE agar tidak terjadi penghitungan ganda. | R3: Catat biaya dasar sekali. Gaji dicatat di GAJI; pembayaran kembali reimburse dicatat melalui REIMBURSE agar tidak terjadi penghitungan ganda. | S3: Catat biaya dasar sekali. Gaji dicatat di GAJI; pembayaran kembali reimburse dicatat melalui REIMBURSE agar tidak terjadi penghitungan ganda. | T3: Catat biaya dasar sekali. Gaji dicatat di GAJI; pembayaran kembali reimburse dicatat melalui REIMBURSE agar tidak terjadi penghitungan ganda. | U3: Catat biaya dasar sekali. Gaji dicatat di GAJI; pembayaran kembali reimburse dicatat melalui REIMBURSE agar tidak terjadi penghitungan ganda. | V3: Catat biaya dasar sekali. Gaji dicatat di GAJI; pembayaran kembali reimburse dicatat melalui REIMBURSE agar tidak terjadi penghitungan ganda. | W3: Catat biaya dasar sekali. Gaji dicatat di GAJI; pembayaran kembali reimburse dicatat melalui REIMBURSE agar tidak terjadi penghitungan ganda. | X3: Catat biaya dasar sekali. Gaji dicatat di GAJI; pembayaran kembali reimburse dicatat melalui REIMBURSE agar tidak terjadi penghitungan ganda.
A4: ID Pengeluaran | B4: Tanggal | C4: Periode | D4: Kode Perkara | E4: Klien | F4: Uraian Pengeluaran | G4: Kategori | H4: Dibayar Oleh | I4: Sumber Dana / Akun | J4: Metode Bayar | K4: Nilai Pengeluaran | L4: Dibebankan Kepada | M4: Perlu Reimburse? | N4: ID Klaim Reimburse | O4: Status Bukti | P4: Nama/Link Bukti | Q4: Status Persetujuan (Manual) | R4: Nilai Disetujui (Manual) | S4: Nilai Direimburse | T4: Sisa Reimburse | U4: Tanggal Reimburse | V4: Status Reimburse | W4: Dapat Ditagih Klien? | X4: Catatan | Y4: Status Validasi | Z4: Disetujui Oleh (Manual) | AA4: Tanggal Persetujuan | AB4: Catatan Persetujuan | AC4: Status Otorisasi
A5: =IF(B5="","","EXP-"&TEXT(B5,"yyyymmdd")&"-"&TEXT(ROW()-4,"000")) -> EXP-20260729-001 | B5: 46232 | C5: =IF(B5="","",TEXT(B5,"yyyy-mm")) -> 2026-07 | D5: 001/2026 | E5: =IF(D5="","",IFERROR(INDEX([1]PERKARA!$B$5:$B$104,MATCH(D5,[1]PERKARA!$A$5:$A$104,0)),"ID TIDAK TERDAFTAR")) -> PT KEMBANG KEMBAR GRUP | F5: ATK | G5: Peralatan Kantor | H5: Kas Kantor | I5: Kas Kantor | J5: QRIS | K5: 128600 | L5: Kantor | M5: Tidak | O5: Lengkap | P5: 800051 | Q5: Disetujui | R5: 128600 | S5: 0 | T5: =IF(B5="","",IF(M5<>"Ya",0,MAX(IF(R5="",K5,R5)-S5,0))) -> 0 | V5: =IF(B5="","",IF(M5<>"Ya","Tidak Perlu",IF(Q5="Ditolak","Ditolak",IF(S5=0,IF(Q5="Disetujui","Belum Dibayar","Belum Diajukan"),IF(T5=0,"Lunas","Dibayar Sebagian"))))) -> Tidak Perlu | W5: Tidak | Y5: =IF(B5="","",IF(AND(D5<>"",E5="ID TIDAK TERDAFTAR"),"PERKARA TIDAK VALID",IF(I5="","AKUN BELUM DIISI",IF(AND(M5="Ya",N5=""),"KLAIM BELUM DIHUBUNGKAN",IF(AND(N5<>"",COUNTIF(REIMBURSE!$A$5:$A$124,N5)=0),"ID KLAIM TIDAK TERDAFTAR",IF(Q5="Ditolak","PENGELUARAN DITOLAK",IF(R5>K5,"NILAI DISETUJUI MELEBIHI BIAYA",IF(AND(Q5="Disetujui",Z5=""),"PENYETUJU BELUM DIISI",IF(Q5<>"Disetujui","MENUNGGU PERSETUJUAN","OK"))))))))) -> OK | Z5: Fajar Roni | AA5: 46258 | AC5: =IF(B5="","",IF(Q5="Ditolak","DITOLAK",IF(AND(Q5="Disetujui",R5>K5),"NILAI DISETUJUI MELEBIHI BIAYA",IF(AND(Q5="Disetujui",R5=""),"NILAI PERSETUJUAN BELUM DIISI",IF(AND(Q5="Disetujui",Z5<>""),"LENGKAP",IF(Q5="Disetujui","NAMA PENYETUJU BELUM DIISI","MENUNGGU PERSETUJUAN MANUAL")))))) -> LENGKAP
A6: =IF(B6="","","EXP-"&TEXT(B6,"yyyymmdd")&"-"&TEXT(ROW()-4,"000")) -> EXP-20260729-002 | B6: 46232 | C6: =IF(B6="","",TEXT(B6,"yyyy-mm")) -> 2026-07 | D6: 001/2026 | E6: =IF(D6="","",IFERROR(INDEX([1]PERKARA!$B$5:$B$104,MATCH(D6,[1]PERKARA!$A$5:$A$104,0)),"ID TIDAK TERDAFTAR")) -> PT KEMBANG KEMBAR GRUP | F6: STAMP RPK Law Office | G6: Peralatan Kantor | H6: Kas Kantor | I6: Kas Kantor | J6: QRIS | K6: 163000 | L6: Kantor | M6: Tidak | O6: Lengkap | P6: HAS 018013 | Q6: Disetujui | R6: 163000 | S6: 0 | T6: =IF(B6="","",IF(M6<>"Ya",0,MAX(IF(R6="",K6,R6)-S6,0))) -> 0 | V6: =IF(B6="","",IF(M6<>"Ya","Tidak Perlu",IF(Q6="Ditolak","Ditolak",IF(S6=0,IF(Q6="Disetujui","Belum Dibayar","Belum Diajukan"),IF(T6=0,"Lunas","Dibayar Sebagian"))))) -> Tidak Perlu | W6: Tidak | Y6: =IF(B6="","",IF(AND(D6<>"",E6="ID TIDAK TERDAFTAR"),"PERKARA TIDAK VALID",IF(I6="","AKUN BELUM DIISI",IF(AND(M6="Ya",N6=""),"KLAIM BELUM DIHUBUNGKAN",IF(AND(N6<>"",COUNTIF(REIMBURSE!$A$5:$A$124,N6)=0),"ID KLAIM TIDAK TERDAFTAR",IF(Q6="Ditolak","PENGELUARAN DITOLAK",IF(R6>K6,"NILAI DISETUJUI MELEBIHI BIAYA",IF(AND(Q6="Disetujui",Z6=""),"PENYETUJU BELUM DIISI",IF(Q6<>"Disetujui","MENUNGGU PERSETUJUAN","OK"))))))))) -> OK | Z6: Fajar Roni | AA6: 46259 | AC6: =IF(B6="","",IF(Q6="Ditolak","DITOLAK",IF(AND(Q6="Disetujui",R6>K6),"NILAI DISETUJUI MELEBIHI BIAYA",IF(AND(Q6="Disetujui",R6=""),"NILAI PERSETUJUAN BELUM DIISI",IF(AND(Q6="Disetujui",Z6<>""),"LENGKAP",IF(Q6="Disetujui","NAMA PENYETUJU BELUM DIISI","MENUNGGU PERSETUJUAN MANUAL")))))) -> LENGKAP
A7: =IF(B7="","","EXP-"&TEXT(B7,"yyyymmdd")&"-"&TEXT(ROW()-4,"000")) -> EXP-20260729-003 | B7: 46232 | C7: =IF(B7="","",TEXT(B7,"yyyy-mm")) -> 2026-07 | D7: 001/2026 | E7: =IF(D7="","",IFERROR(INDEX([1]PERKARA!$B$5:$B$104,MATCH(D7,[1]PERKARA!$A$5:$A$104,0)),"ID TIDAK TERDAFTAR")) -> PT KEMBANG KEMBAR GRUP | F7: PRINTER HP SMART TANK 583 | G7: Peralatan Kantor | H7: Kas Kantor | I7: Kas Kantor | J7: QRIS | K7: 2099000 | L7: Kantor | M7: Tidak | O7: Lengkap | P7: Inv 7132-68350 | Q7: Disetujui | R7: 2099000 | S7: 0 | T7: =IF(B7="","",IF(M7<>"Ya",0,MAX(IF(R7="",K7,R7)-S7,0))) -> 0 | V7: =IF(B7="","",IF(M7<>"Ya","Tidak Perlu",IF(Q7="Ditolak","Ditolak",IF(S7=0,IF(Q7="Disetujui","Belum Dibayar","Belum Diajukan"),IF(T7=0,"Lunas","Dibayar Sebagian"))))) -> Tidak Perlu | W7: Tidak | Y7: =IF(B7="","",IF(AND(D7<>"",E7="ID TIDAK TERDAFTAR"),"PERKARA TIDAK VALID",IF(I7="","AKUN BELUM DIISI",IF(AND(M7="Ya",N7=""),"KLAIM BELUM DIHUBUNGKAN",IF(AND(N7<>"",COUNTIF(REIMBURSE!$A$5:$A$124,N7)=0),"ID KLAIM TIDAK TERDAFTAR",IF(Q7="Ditolak","PENGELUARAN DITOLAK",IF(R7>K7,"NILAI DISETUJUI MELEBIHI BIAYA",IF(AND(Q7="Disetujui",Z7=""),"PENYETUJU BELUM DIISI",IF(Q7<>"Disetujui","MENUNGGU PERSETUJUAN","OK"))))))))) -> OK | Z7: Fajar Roni | AA7: 46260 | AC7: =IF(B7="","",IF(Q7="Ditolak","DITOLAK",IF(AND(Q7="Disetujui",R7>K7),"NILAI DISETUJUI MELEBIHI BIAYA",IF(AND(Q7="Disetujui",R7=""),"NILAI PERSETUJUAN BELUM DIISI",IF(AND(Q7="Disetujui",Z7<>""),"LENGKAP",IF(Q7="Disetujui","NAMA PENYETUJU BELUM DIISI","MENUNGGU PERSETUJUAN MANUAL")))))) -> LENGKAP
A8: =IF(B8="","","EXP-"&TEXT(B8,"yyyymmdd")&"-"&TEXT(ROW()-4,"000")) -> EXP-20260815-004 | B8: 46249 | C8: =IF(B8="","",TEXT(B8,"yyyy-mm")) -> 2026-08 | D8: 001/2026 | E8: =IF(D8="","",IFERROR(INDEX([1]PERKARA!$B$5:$B$104,MATCH(D8,[1]PERKARA!$A$5:$A$104,0)),"ID TIDAK TERDAFTAR")) -> PT KEMBANG KEMBAR GRUP | F8: Tiket Woosh | G8: Transportasi | H8: Kas Kantor | I8: Kas Kantor | J8: QRIS | K8: 325000 | L8: Kantor | M8: Tidak | O8: Lengkap | P8: 62003XZ086202608149437826 | Q8: Disetujui | R8: 325000 | S8: 0 | T8: =IF(B8="","",IF(M8<>"Ya",0,MAX(IF(R8="",K8,R8)-S8,0))) -> 0 | V8: =IF(B8="","",IF(M8<>"Ya","Tidak Perlu",IF(Q8="Ditolak","Ditolak",IF(S8=0,IF(Q8="Disetujui","Belum Dibayar","Belum Diajukan"),IF(T8=0,"Lunas","Dibayar Sebagian"))))) -> Tidak Perlu | W8: Tidak | Y8: =IF(B8="","",IF(AND(D8<>"",E8="ID TIDAK TERDAFTAR"),"PERKARA TIDAK VALID",IF(I8="","AKUN BELUM DIISI",IF(AND(M8="Ya",N8=""),"KLAIM BELUM DIHUBUNGKAN",IF(AND(N8<>"",COUNTIF(REIMBURSE!$A$5:$A$124,N8)=0),"ID KLAIM TIDAK TERDAFTAR",IF(Q8="Ditolak","PENGELUARAN DITOLAK",IF(R8>K8,"NILAI DISETUJUI MELEBIHI BIAYA",IF(AND(Q8="Disetujui",Z8=""),"PENYETUJU BELUM DIISI",IF(Q8<>"Disetujui","MENUNGGU PERSETUJUAN","OK"))))))))) -> OK | Z8: Fajar Roni | AA8: 46261 | AC8: =IF(B8="","",IF(Q8="Ditolak","DITOLAK",IF(AND(Q8="Disetujui",R8>K8),"NILAI DISETUJUI MELEBIHI BIAYA",IF(AND(Q8="Disetujui",R8=""),"NILAI PERSETUJUAN BELUM DIISI",IF(AND(Q8="Disetujui",Z8<>""),"LENGKAP",IF(Q8="Disetujui","NAMA PENYETUJU BELUM DIISI","MENUNGGU PERSETUJUAN MANUAL")))))) -> LENGKAP
A9: =IF(B9="","","EXP-"&TEXT(B9,"yyyymmdd")&"-"&TEXT(ROW()-4,"000")) -> EXP-20260815-005 | B9: 46249 | C9: =IF(B9="","",TEXT(B9,"yyyy-mm")) -> 2026-08 | D9: 001/2026 | E9: =IF(D9="","",IFERROR(INDEX([1]PERKARA!$B$5:$B$104,MATCH(D9,[1]PERKARA!$A$5:$A$104,0)),"ID TIDAK TERDAFTAR")) -> PT KEMBANG KEMBAR GRUP | F9: Tiket Woosh | G9: Transportasi | H9: Kas Kantor | I9: Kas Kantor | J9: QRIS | K9: 325000 | L9: Kantor | M9: Tidak | O9: Lengkap | P9: 62001XZ086202608149080460 | Q9: Disetujui | R9: 325000 | S9: 0 | T9: =IF(B9="","",IF(M9<>"Ya",0,MAX(IF(R9="",K9,R9)-S9,0))) -> 0 | V9: =IF(B9="","",IF(M9<>"Ya","Tidak Perlu",IF(Q9="Ditolak","Ditolak",IF(S9=0,IF(Q9="Disetujui","Belum Dibayar","Belum Diajukan"),IF(T9=0,"Lunas","Dibayar Sebagian"))))) -> Tidak Perlu | W9: Tidak | Y9: =IF(B9="","",IF(AND(D9<>"",E9="ID TIDAK TERDAFTAR"),"PERKARA TIDAK VALID",IF(I9="","AKUN BELUM DIISI",IF(AND(M9="Ya",N9=""),"KLAIM BELUM DIHUBUNGKAN",IF(AND(N9<>"",COUNTIF(REIMBURSE!$A$5:$A$124,N9)=0),"ID KLAIM TIDAK TERDAFTAR",IF(Q9="Ditolak","PENGELUARAN DITOLAK",IF(R9>K9,"NILAI DISETUJUI MELEBIHI BIAYA",IF(AND(Q9="Disetujui",Z9=""),"PENYETUJU BELUM DIISI",IF(Q9<>"Disetujui","MENUNGGU PERSETUJUAN","OK"))))))))) -> OK | Z9: Fajar Roni | AA9: 46262 | AC9: =IF(B9="","",IF(Q9="Ditolak","DITOLAK",IF(AND(Q9="Disetujui",R9>K9),"NILAI DISETUJUI MELEBIHI BIAYA",IF(AND(Q9="Disetujui",R9=""),"NILAI PERSETUJUAN BELUM DIISI",IF(AND(Q9="Disetujui",Z9<>""),"LENGKAP",IF(Q9="Disetujui","NAMA PENYETUJU BELUM DIISI","MENUNGGU PERSETUJUAN MANUAL")))))) -> LENGKAP
A10: =IF(B10="","","EXP-"&TEXT(B10,"yyyymmdd")&"-"&TEXT(ROW()-4,"000")) -> EXP-20260815-006 | B10: 46249 | C10: =IF(B10="","",TEXT(B10,"yyyy-mm")) -> 2026-08 | D10: 001/2026 | E10: =IF(D10="","",IFERROR(INDEX([1]PERKARA!$B$5:$B$104,MATCH(D10,[1]PERKARA!$A$5:$A$104,0)),"ID TIDAK TERDAFTAR")) -> PT KEMBANG KEMBAR GRUP | F10: Starbucks | G10: Konsumsi | H10: Kas Kantor | I10: Kas Kantor | J10: QRIS | K10: 83000 | L10: Kantor | M10: Tidak | O10: Lengkap | P10: SSCDH178661366499SCDH002 | Q10: Disetujui | R10: 83000 | S10: 0 | T10: =IF(B10="","",IF(M10<>"Ya",0,MAX(IF(R10="",K10,R10)-S10,0))) -> 0 | V10: =IF(B10="","",IF(M10<>"Ya","Tidak Perlu",IF(Q10="Ditolak","Ditolak",IF(S10=0,IF(Q10="Disetujui","Belum Dibayar","Belum Diajukan"),IF(T10=0,"Lunas","Dibayar Sebagian"))))) -> Tidak Perlu | W10: Tidak | Y10: =IF(B10="","",IF(AND(D10<>"",E10="ID TIDAK TERDAFTAR"),"PERKARA TIDAK VALID",IF(I10="","AKUN BELUM DIISI",IF(AND(M10="Ya",N10=""),"KLAIM BELUM DIHUBUNGKAN",IF(AND(N10<>"",COUNTIF(REIMBURSE!$A$5:$A$124,N10)=0),"ID KLAIM TIDAK TERDAFTAR",IF(Q10="Ditolak","PENGELUARAN DITOLAK",IF(R10>K10,"NILAI DISETUJUI MELEBIHI BIAYA",IF(AND(Q10="Disetujui",Z10=""),"PENYETUJU BELUM DIISI",IF(Q10<>"Disetujui","MENUNGGU PERSETUJUAN","OK"))))))))) -> OK | Z10: Fajar Roni | AA10: 46263 | AC10: =IF(B10="","",IF(Q10="Ditolak","DITOLAK",IF(AND(Q10="Disetujui",R10>K10),"NILAI DISETUJUI MELEBIHI BIAYA",IF(AND(Q10="Disetujui",R10=""),"NILAI PERSETUJUAN BELUM DIISI",IF(AND(Q10="Disetujui",Z10<>""),"LENGKAP",IF(Q10="Disetujui","NAMA PENYETUJU BELUM DIISI","MENUNGGU PERSETUJUAN MANUAL")))))) -> LENGKAP
A11: =IF(B11="","","EXP-"&TEXT(B11,"yyyymmdd")&"-"&TEXT(ROW()-4,"000")) -> EXP-20260815-007 | B11: 46249 | C11: =IF(B11="","",TEXT(B11,"yyyy-mm")) -> 2026-08 | D11: 001/2026 | E11: =IF(D11="","",IFERROR(INDEX([1]PERKARA!$B$5:$B$104,MATCH(D11,[1]PERKARA!$A$5:$A$104,0)),"ID TIDAK TERDAFTAR")) -> PT KEMBANG KEMBAR GRUP | F11: Starbucks | G11: Konsumsi | H11: Kas Kantor | I11: Kas Kantor | J11: QRIS | K11: 97800 | L11: Kantor | M11: Tidak | O11: Lengkap | P11: SSCDH178661504395SCDH002 | Q11: Disetujui | R11: 97800 | S11: 0 | T11: =IF(B11="","",IF(M11<>"Ya",0,MAX(IF(R11="",K11,R11)-S11,0))) -> 0 | V11: =IF(B11="","",IF(M11<>"Ya","Tidak Perlu",IF(Q11="Ditolak","Ditolak",IF(S11=0,IF(Q11="Disetujui","Belum Dibayar","Belum Diajukan"),IF(T11=0,"Lunas","Dibayar Sebagian"))))) -> Tidak Perlu | W11: Tidak | Y11: =IF(B11="","",IF(AND(D11<>"",E11="ID TIDAK TERDAFTAR"),"PERKARA TIDAK VALID",IF(I11="","AKUN BELUM DIISI",IF(AND(M11="Ya",N11=""),"KLAIM BELUM DIHUBUNGKAN",IF(AND(N11<>"",COUNTIF(REIMBURSE!$A$5:$A$124,N11)=0),"ID KLAIM TIDAK TERDAFTAR",IF(Q11="Ditolak","PENGELUARAN DITOLAK",IF(R11>K11,"NILAI DISETUJUI MELEBIHI BIAYA",IF(AND(Q11="Disetujui",Z11=""),"PENYETUJU BELUM DIISI",IF(Q11<>"Disetujui","MENUNGGU PERSETUJUAN","OK"))))))))) -> OK | Z11: Fajar Roni | AA11: 46264 | AC11: =IF(B11="","",IF(Q11="Ditolak","DITOLAK",IF(AND(Q11="Disetujui",R11>K11),"NILAI DISETUJUI MELEBIHI BIAYA",IF(AND(Q11="Disetujui",R11=""),"NILAI PERSETUJUAN BELUM DIISI",IF(AND(Q11="Disetujui",Z11<>""),"LENGKAP",IF(Q11="Disetujui","NAMA PENYETUJU BELUM DIISI","MENUNGGU PERSETUJUAN MANUAL")))))) -> LENGKAP
A12: =IF(B12="","","EXP-"&TEXT(B12,"yyyymmdd")&"-"&TEXT(ROW()-4,"000")) -> EXP-20260815-008 | B12: 46249 | C12: =IF(B12="","",TEXT(B12,"yyyy-mm")) -> 2026-08 | D12: 001/2026 | E12: =IF(D12="","",IFERROR(INDEX([1]PERKARA!$B$5:$B$104,MATCH(D12,[1]PERKARA!$A$5:$A$104,0)),"ID TIDAK TERDAFTAR")) -> PT KEMBANG KEMBAR GRUP | F12: Kartikasari | G12: Konsumsi | H12: Kas Kantor | I12: Kas Kantor | J12: QRIS | K12: 325000 | L12: Kantor | M12: Tidak | O12: Lengkap | P12: 11/ARCG/00093516 | Q12: Disetujui | R12: 325000 | S12: 0 | T12: =IF(B12="","",IF(M12<>"Ya",0,MAX(IF(R12="",K12,R12)-S12,0))) -> 0 | V12: =IF(B12="","",IF(M12<>"Ya","Tidak Perlu",IF(Q12="Ditolak","Ditolak",IF(S12=0,IF(Q12="Disetujui","Belum Dibayar","Belum Diajukan"),IF(T12=0,"Lunas","Dibayar Sebagian"))))) -> Tidak Perlu | W12: Tidak | Y12: =IF(B12="","",IF(AND(D12<>"",E12="ID TIDAK TERDAFTAR"),"PERKARA TIDAK VALID",IF(I12="","AKUN BELUM DIISI",IF(AND(M12="Ya",N12=""),"KLAIM BELUM DIHUBUNGKAN",IF(AND(N12<>"",COUNTIF(REIMBURSE!$A$5:$A$124,N12)=0),"ID KLAIM TIDAK TERDAFTAR",IF(Q12="Ditolak","PENGELUARAN DITOLAK",IF(R12>K12,"NILAI DISETUJUI MELEBIHI BIAYA",IF(AND(Q12="Disetujui",Z12=""),"PENYETUJU BELUM DIISI",IF(Q12<>"Disetujui","MENUNGGU PERSETUJUAN","OK"))))))))) -> OK | Z12: Fajar Roni | AA12: 46265 | AC12: =IF(B12="","",IF(Q12="Ditolak","DITOLAK",IF(AND(Q12="Disetujui",R12>K12),"NILAI DISETUJUI MELEBIHI BIAYA",IF(AND(Q12="Disetujui",R12=""),"NILAI PERSETUJUAN BELUM DIISI",IF(AND(Q12="Disetujui",Z12<>""),"LENGKAP",IF(Q12="Disetujui","NAMA PENYETUJU BELUM DIISI","MENUNGGU PERSETUJUAN MANUAL")))))) -> LENGKAP
A13: =IF(B13="","","EXP-"&TEXT(B13,"yyyymmdd")&"-"&TEXT(ROW()-4,"000")) -> EXP-20260817-009 | B13: 46251 | C13: =IF(B13="","",TEXT(B13,"yyyy-mm")) -> 2026-08 | D13: 001/2026 | E13: =IF(D13="","",IFERROR(INDEX([1]PERKARA!$B$5:$B$104,MATCH(D13,[1]PERKARA!$A$5:$A$104,0)),"ID TIDAK TERDAFTAR")) -> PT KEMBANG KEMBAR GRUP | F13: Domain Website | G13: Software/Langganan | H13: Kas Kantor | I13: Kas Kantor | J13: QRIS | K13: 51000 | L13: Kantor | M13: Tidak | O13: Tidak Lengkap | Q13: Disetujui | R13: 51000 | S13: 0 | T13: =IF(B13="","",IF(M13<>"Ya",0,MAX(IF(R13="",K13,R13)-S13,0))) -> 0 | V13: =IF(B13="","",IF(M13<>"Ya","Tidak Perlu",IF(Q13="Ditolak","Ditolak",IF(S13=0,IF(Q13="Disetujui","Belum Dibayar","Belum Diajukan"),IF(T13=0,"Lunas","Dibayar Sebagian"))))) -> Tidak Perlu | W13: Tidak | Y13: =IF(B13="","",IF(AND(D13<>"",E13="ID TIDAK TERDAFTAR"),"PERKARA TIDAK VALID",IF(I13="","AKUN BELUM DIISI",IF(AND(M13="Ya",N13=""),"KLAIM BELUM DIHUBUNGKAN",IF(AND(N13<>"",COUNTIF(REIMBURSE!$A$5:$A$124,N13)=0),"ID KLAIM TIDAK TERDAFTAR",IF(Q13="Ditolak","PENGELUARAN DITOLAK",IF(R13>K13,"NILAI DISETUJUI MELEBIHI BIAYA",IF(AND(Q13="Disetujui",Z13=""),"PENYETUJU BELUM DIISI",IF(Q13<>"Disetujui","MENUNGGU PERSETUJUAN","OK"))))))))) -> OK | Z13: Fajar Roni | AA13: 46266 | AC13: =IF(B13="","",IF(Q13="Ditolak","DITOLAK",IF(AND(Q13="Disetujui",R13>K13),"NILAI DISETUJUI MELEBIHI BIAYA",IF(AND(Q13="Disetujui",R13=""),"NILAI PERSETUJUAN BELUM DIISI",IF(AND(Q13="Disetujui",Z13<>""),"LENGKAP",IF(Q13="Disetujui","NAMA PENYETUJU BELUM DIISI","MENUNGGU PERSETUJUAN MANUAL")))))) -> LENGKAP
A14: =IF(B14="","","EXP-"&TEXT(B14,"yyyymmdd")&"-"&TEXT(ROW()-4,"000")) -> EXP-20260817-010 | B14: 46251 | C14: =IF(B14="","",TEXT(B14,"yyyy-mm")) -> 2026-08 | D14: 001/2026 | E14: =IF(D14="","",IFERROR(INDEX([1]PERKARA!$B$5:$B$104,MATCH(D14,[1]PERKARA!$A$5:$A$104,0)),"ID TIDAK TERDAFTAR")) -> PT KEMBANG KEMBAR GRUP | F14: Email Domain Kantor | G14: Software/Langganan | H14: Kas Kantor | I14: Kas Kantor | J14: QRIS | K14: 145188 | L14: Kantor | M14: Tidak | O14: Tidak Lengkap | P14: QRIS JD9FEK1WRSDI8FWAKOFU8CZNC | Q14: Disetujui | R14: 145188 | S14: 0 | T14: =IF(B14="","",IF(M14<>"Ya",0,MAX(IF(R14="",K14,R14)-S14,0))) -> 0 | V14: =IF(B14="","",IF(M14<>"Ya","Tidak Perlu",IF(Q14="Ditolak","Ditolak",IF(S14=0,IF(Q14="Disetujui","Belum Dibayar","Belum Diajukan"),IF(T14=0,"Lunas","Dibayar Sebagian"))))) -> Tidak Perlu | W14: Tidak | Y14: =IF(B14="","",IF(AND(D14<>"",E14="ID TIDAK TERDAFTAR"),"PERKARA TIDAK VALID",IF(I14="","AKUN BELUM DIISI",IF(AND(M14="Ya",N14=""),"KLAIM BELUM DIHUBUNGKAN",IF(AND(N14<>"",COUNTIF(REIMBURSE!$A$5:$A$124,N14)=0),"ID KLAIM TIDAK TERDAFTAR",IF(Q14="Ditolak","PENGELUARAN DITOLAK",IF(R14>K14,"NILAI DISETUJUI MELEBIHI BIAYA",IF(AND(Q14="Disetujui",Z14=""),"PENYETUJU BELUM DIISI",IF(Q14<>"Disetujui","MENUNGGU PERSETUJUAN","OK"))))))))) -> OK | Z14: Fajar Roni | AA14: 46267 | AC14: =IF(B14="","",IF(Q14="Ditolak","DITOLAK",IF(AND(Q14="Disetujui",R14>K14),"NILAI DISETUJUI MELEBIHI BIAYA",IF(AND(Q14="Disetujui",R14=""),"NILAI PERSETUJUAN BELUM DIISI",IF(AND(Q14="Disetujui",Z14<>""),"LENGKAP",IF(Q14="Disetujui","NAMA PENYETUJU BELUM DIISI","MENUNGGU PERSETUJUAN MANUAL")))))) -> LENGKAP
A15: =IF(B15="","","EXP-"&TEXT(B15,"yyyymmdd")&"-"&TEXT(ROW()-4,"000")) -> EXP-20260821-011 | B15: 46255 | C15: =IF(B15="","",TEXT(B15,"yyyy-mm")) -> 2026-08 | D15: 001/2026 | E15: =IF(D15="","",IFERROR(INDEX([1]PERKARA!$B$5:$B$104,MATCH(D15,[1]PERKARA!$A$5:$A$104,0)),"ID TIDAK TERDAFTAR")) -> PT KEMBANG KEMBAR GRUP | F15: Rapat Mingguan | G15: Konsumsi | H15: Kas Kantor | I15: Kas Kantor | J15: QRIS | K15: 353320 | L15: Kantor | M15: Tidak | O15: Lengkap | P15: 110723 | Q15: Disetujui | R15: 353320 | S15: 0 | T15: =IF(B15="","",IF(M15<>"Ya",0,MAX(IF(R15="",K15,R15)-S15,0))) -> 0 | V15: =IF(B15="","",IF(M15<>"Ya","Tidak Perlu",IF(Q15="Ditolak","Ditolak",IF(S15=0,IF(Q15="Disetujui","Belum Dibayar","Belum Diajukan"),IF(T15=0,"Lunas","Dibayar Sebagian"))))) -> Tidak Perlu | W15: Tidak | Y15: =IF(B15="","",IF(AND(D15<>"",E15="ID TIDAK TERDAFTAR"),"PERKARA TIDAK VALID",IF(I15="","AKUN BELUM DIISI",IF(AND(M15="Ya",N15=""),"KLAIM BELUM DIHUBUNGKAN",IF(AND(N15<>"",COUNTIF(REIMBURSE!$A$5:$A$124,N15)=0),"ID KLAIM TIDAK TERDAFTAR",IF(Q15="Ditolak","PENGELUARAN DITOLAK",IF(R15>K15,"NILAI DISETUJUI MELEBIHI BIAYA",IF(AND(Q15="Disetujui",Z15=""),"PENYETUJU BELUM DIISI",IF(Q15<>"Disetujui","MENUNGGU PERSETUJUAN","OK"))))))))) -> OK | Z15: Fajar Roni | AA15: 46268 | AC15: =IF(B15="","",IF(Q15="Ditolak","DITOLAK",IF(AND(Q15="Disetujui",R15>K15),"NILAI DISETUJUI MELEBIHI BIAYA",IF(AND(Q15="Disetujui",R15=""),"NILAI PERSETUJUAN BELUM DIISI",IF(AND(Q15="Disetujui",Z15<>""),"LENGKAP",IF(Q15="Disetujui","NAMA PENYETUJU BELUM DIISI","MENUNGGU PERSETUJUAN MANUAL")))))) -> LENGKAP
A16: =IF(B16="","","EXP-"&TEXT(B16,"yyyymmdd")&"-"&TEXT(ROW()-4,"000")) | C16: =IF(B16="","",TEXT(B16,"yyyy-mm")) | E16: =IF(D16="","",IFERROR(INDEX(PERKARA!$B$5:$B$104,MATCH(D16,PERKARA!$A$5:$A$104,0)),"ID TIDAK TERDAFTAR")) | T16: =IF(B16="","",IF(M16<>"Ya",0,MAX(IF(R16="",K16,R16)-S16,0))) | V16: =IF(B16="","",IF(M16<>"Ya","Tidak Perlu",IF(Q16="Ditolak","Ditolak",IF(S16=0,IF(Q16="Disetujui","Belum Dibayar","Belum Diajukan"),IF(T16=0,"Lunas","Dibayar Sebagian"))))) | Y16: =IF(B16="","",IF(AND(D16<>"",E16="ID TIDAK TERDAFTAR"),"PERKARA TIDAK VALID",IF(I16="","AKUN BELUM DIISI",IF(AND(M16="Ya",N16=""),"KLAIM BELUM DIHUBUNGKAN",IF(AND(N16<>"",COUNTIF(REIMBURSE!$A$5:$A$124,N16)=0),"ID KLAIM TIDAK TERDAFTAR",IF(Q16="Ditolak","PENGELUARAN DITOLAK",IF(R16>K16,"NILAI DISETUJUI MELEBIHI BIAYA",IF(AND(Q16="Disetujui",Z16=""),"PENYETUJU BELUM DIISI",IF(Q16<>"Disetujui","MENUNGGU PERSETUJUAN","OK"))))))))) | AC16: =IF(B16="","",IF(Q16="Ditolak","DITOLAK",IF(AND(Q16="Disetujui",R16>K16),"NILAI DISETUJUI MELEBIHI BIAYA",IF(AND(Q16="Disetujui",R16=""),"NILAI PERSETUJUAN BELUM DIISI",IF(AND(Q16="Disetujui",Z16<>""),"LENGKAP",IF(Q16="Disetujui","NAMA PENYETUJU BELUM DIISI","MENUNGGU PERSETUJUAN MANUAL"))))))
A17: =IF(B17="","","EXP-"&TEXT(B17,"yyyymmdd")&"-"&TEXT(ROW()-4,"000")) | C17: =IF(B17="","",TEXT(B17,"yyyy-mm")) | E17: =IF(D17="","",IFERROR(INDEX(PERKARA!$B$5:$B$104,MATCH(D17,PERKARA!$A$5:$A$104,0)),"ID TIDAK TERDAFTAR")) | T17: =IF(B17="","",IF(M17<>"Ya",0,MAX(IF(R17="",K17,R17)-S17,0))) | V17: =IF(B17="","",IF(M17<>"Ya","Tidak Perlu",IF(Q17="Ditolak","Ditolak",IF(S17=0,IF(Q17="Disetujui","Belum Dibayar","Belum Diajukan"),IF(T17=0,"Lunas","Dibayar Sebagian"))))) | Y17: =IF(B17="","",IF(AND(D17<>"",E17="ID TIDAK TERDAFTAR"),"PERKARA TIDAK VALID",IF(I17="","AKUN BELUM DIISI",IF(AND(M17="Ya",N17=""),"KLAIM BELUM DIHUBUNGKAN",IF(AND(N17<>"",COUNTIF(REIMBURSE!$A$5:$A$124,N17)=0),"ID KLAIM TIDAK TERDAFTAR",IF(Q17="Ditolak","PENGELUARAN DITOLAK",IF(R17>K17,"NILAI DISETUJUI MELEBIHI BIAYA",IF(AND(Q17="Disetujui",Z17=""),"PENYETUJU BELUM DIISI",IF(Q17<>"Disetujui","MENUNGGU PERSETUJUAN","OK"))))))))) | AC17: =IF(B17="","",IF(Q17="Ditolak","DITOLAK",IF(AND(Q17="Disetujui",R17>K17),"NILAI DISETUJUI MELEBIHI BIAYA",IF(AND(Q17="Disetujui",R17=""),"NILAI PERSETUJUAN BELUM DIISI",IF(AND(Q17="Disetujui",Z17<>""),"LENGKAP",IF(Q17="Disetujui","NAMA PENYETUJU BELUM DIISI","MENUNGGU PERSETUJUAN MANUAL"))))))
A18: =IF(B18="","","EXP-"&TEXT(B18,"yyyymmdd")&"-"&TEXT(ROW()-4,"000")) | C18: =IF(B18="","",TEXT(B18,"yyyy-mm")) | E18: =IF(D18="","",IFERROR(INDEX(PERKARA!$B$5:$B$104,MATCH(D18,PERKARA!$A$5:$A$104,0)),"ID TIDAK TERDAFTAR")) | T18: =IF(B18="","",IF(M18<>"Ya",0,MAX(IF(R18="",K18,R18)-S18,0))) | V18: =IF(B18="","",IF(M18<>"Ya","Tidak Perlu",IF(Q18="Ditolak","Ditolak",IF(S18=0,IF(Q18="Disetujui","Belum Dibayar","Belum Diajukan"),IF(T18=0,"Lunas","Dibayar Sebagian"))))) | Y18: =IF(B18="","",IF(AND(D18<>"",E18="ID TIDAK TERDAFTAR"),"PERKARA TIDAK VALID",IF(I18="","AKUN BELUM DIISI",IF(AND(M18="Ya",N18=""),"KLAIM BELUM DIHUBUNGKAN",IF(AND(N18<>"",COUNTIF(REIMBURSE!$A$5:$A$124,N18)=0),"ID KLAIM TIDAK TERDAFTAR",IF(Q18="Ditolak","PENGELUARAN DITOLAK",IF(R18>K18,"NILAI DISETUJUI MELEBIHI BIAYA",IF(AND(Q18="Disetujui",Z18=""),"PENYETUJU BELUM DIISI",IF(Q18<>"Disetujui","MENUNGGU PERSETUJUAN","OK"))))))))) | AC18: =IF(B18="","",IF(Q18="Ditolak","DITOLAK",IF(AND(Q18="Disetujui",R18>K18),"NILAI DISETUJUI MELEBIHI BIAYA",IF(AND(Q18="Disetujui",R18=""),"NILAI PERSETUJUAN BELUM DIISI",IF(AND(Q18="Disetujui",Z18<>""),"LENGKAP",IF(Q18="Disetujui","NAMA PENYETUJU BELUM DIISI","MENUNGGU PERSETUJUAN MANUAL"))))))
A19: =IF(B19="","","EXP-"&TEXT(B19,"yyyymmdd")&"-"&TEXT(ROW()-4,"000")) | C19: =IF(B19="","",TEXT(B19,"yyyy-mm")) | E19: =IF(D19="","",IFERROR(INDEX(PERKARA!$B$5:$B$104,MATCH(D19,PERKARA!$A$5:$A$104,0)),"ID TIDAK TERDAFTAR")) | T19: =IF(B19="","",IF(M19<>"Ya",0,MAX(IF(R19="",K19,R19)-S19,0))) | V19: =IF(B19="","",IF(M19<>"Ya","Tidak Perlu",IF(Q19="Ditolak","Ditolak",IF(S19=0,IF(Q19="Disetujui","Belum Dibayar","Belum Diajukan"),IF(T19=0,"Lunas","Dibayar Sebagian"))))) | Y19: =IF(B19="","",IF(AND(D19<>"",E19="ID TIDAK TERDAFTAR"),"PERKARA TIDAK VALID",IF(I19="","AKUN BELUM DIISI",IF(AND(M19="Ya",N19=""),"KLAIM BELUM DIHUBUNGKAN",IF(AND(N19<>"",COUNTIF(REIMBURSE!$A$5:$A$124,N19)=0),"ID KLAIM TIDAK TERDAFTAR",IF(Q19="Ditolak","PENGELUARAN DITOLAK",IF(R19>K19,"NILAI DISETUJUI MELEBIHI BIAYA",IF(AND(Q19="Disetujui",Z19=""),"PENYETUJU BELUM DIISI",IF(Q19<>"Disetujui","MENUNGGU PERSETUJUAN","OK"))))))))) | AC19: =IF(B19="","",IF(Q19="Ditolak","DITOLAK",IF(AND(Q19="Disetujui",R19>K19),"NILAI DISETUJUI MELEBIHI BIAYA",IF(AND(Q19="Disetujui",R19=""),"NILAI PERSETUJUAN BELUM DIISI",IF(AND(Q19="Disetujui",Z19<>""),"LENGKAP",IF(Q19="Disetujui","NAMA PENYETUJU BELUM DIISI","MENUNGGU PERSETUJUAN MANUAL"))))))
A20: =IF(B20="","","EXP-"&TEXT(B20,"yyyymmdd")&"-"&TEXT(ROW()-4,"000")) | C20: =IF(B20="","",TEXT(B20,"yyyy-mm")) | E20: =IF(D20="","",IFERROR(INDEX(PERKARA!$B$5:$B$104,MATCH(D20,PERKARA!$A$5:$A$104,0)),"ID TIDAK TERDAFTAR")) | T20: =IF(B20="","",IF(M20<>"Ya",0,MAX(IF(R20="",K20,R20)-S20,0))) | V20: =IF(B20="","",IF(M20<>"Ya","Tidak Perlu",IF(Q20="Ditolak","Ditolak",IF(S20=0,IF(Q20="Disetujui","Belum Dibayar","Belum Diajukan"),IF(T20=0,"Lunas","Dibayar Sebagian"))))) | Y20: =IF(B20="","",IF(AND(D20<>"",E20="ID TIDAK TERDAFTAR"),"PERKARA TIDAK VALID",IF(I20="","AKUN BELUM DIISI",IF(AND(M20="Ya",N20=""),"KLAIM BELUM DIHUBUNGKAN",IF(AND(N20<>"",COUNTIF(REIMBURSE!$A$5:$A$124,N20)=0),"ID KLAIM TIDAK TERDAFTAR",IF(Q20="Ditolak","PENGELUARAN DITOLAK",IF(R20>K20,"NILAI DISETUJUI MELEBIHI BIAYA",IF(AND(Q20="Disetujui",Z20=""),"PENYETUJU BELUM DIISI",IF(Q20<>"Disetujui","MENUNGGU PERSETUJUAN","OK"))))))))) | AC20: =IF(B20="","",IF(Q20="Ditolak","DITOLAK",IF(AND(Q20="Disetujui",R20>K20),"NILAI DISETUJUI MELEBIHI BIAYA",IF(AND(Q20="Disetujui",R20=""),"NILAI PERSETUJUAN BELUM DIISI",IF(AND(Q20="Disetujui",Z20<>""),"LENGKAP",IF(Q20="Disetujui","NAMA PENYETUJU BELUM DIISI","MENUNGGU PERSETUJUAN MANUAL"))))))
A21: =IF(B21="","","EXP-"&TEXT(B21,"yyyymmdd")&"-"&TEXT(ROW()-4,"000")) | C21: =IF(B21="","",TEXT(B21,"yyyy-mm")) | E21: =IF(D21="","",IFERROR(INDEX(PERKARA!$B$5:$B$104,MATCH(D21,PERKARA!$A$5:$A$104,0)),"ID TIDAK TERDAFTAR")) | T21: =IF(B21="","",IF(M21<>"Ya",0,MAX(IF(R21="",K21,R21)-S21,0))) | V21: =IF(B21="","",IF(M21<>"Ya","Tidak Perlu",IF(Q21="Ditolak","Ditolak",IF(S21=0,IF(Q21="Disetujui","Belum Dibayar","Belum Diajukan"),IF(T21=0,"Lunas","Dibayar Sebagian"))))) | Y21: =IF(B21="","",IF(AND(D21<>"",E21="ID TIDAK TERDAFTAR"),"PERKARA TIDAK VALID",IF(I21="","AKUN BELUM DIISI",IF(AND(M21="Ya",N21=""),"KLAIM BELUM DIHUBUNGKAN",IF(AND(N21<>"",COUNTIF(REIMBURSE!$A$5:$A$124,N21)=0),"ID KLAIM TIDAK TERDAFTAR",IF(Q21="Ditolak","PENGELUARAN DITOLAK",IF(R21>K21,"NILAI DISETUJUI MELEBIHI BIAYA",IF(AND(Q21="Disetujui",Z21=""),"PENYETUJU BELUM DIISI",IF(Q21<>"Disetujui","MENUNGGU PERSETUJUAN","OK"))))))))) | AC21: =IF(B21="","",IF(Q21="Ditolak","DITOLAK",IF(AND(Q21="Disetujui",R21>K21),"NILAI DISETUJUI MELEBIHI BIAYA",IF(AND(Q21="Disetujui",R21=""),"NILAI PERSETUJUAN BELUM DIISI",IF(AND(Q21="Disetujui",Z21<>""),"LENGKAP",IF(Q21="Disetujui","NAMA PENYETUJU BELUM DIISI","MENUNGGU PERSETUJUAN MANUAL"))))))
A22: =IF(B22="","","EXP-"&TEXT(B22,"yyyymmdd")&"-"&TEXT(ROW()-4,"000")) | C22: =IF(B22="","",TEXT(B22,"yyyy-mm")) | E22: =IF(D22="","",IFERROR(INDEX(PERKARA!$B$5:$B$104,MATCH(D22,PERKARA!$A$5:$A$104,0)),"ID TIDAK TERDAFTAR")) | T22: =IF(B22="","",IF(M22<>"Ya",0,MAX(IF(R22="",K22,R22)-S22,0))) | V22: =IF(B22="","",IF(M22<>"Ya","Tidak Perlu",IF(Q22="Ditolak","Ditolak",IF(S22=0,IF(Q22="Disetujui","Belum Dibayar","Belum Diajukan"),IF(T22=0,"Lunas","Dibayar Sebagian"))))) | Y22: =IF(B22="","",IF(AND(D22<>"",E22="ID TIDAK TERDAFTAR"),"PERKARA TIDAK VALID",IF(I22="","AKUN BELUM DIISI",IF(AND(M22="Ya",N22=""),"KLAIM BELUM DIHUBUNGKAN",IF(AND(N22<>"",COUNTIF(REIMBURSE!$A$5:$A$124,N22)=0),"ID KLAIM TIDAK TERDAFTAR",IF(Q22="Ditolak","PENGELUARAN DITOLAK",IF(R22>K22,"NILAI DISETUJUI MELEBIHI BIAYA",IF(AND(Q22="Disetujui",Z22=""),"PENYETUJU BELUM DIISI",IF(Q22<>"Disetujui","MENUNGGU PERSETUJUAN","OK"))))))))) | AC22: =IF(B22="","",IF(Q22="Ditolak","DITOLAK",IF(AND(Q22="Disetujui",R22>K22),"NILAI DISETUJUI MELEBIHI BIAYA",IF(AND(Q22="Disetujui",R22=""),"NILAI PERSETUJUAN BELUM DIISI",IF(AND(Q22="Disetujui",Z22<>""),"LENGKAP",IF(Q22="Disetujui","NAMA PENYETUJU BELUM DIISI","MENUNGGU PERSETUJUAN MANUAL"))))))
A23: =IF(B23="","","EXP-"&TEXT(B23,"yyyymmdd")&"-"&TEXT(ROW()-4,"000")) | C23: =IF(B23="","",TEXT(B23,"yyyy-mm")) | E23: =IF(D23="","",IFERROR(INDEX(PERKARA!$B$5:$B$104,MATCH(D23,PERKARA!$A$5:$A$104,0)),"ID TIDAK TERDAFTAR")) | T23: =IF(B23="","",IF(M23<>"Ya",0,MAX(IF(R23="",K23,R23)-S23,0))) | V23: =IF(B23="","",IF(M23<>"Ya","Tidak Perlu",IF(Q23="Ditolak","Ditolak",IF(S23=0,IF(Q23="Disetujui","Belum Dibayar","Belum Diajukan"),IF(T23=0,"Lunas","Dibayar Sebagian"))))) | Y23: =IF(B23="","",IF(AND(D23<>"",E23="ID TIDAK TERDAFTAR"),"PERKARA TIDAK VALID",IF(I23="","AKUN BELUM DIISI",IF(AND(M23="Ya",N23=""),"KLAIM BELUM DIHUBUNGKAN",IF(AND(N23<>"",COUNTIF(REIMBURSE!$A$5:$A$124,N23)=0),"ID KLAIM TIDAK TERDAFTAR",IF(Q23="Ditolak","PENGELUARAN DITOLAK",IF(R23>K23,"NILAI DISETUJUI MELEBIHI BIAYA",IF(AND(Q23="Disetujui",Z23=""),"PENYETUJU BELUM DIISI",IF(Q23<>"Disetujui","MENUNGGU PERSETUJUAN","OK"))))))))) | AC23: =IF(B23="","",IF(Q23="Ditolak","DITOLAK",IF(AND(Q23="Disetujui",R23>K23),"NILAI DISETUJUI MELEBIHI BIAYA",IF(AND(Q23="Disetujui",R23=""),"NILAI PERSETUJUAN BELUM DIISI",IF(AND(Q23="Disetujui",Z23<>""),"LENGKAP",IF(Q23="Disetujui","NAMA PENYETUJU BELUM DIISI","MENUNGGU PERSETUJUAN MANUAL"))))))
A24: =IF(B24="","","EXP-"&TEXT(B24,"yyyymmdd")&"-"&TEXT(ROW()-4,"000")) | C24: =IF(B24="","",TEXT(B24,"yyyy-mm")) | E24: =IF(D24="","",IFERROR(INDEX(PERKARA!$B$5:$B$104,MATCH(D24,PERKARA!$A$5:$A$104,0)),"ID TIDAK TERDAFTAR")) | T24: =IF(B24="","",IF(M24<>"Ya",0,MAX(IF(R24="",K24,R24)-S24,0))) | V24: =IF(B24="","",IF(M24<>"Ya","Tidak Perlu",IF(Q24="Ditolak","Ditolak",IF(S24=0,IF(Q24="Disetujui","Belum Dibayar","Belum Diajukan"),IF(T24=0,"Lunas","Dibayar Sebagian"))))) | Y24: =IF(B24="","",IF(AND(D24<>"",E24="ID TIDAK TERDAFTAR"),"PERKARA TIDAK VALID",IF(I24="","AKUN BELUM DIISI",IF(AND(M24="Ya",N24=""),"KLAIM BELUM DIHUBUNGKAN",IF(AND(N24<>"",COUNTIF(REIMBURSE!$A$5:$A$124,N24)=0),"ID KLAIM TIDAK TERDAFTAR",IF(Q24="Ditolak","PENGELUARAN DITOLAK",IF(R24>K24,"NILAI DISETUJUI MELEBIHI BIAYA",IF(AND(Q24="Disetujui",Z24=""),"PENYETUJU BELUM DIISI",IF(Q24<>"Disetujui","MENUNGGU PERSETUJUAN","OK"))))))))) | AC24: =IF(B24="","",IF(Q24="Ditolak","DITOLAK",IF(AND(Q24="Disetujui",R24>K24),"NILAI DISETUJUI MELEBIHI BIAYA",IF(AND(Q24="Disetujui",R24=""),"NILAI PERSETUJUAN BELUM DIISI",IF(AND(Q24="Disetujui",Z24<>""),"LENGKAP",IF(Q24="Disetujui","NAMA PENYETUJU BELUM DIISI","MENUNGGU PERSETUJUAN MANUAL"))))))
A25: =IF(B25="","","EXP-"&TEXT(B25,"yyyymmdd")&"-"&TEXT(ROW()-4,"000")) | C25: =IF(B25="","",TEXT(B25,"yyyy-mm")) | E25: =IF(D25="","",IFERROR(INDEX(PERKARA!$B$5:$B$104,MATCH(D25,PERKARA!$A$5:$A$104,0)),"ID TIDAK TERDAFTAR")) | T25: =IF(B25="","",IF(M25<>"Ya",0,MAX(IF(R25="",K25,R25)-S25,0))) | V25: =IF(B25="","",IF(M25<>"Ya","Tidak Perlu",IF(Q25="Ditolak","Ditolak",IF(S25=0,IF(Q25="Disetujui","Belum Dibayar","Belum Diajukan"),IF(T25=0,"Lunas","Dibayar Sebagian"))))) | Y25: =IF(B25="","",IF(AND(D25<>"",E25="ID TIDAK TERDAFTAR"),"PERKARA TIDAK VALID",IF(I25="","AKUN BELUM DIISI",IF(AND(M25="Ya",N25=""),"KLAIM BELUM DIHUBUNGKAN",IF(AND(N25<>"",COUNTIF(REIMBURSE!$A$5:$A$124,N25)=0),"ID KLAIM TIDAK TERDAFTAR",IF(Q25="Ditolak","PENGELUARAN DITOLAK",IF(R25>K25,"NILAI DISETUJUI MELEBIHI BIAYA",IF(AND(Q25="Disetujui",Z25=""),"PENYETUJU BELUM DIISI",IF(Q25<>"Disetujui","MENUNGGU PERSETUJUAN","OK"))))))))) | AC25: =IF(B25="","",IF(Q25="Ditolak","DITOLAK",IF(AND(Q25="Disetujui",R25>K25),"NILAI DISETUJUI MELEBIHI BIAYA",IF(AND(Q25="Disetujui",R25=""),"NILAI PERSETUJUAN BELUM DIISI",IF(AND(Q25="Disetujui",Z25<>""),"LENGKAP",IF(Q25="Disetujui","NAMA PENYETUJU BELUM DIISI","MENUNGGU PERSETUJUAN MANUAL"))))))
A26: =IF(B26="","","EXP-"&TEXT(B26,"yyyymmdd")&"-"&TEXT(ROW()-4,"000")) | C26: =IF(B26="","",TEXT(B26,"yyyy-mm")) | E26: =IF(D26="","",IFERROR(INDEX(PERKARA!$B$5:$B$104,MATCH(D26,PERKARA!$A$5:$A$104,0)),"ID TIDAK TERDAFTAR")) | T26: =IF(B26="","",IF(M26<>"Ya",0,MAX(IF(R26="",K26,R26)-S26,0))) | V26: =IF(B26="","",IF(M26<>"Ya","Tidak Perlu",IF(Q26="Ditolak","Ditolak",IF(S26=0,IF(Q26="Disetujui","Belum Dibayar","Belum Diajukan"),IF(T26=0,"Lunas","Dibayar Sebagian"))))) | Y26: =IF(B26="","",IF(AND(D26<>"",E26="ID TIDAK TERDAFTAR"),"PERKARA TIDAK VALID",IF(I26="","AKUN BELUM DIISI",IF(AND(M26="Ya",N26=""),"KLAIM BELUM DIHUBUNGKAN",IF(AND(N26<>"",COUNTIF(REIMBURSE!$A$5:$A$124,N26)=0),"ID KLAIM TIDAK TERDAFTAR",IF(Q26="Ditolak","PENGELUARAN DITOLAK",IF(R26>K26,"NILAI DISETUJUI MELEBIHI BIAYA",IF(AND(Q26="Disetujui",Z26=""),"PENYETUJU BELUM DIISI",IF(Q26<>"Disetujui","MENUNGGU PERSETUJUAN","OK"))))))))) | AC26: =IF(B26="","",IF(Q26="Ditolak","DITOLAK",IF(AND(Q26="Disetujui",R26>K26),"NILAI DISETUJUI MELEBIHI BIAYA",IF(AND(Q26="Disetujui",R26=""),"NILAI PERSETUJUAN BELUM DIISI",IF(AND(Q26="Disetujui",Z26<>""),"LENGKAP",IF(Q26="Disetujui","NAMA PENYETUJU BELUM DIISI","MENUNGGU PERSETUJUAN MANUAL"))))))
A27: =IF(B27="","","EXP-"&TEXT(B27,"yyyymmdd")&"-"&TEXT(ROW()-4,"000")) | C27: =IF(B27="","",TEXT(B27,"yyyy-mm")) | E27: =IF(D27="","",IFERROR(INDEX(PERKARA!$B$5:$B$104,MATCH(D27,PERKARA!$A$5:$A$104,0)),"ID TIDAK TERDAFTAR")) | T27: =IF(B27="","",IF(M27<>"Ya",0,MAX(IF(R27="",K27,R27)-S27,0))) | V27: =IF(B27="","",IF(M27<>"Ya","Tidak Perlu",IF(Q27="Ditolak","Ditolak",IF(S27=0,IF(Q27="Disetujui","Belum Dibayar","Belum Diajukan"),IF(T27=0,"Lunas","Dibayar Sebagian"))))) | Y27: =IF(B27="","",IF(AND(D27<>"",E27="ID TIDAK TERDAFTAR"),"PERKARA TIDAK VALID",IF(I27="","AKUN BELUM DIISI",IF(AND(M27="Ya",N27=""),"KLAIM BELUM DIHUBUNGKAN",IF(AND(N27<>"",COUNTIF(REIMBURSE!$A$5:$A$124,N27)=0),"ID KLAIM TIDAK TERDAFTAR",IF(Q27="Ditolak","PENGELUARAN DITOLAK",IF(R27>K27,"NILAI DISETUJUI MELEBIHI BIAYA",IF(AND(Q27="Disetujui",Z27=""),"PENYETUJU BELUM DIISI",IF(Q27<>"Disetujui","MENUNGGU PERSETUJUAN","OK"))))))))) | AC27: =IF(B27="","",IF(Q27="Ditolak","DITOLAK",IF(AND(Q27="Disetujui",R27>K27),"NILAI DISETUJUI MELEBIHI BIAYA",IF(AND(Q27="Disetujui",R27=""),"NILAI PERSETUJUAN BELUM DIISI",IF(AND(Q27="Disetujui",Z27<>""),"LENGKAP",IF(Q27="Disetujui","NAMA PENYETUJU BELUM DIISI","MENUNGGU PERSETUJUAN MANUAL"))))))
... A204: =IF(B204="","","EXP-"&TEXT(B204,"yyyymmdd")&"-"&TEXT(ROW()-4,"000")) | C204: =IF(B204="","",TEXT(B204,"yyyy-mm")) | E204: =IF(D204="","",IFERROR(INDEX(PERKARA!$B$5:$B$104,MATCH(D204,PERKARA!$A$5:$A$104,0)),"ID TIDAK TERDAFTAR")) | T204: =IF(B204="","",IF(M204<>"Ya",0,MAX(IF(R204="",K204,R204)-S204,0))) | V204: =IF(B204="","",IF(M204<>"Ya","Tidak Perlu",IF(Q204="Ditolak","Ditolak",IF(S204=0,IF(Q204="Disetujui","Belum Dibayar","Belum Diajukan"),IF(T204=0,"Lunas","Dibayar Sebagian"))))) | Y204: =IF(B204="","",IF(AND(D204<>"",E204="ID TIDAK TERDAFTAR"),"PERKARA TIDAK VALID",IF(I204="","AKUN BELUM DIISI",IF(AND(M204="Ya",N204=""),"KLAIM BELUM DIHUBUNGKAN",IF(AND(N204<>"",COUNTIF(REIMBURSE!$A$5:$A$124,N204)=0),"ID KLAIM TIDAK TERDAFTAR",IF(Q204="Ditolak","PENGELUARAN DITOLAK",IF(R204>K204,"NILAI DISETUJUI MELEBIHI BIAYA",IF(AND(Q204="Disetujui",Z204=""),"PENYETUJU BELUM DIISI",IF(Q204<>"Disetujui","MENUNGGU PERSETUJUAN","OK"))))))))) | AC204: =IF(B204="","",IF(Q204="Ditolak","DITOLAK",IF(AND(Q204="Disetujui",R204>K204),"NILAI DISETUJUI MELEBIHI BIAYA",IF(AND(Q204="Disetujui",R204=""),"NILAI PERSETUJUAN BELUM DIISI",IF(AND(Q204="Disetujui",Z204<>""),"LENGKAP",IF(Q204="Disetujui","NAMA PENYETUJU BELUM DIISI","MENUNGGU PERSETUJUAN MANUAL"))))))

Sheet KAS_BANK
A1: R | P | K KAS, BANK & REKONSILIASI | B1: R | P | K KAS, BANK & REKONSILIASI | C1: R | P | K KAS, BANK & REKONSILIASI | D1: R | P | K KAS, BANK & REKONSILIASI | E1: R | P | K KAS, BANK & REKONSILIASI | F1: R | P | K KAS, BANK & REKONSILIASI | G1: R | P | K KAS, BANK & REKONSILIASI | H1: R | P | K KAS, BANK & REKONSILIASI | I1: R | P | K KAS, BANK & REKONSILIASI | J1: R | P | K KAS, BANK & REKONSILIASI | K1: R | P | K KAS, BANK & REKONSILIASI | L1: R | P | K KAS, BANK & REKONSILIASI | M1: R | P | K KAS, BANK & REKONSILIASI | N1: R | P | K KAS, BANK & REKONSILIASI | O1: R | P | K KAS, BANK & REKONSILIASI | P1: R | P | K KAS, BANK & REKONSILIASI | Q1: R | P | K KAS, BANK & REKONSILIASI
A2: R | P | K KAS, BANK & REKONSILIASI | B2: R | P | K KAS, BANK & REKONSILIASI | C2: R | P | K KAS, BANK & REKONSILIASI | D2: R | P | K KAS, BANK & REKONSILIASI | E2: R | P | K KAS, BANK & REKONSILIASI | F2: R | P | K KAS, BANK & REKONSILIASI | G2: R | P | K KAS, BANK & REKONSILIASI | H2: R | P | K KAS, BANK & REKONSILIASI | I2: R | P | K KAS, BANK & REKONSILIASI | J2: R | P | K KAS, BANK & REKONSILIASI | K2: R | P | K KAS, BANK & REKONSILIASI | L2: R | P | K KAS, BANK & REKONSILIASI | M2: R | P | K KAS, BANK & REKONSILIASI | N2: R | P | K KAS, BANK & REKONSILIASI | O2: R | P | K KAS, BANK & REKONSILIASI | P2: R | P | K KAS, BANK & REKONSILIASI | Q2: R | P | K KAS, BANK & REKONSILIASI
A3: Saldo awal bersumber dari SALDO_AWAL_2027. Saldo akun partner negatif adalah talangan, bukan kas fisik negatif. Isi saldo pembukaan hanya pada sheet SALDO_AWAL_2027. | B3: Saldo Awal hanya diisi sekali pada awal tahun. Saldo buku menghitung seluruh transaksi tahun berjalan; saldo antarbulan dapat dilihat pada ARUS_KAS. Isi saldo fisik/rekening saat rekonsiliasi. | C3: Saldo Awal hanya diisi sekali pada awal tahun. Saldo buku menghitung seluruh transaksi tahun berjalan; saldo antarbulan dapat dilihat pada ARUS_KAS. Isi saldo fisik/rekening saat rekonsiliasi. | D3: Saldo Awal hanya diisi sekali pada awal tahun. Saldo buku menghitung seluruh transaksi tahun berjalan; saldo antarbulan dapat dilihat pada ARUS_KAS. Isi saldo fisik/rekening saat rekonsiliasi. | E3: Saldo Awal hanya diisi sekali pada awal tahun. Saldo buku menghitung seluruh transaksi tahun berjalan; saldo antarbulan dapat dilihat pada ARUS_KAS. Isi saldo fisik/rekening saat rekonsiliasi. | F3: Saldo Awal hanya diisi sekali pada awal tahun. Saldo buku menghitung seluruh transaksi tahun berjalan; saldo antarbulan dapat dilihat pada ARUS_KAS. Isi saldo fisik/rekening saat rekonsiliasi. | G3: Saldo Awal hanya diisi sekali pada awal tahun. Saldo buku menghitung seluruh transaksi tahun berjalan; saldo antarbulan dapat dilihat pada ARUS_KAS. Isi saldo fisik/rekening saat rekonsiliasi. | H3: Saldo Awal hanya diisi sekali pada awal tahun. Saldo buku menghitung seluruh transaksi tahun berjalan; saldo antarbulan dapat dilihat pada ARUS_KAS. Isi saldo fisik/rekening saat rekonsiliasi. | I3: Saldo Awal hanya diisi sekali pada awal tahun. Saldo buku menghitung seluruh transaksi tahun berjalan; saldo antarbulan dapat dilihat pada ARUS_KAS. Isi saldo fisik/rekening saat rekonsiliasi. | J3: Saldo Awal hanya diisi sekali pada awal tahun. Saldo buku menghitung seluruh transaksi tahun berjalan; saldo antarbulan dapat dilihat pada ARUS_KAS. Isi saldo fisik/rekening saat rekonsiliasi. | K3: Saldo Awal hanya diisi sekali pada awal tahun. Saldo buku menghitung seluruh transaksi tahun berjalan; saldo antarbulan dapat dilihat pada ARUS_KAS. Isi saldo fisik/rekening saat rekonsiliasi. | L3: Saldo Awal hanya diisi sekali pada awal tahun. Saldo buku menghitung seluruh transaksi tahun berjalan; saldo antarbulan dapat dilihat pada ARUS_KAS. Isi saldo fisik/rekening saat rekonsiliasi. | M3: Saldo Awal hanya diisi sekali pada awal tahun. Saldo buku menghitung seluruh transaksi tahun berjalan; saldo antarbulan dapat dilihat pada ARUS_KAS. Isi saldo fisik/rekening saat rekonsiliasi. | N3: Saldo Awal hanya diisi sekali pada awal tahun. Saldo buku menghitung seluruh transaksi tahun berjalan; saldo antarbulan dapat dilihat pada ARUS_KAS. Isi saldo fisik/rekening saat rekonsiliasi. | O3: Saldo Awal hanya diisi sekali pada awal tahun. Saldo buku menghitung seluruh transaksi tahun berjalan; saldo antarbulan dapat dilihat pada ARUS_KAS. Isi saldo fisik/rekening saat rekonsiliasi. | P3: Saldo Awal hanya diisi sekali pada awal tahun. Saldo buku menghitung seluruh transaksi tahun berjalan; saldo antarbulan dapat dilihat pada ARUS_KAS. Isi saldo fisik/rekening saat rekonsiliasi. | Q3: Saldo Awal hanya diisi sekali pada awal tahun. Saldo buku menghitung seluruh transaksi tahun berjalan; saldo antarbulan dapat dilihat pada ARUS_KAS. Isi saldo fisik/rekening saat rekonsiliasi.
A4: Akun Kas / Bank | B4: Saldo Awal | C4: Seluruh Pemasukan | D4: Pengeluaran Langsung | E4: Gaji Bersih Dibayar | F4: Reimburse Dibayar | G4: Dana Klien Keluar | H4: Pembayaran Partner | I4: Pembayaran Kewajiban | J4: Transfer Masuk | K4: Transfer Keluar | L4: Saldo Menurut Buku | M4: Saldo Fisik / Rekening | N4: Selisih Rekonsiliasi | O4: Status | P4: Tanggal Rekonsiliasi | Q4: Catatan | R4: Pemulihan Talangan | S4: Kas Tersedia | T4: Talangan Partner
A5: Kas Kantor | B5: =SALDO_AWAL_2026!B9 -> 0 | C5: =SUMIFS(PEMASUKAN!$J$5:$J$204,PEMASUKAN!$K$5:$K$204,A5) -> 16000000 | D5: =SUMIFS(PENGELUARAN!$K$5:$K$204,PENGELUARAN!$I$5:$I$204,A5) -> 4095908 | E5: =SUMIFS(GAJI!$P$5:$P$124,GAJI!$T$5:$T$124,A5,GAJI!$R$5:$R$124,"Dibayar") -> 0 | F5: =SUMIFS(REIMBURSE!$J$5:$J$124,REIMBURSE!$O$5:$O$124,A5) -> 0 | G5: =SUMIFS(DANA_KLIEN!$H$5:$H$154,DANA_KLIEN!$J$5:$J$154,A5) -> 0 | H5: =SUMIFS(PARTNER!$I$5:$I$124,PARTNER!$L$5:$L$124,A5) -> 9000000 | I5: =SUMIFS(KEWAJIBAN!$F$5:$F$124,KEWAJIBAN!$J$5:$J$124,A5) -> 0 | J5: =SUMIFS(TRANSFER_KAS!$F$5:$F$204,TRANSFER_KAS!$E$5:$E$204,A5) -> 0 | K5: =SUMIFS(TRANSFER_KAS!$F$5:$F$204,TRANSFER_KAS!$D$5:$D$204,A5) -> 0 | L5: =B5+C5-SUM(D5:I5)+J5-K5+IF(R5="",0,R5) -> 2904092 | M5: 2904092 | N5: =IF(M5="","",M5-L5) -> 0 | O5: Belum Direkonsiliasi | R5: =IF(IF(A5=MASTER!$G$7,MASTER!$A$5,IF(A5=MASTER!$G$8,MASTER!$A$6,IF(A5=MASTER!$G$9,MASTER!$A$7,"")))="","",SUMIFS(REIMBURSE!$J$5:$J$124,REIMBURSE!$C$5:$C$124,IF(A5=MASTER!$G$7,MASTER!$A$5,IF(A5=MASTER!$G$8,MASTER!$A$6,IF(A5=MASTER!$G$9,MASTER!$A$7,""))))+SUMIFS(PARTNER!$I$5:$I$124,PARTNER!$D$5:$D$124,IF(A5=MASTER!$G$7,MASTER!$A$5,IF(A5=MASTER!$G$8,MASTER!$A$6,IF(A5=MASTER!$G$9,MASTER!$A$7,""))),PARTNER!$E$5:$E$124,"Pengembalian Talangan")) | S5: =IF(A5="Bank Dana Klien",0,MAX(L5,0)) -> 2904092 | T5: =IF(OR(A5=MASTER!$G$7,A5=MASTER!$G$8,A5=MASTER!$G$9),MAX(-L5,0),0) -> 0
A6: Bank Operasional | B6: =SALDO_AWAL_2026!B10 -> 0 | C6: =SUMIFS(PEMASUKAN!$J$5:$J$204,PEMASUKAN!$K$5:$K$204,A6) -> 0 | D6: =SUMIFS(PENGELUARAN!$K$5:$K$204,PENGELUARAN!$I$5:$I$204,A6) -> 0 | E6: =SUMIFS(GAJI!$P$5:$P$124,GAJI!$T$5:$T$124,A6,GAJI!$R$5:$R$124,"Dibayar") -> 0 | F6: =SUMIFS(REIMBURSE!$J$5:$J$124,REIMBURSE!$O$5:$O$124,A6) -> 0 | G6: =SUMIFS(DANA_KLIEN!$H$5:$H$154,DANA_KLIEN!$J$5:$J$154,A6) -> 0 | H6: =SUMIFS(PARTNER!$I$5:$I$124,PARTNER!$L$5:$L$124,A6) -> 0 | I6: =SUMIFS(KEWAJIBAN!$F$5:$F$124,KEWAJIBAN!$J$5:$J$124,A6) -> 0 | J6: =SUMIFS(TRANSFER_KAS!$F$5:$F$204,TRANSFER_KAS!$E$5:$E$204,A6) -> 0 | K6: =SUMIFS(TRANSFER_KAS!$F$5:$F$204,TRANSFER_KAS!$D$5:$D$204,A6) -> 0 | L6: =B6+C6-SUM(D6:I6)+J6-K6+IF(R6="",0,R6) -> 0 | M6: 0 | N6: =IF(M6="","",M6-L6) -> 0 | O6: Belum Direkonsiliasi | R6: =IF(IF(A6=MASTER!$G$7,MASTER!$A$5,IF(A6=MASTER!$G$8,MASTER!$A$6,IF(A6=MASTER!$G$9,MASTER!$A$7,"")))="","",SUMIFS(REIMBURSE!$J$5:$J$124,REIMBURSE!$C$5:$C$124,IF(A6=MASTER!$G$7,MASTER!$A$5,IF(A6=MASTER!$G$8,MASTER!$A$6,IF(A6=MASTER!$G$9,MASTER!$A$7,""))))+SUMIFS(PARTNER!$I$5:$I$124,PARTNER!$D$5:$D$124,IF(A6=MASTER!$G$7,MASTER!$A$5,IF(A6=MASTER!$G$8,MASTER!$A$6,IF(A6=MASTER!$G$9,MASTER!$A$7,""))),PARTNER!$E$5:$E$124,"Pengembalian Talangan")) | S6: =IF(A6="Bank Dana Klien",0,MAX(L6,0)) -> 0 | T6: =IF(OR(A6=MASTER!$G$7,A6=MASTER!$G$8,A6=MASTER!$G$9),MAX(-L6,0),0) -> 0
A7: Kas Fajar | B7: =SALDO_AWAL_2026!B11 -> 0 | C7: =SUMIFS(PEMASUKAN!$J$5:$J$204,PEMASUKAN!$K$5:$K$204,A7) -> 0 | D7: =SUMIFS(PENGELUARAN!$K$5:$K$204,PENGELUARAN!$I$5:$I$204,A7) -> 0 | E7: =SUMIFS(GAJI!$P$5:$P$124,GAJI!$T$5:$T$124,A7,GAJI!$R$5:$R$124,"Dibayar") -> 1000000 | F7: =SUMIFS(REIMBURSE!$J$5:$J$124,REIMBURSE!$O$5:$O$124,A7) -> 0 | G7: =SUMIFS(DANA_KLIEN!$H$5:$H$154,DANA_KLIEN!$J$5:$J$154,A7) -> 0 | H7: =SUMIFS(PARTNER!$I$5:$I$124,PARTNER!$L$5:$L$124,A7) -> 0 | I7: =SUMIFS(KEWAJIBAN!$F$5:$F$124,KEWAJIBAN!$J$5:$J$124,A7) -> 0 | J7: =SUMIFS(TRANSFER_KAS!$F$5:$F$204,TRANSFER_KAS!$E$5:$E$204,A7) -> 0 | K7: =SUMIFS(TRANSFER_KAS!$F$5:$F$204,TRANSFER_KAS!$D$5:$D$204,A7) -> 0 | L7: =B7+C7-SUM(D7:I7)+J7-K7+IF(R7="",0,R7) -> -1000000 | M7: 0 | N7: =IF(M7="","",M7-L7) -> 1000000 | O7: TALANGAN PARTNER | R7: =IF(IF(A7=MASTER!$G$7,MASTER!$A$5,IF(A7=MASTER!$G$8,MASTER!$A$6,IF(A7=MASTER!$G$9,MASTER!$A$7,"")))="","",SUMIFS(REIMBURSE!$J$5:$J$124,REIMBURSE!$C$5:$C$124,IF(A7=MASTER!$G$7,MASTER!$A$5,IF(A7=MASTER!$G$8,MASTER!$A$6,IF(A7=MASTER!$G$9,MASTER!$A$7,""))))+SUMIFS(PARTNER!$I$5:$I$124,PARTNER!$D$5:$D$124,IF(A7=MASTER!$G$7,MASTER!$A$5,IF(A7=MASTER!$G$8,MASTER!$A$6,IF(A7=MASTER!$G$9,MASTER!$A$7,""))),PARTNER!$E$5:$E$124,"Pengembalian Talangan")) -> 0 | S7: =IF(A7="Bank Dana Klien",0,MAX(L7,0)) -> 0 | T7: =IF(OR(A7=MASTER!$G$7,A7=MASTER!$G$8,A7=MASTER!$G$9),MAX(-L7,0),0) -> 1000000
A8: Kas Reza | B8: =SALDO_AWAL_2026!B12 -> 0 | C8: =SUMIFS(PEMASUKAN!$J$5:$J$204,PEMASUKAN!$K$5:$K$204,A8) -> 0 | D8: =SUMIFS(PENGELUARAN!$K$5:$K$204,PENGELUARAN!$I$5:$I$204,A8) -> 0 | E8: =SUMIFS(GAJI!$P$5:$P$124,GAJI!$T$5:$T$124,A8,GAJI!$R$5:$R$124,"Dibayar") -> 0 | F8: =SUMIFS(REIMBURSE!$J$5:$J$124,REIMBURSE!$O$5:$O$124,A8) -> 0 | G8: =SUMIFS(DANA_KLIEN!$H$5:$H$154,DANA_KLIEN!$J$5:$J$154,A8) -> 0 | H8: =SUMIFS(PARTNER!$I$5:$I$124,PARTNER!$L$5:$L$124,A8) -> 0 | I8: =SUMIFS(KEWAJIBAN!$F$5:$F$124,KEWAJIBAN!$J$5:$J$124,A8) -> 0 | J8: =SUMIFS(TRANSFER_KAS!$F$5:$F$204,TRANSFER_KAS!$E$5:$E$204,A8) -> 0 | K8: =SUMIFS(TRANSFER_KAS!$F$5:$F$204,TRANSFER_KAS!$D$5:$D$204,A8) -> 0 | L8: =B8+C8-SUM(D8:I8)+J8-K8+IF(R8="",0,R8) -> 0 | M8: 0 | N8: =IF(M8="","",M8-L8) -> 0 | O8: Belum Direkonsiliasi | R8: =IF(IF(A8=MASTER!$G$7,MASTER!$A$5,IF(A8=MASTER!$G$8,MASTER!$A$6,IF(A8=MASTER!$G$9,MASTER!$A$7,"")))="","",SUMIFS(REIMBURSE!$J$5:$J$124,REIMBURSE!$C$5:$C$124,IF(A8=MASTER!$G$7,MASTER!$A$5,IF(A8=MASTER!$G$8,MASTER!$A$6,IF(A8=MASTER!$G$9,MASTER!$A$7,""))))+SUMIFS(PARTNER!$I$5:$I$124,PARTNER!$D$5:$D$124,IF(A8=MASTER!$G$7,MASTER!$A$5,IF(A8=MASTER!$G$8,MASTER!$A$6,IF(A8=MASTER!$G$9,MASTER!$A$7,""))),PARTNER!$E$5:$E$124,"Pengembalian Talangan")) -> 0 | S8: =IF(A8="Bank Dana Klien",0,MAX(L8,0)) -> 0 | T8: =IF(OR(A8=MASTER!$G$7,A8=MASTER!$G$8,A8=MASTER!$G$9),MAX(-L8,0),0) -> 0
A9: Kas Anggara | B9: =SALDO_AWAL_2026!B13 -> 0 | C9: =SUMIFS(PEMASUKAN!$J$5:$J$204,PEMASUKAN!$K$5:$K$204,A9) -> 0 | D9: =SUMIFS(PENGELUARAN!$K$5:$K$204,PENGELUARAN!$I$5:$I$204,A9) -> 0 | E9: =SUMIFS(GAJI!$P$5:$P$124,GAJI!$T$5:$T$124,A9,GAJI!$R$5:$R$124,"Dibayar") -> 0 | F9: =SUMIFS(REIMBURSE!$J$5:$J$124,REIMBURSE!$O$5:$O$124,A9) -> 0 | G9: =SUMIFS(DANA_KLIEN!$H$5:$H$154,DANA_KLIEN!$J$5:$J$154,A9) -> 0 | H9: =SUMIFS(PARTNER!$I$5:$I$124,PARTNER!$L$5:$L$124,A9) -> 0 | I9: =SUMIFS(KEWAJIBAN!$F$5:$F$124,KEWAJIBAN!$J$5:$J$124,A9) -> 0 | J9: =SUMIFS(TRANSFER_KAS!$F$5:$F$204,TRANSFER_KAS!$E$5:$E$204,A9) -> 0 | K9: =SUMIFS(TRANSFER_KAS!$F$5:$F$204,TRANSFER_KAS!$D$5:$D$204,A9) -> 0 | L9: =B9+C9-SUM(D9:I9)+J9-K9+IF(R9="",0,R9) -> 0 | M9: 0 | N9: =IF(M9="","",M9-L9) -> 0 | O9: Belum Direkonsiliasi | R9: =IF(IF(A9=MASTER!$G$7,MASTER!$A$5,IF(A9=MASTER!$G$8,MASTER!$A$6,IF(A9=MASTER!$G$9,MASTER!$A$7,"")))="","",SUMIFS(REIMBURSE!$J$5:$J$124,REIMBURSE!$C$5:$C$124,IF(A9=MASTER!$G$7,MASTER!$A$5,IF(A9=MASTER!$G$8,MASTER!$A$6,IF(A9=MASTER!$G$9,MASTER!$A$7,""))))+SUMIFS(PARTNER!$I$5:$I$124,PARTNER!$D$5:$D$124,IF(A9=MASTER!$G$7,MASTER!$A$5,IF(A9=MASTER!$G$8,MASTER!$A$6,IF(A9=MASTER!$G$9,MASTER!$A$7,""))),PARTNER!$E$5:$E$124,"Pengembalian Talangan")) -> 0 | S9: =IF(A9="Bank Dana Klien",0,MAX(L9,0)) -> 0 | T9: =IF(OR(A9=MASTER!$G$7,A9=MASTER!$G$8,A9=MASTER!$G$9),MAX(-L9,0),0) -> 0
A10: Bank Dana Klien | B10: =SALDO_AWAL_2026!B14 -> 0 | C10: =SUMIFS(PEMASUKAN!$J$5:$J$204,PEMASUKAN!$K$5:$K$204,A10) -> 0 | D10: =SUMIFS(PENGELUARAN!$K$5:$K$204,PENGELUARAN!$I$5:$I$204,A10) -> 0 | E10: =SUMIFS(GAJI!$P$5:$P$124,GAJI!$T$5:$T$124,A10,GAJI!$R$5:$R$124,"Dibayar") -> 0 | F10: =SUMIFS(REIMBURSE!$J$5:$J$124,REIMBURSE!$O$5:$O$124,A10) -> 0 | G10: =SUMIFS(DANA_KLIEN!$H$5:$H$154,DANA_KLIEN!$J$5:$J$154,A10) -> 0 | H10: =SUMIFS(PARTNER!$I$5:$I$124,PARTNER!$L$5:$L$124,A10) -> 0 | I10: =SUMIFS(KEWAJIBAN!$F$5:$F$124,KEWAJIBAN!$J$5:$J$124,A10) -> 0 | J10: =SUMIFS(TRANSFER_KAS!$F$5:$F$204,TRANSFER_KAS!$E$5:$E$204,A10) -> 0 | K10: =SUMIFS(TRANSFER_KAS!$F$5:$F$204,TRANSFER_KAS!$D$5:$D$204,A10) -> 0 | L10: =B10+C10-SUM(D10:I10)+J10-K10+IF(R10="",0,R10) -> 0 | M10: 0 | N10: =IF(M10="","",M10-L10) -> 0 | O10: Belum Direkonsiliasi | R10: =IF(IF(A10=MASTER!$G$7,MASTER!$A$5,IF(A10=MASTER!$G$8,MASTER!$A$6,IF(A10=MASTER!$G$9,MASTER!$A$7,"")))="","",SUMIFS(REIMBURSE!$J$5:$J$124,REIMBURSE!$C$5:$C$124,IF(A10=MASTER!$G$7,MASTER!$A$5,IF(A10=MASTER!$G$8,MASTER!$A$6,IF(A10=MASTER!$G$9,MASTER!$A$7,""))))+SUMIFS(PARTNER!$I$5:$I$124,PARTNER!$D$5:$D$124,IF(A10=MASTER!$G$7,MASTER!$A$5,IF(A10=MASTER!$G$8,MASTER!$A$6,IF(A10=MASTER!$G$9,MASTER!$A$7,""))),PARTNER!$E$5:$E$124,"Pengembalian Talangan")) | S10: =IF(A10="Bank Dana Klien",0,MAX(L10,0)) -> 0 | T10: =IF(OR(A10=MASTER!$G$7,A10=MASTER!$G$8,A10=MASTER!$G$9),MAX(-L10,0),0) -> 0
A13: CATATAN PENGENDALIAN KAS | B13: CATATAN PENGENDALIAN KAS | C13: CATATAN PENGENDALIAN KAS | D13: CATATAN PENGENDALIAN KAS | E13: CATATAN PENGENDALIAN KAS | F13: CATATAN PENGENDALIAN KAS | G13: CATATAN PENGENDALIAN KAS | H13: CATATAN PENGENDALIAN KAS | I13: CATATAN PENGENDALIAN KAS | J13: CATATAN PENGENDALIAN KAS | K13: CATATAN PENGENDALIAN KAS | L13: CATATAN PENGENDALIAN KAS | M13: CATATAN PENGENDALIAN KAS | N13: CATATAN PENGENDALIAN KAS | O13: CATATAN PENGENDALIAN KAS | P13: CATATAN PENGENDALIAN KAS | Q13: CATATAN PENGENDALIAN KAS
A14: Dana di Bank Dana Klien harus diperlakukan sebagai dana terbatas, bukan kas bebas operasional. Isi kolom saldo fisik/rekening setelah memeriksa mutasi bank atau menghitung uang tunai. Transfer antar akun harus seimbang antara transfer masuk dan transfer keluar. | B14: Dana di Bank Dana Klien harus diperlakukan sebagai dana terbatas, bukan kas bebas operasional. Isi kolom saldo fisik/rekening setelah memeriksa mutasi bank atau menghitung uang tunai. Transfer antar akun harus seimbang antara transfer masuk dan transfer keluar. | C14: Dana di Bank Dana Klien harus diperlakukan sebagai dana terbatas, bukan kas bebas operasional. Isi kolom saldo fisik/rekening setelah memeriksa mutasi bank atau menghitung uang tunai. Transfer antar akun harus seimbang antara transfer masuk dan transfer keluar. | D14: Dana di Bank Dana Klien harus diperlakukan sebagai dana terbatas, bukan kas bebas operasional. Isi kolom saldo fisik/rekening setelah memeriksa mutasi bank atau menghitung uang tunai. Transfer antar akun harus seimbang antara transfer masuk dan transfer keluar. | E14: Dana di Bank Dana Klien harus diperlakukan sebagai dana terbatas, bukan kas bebas operasional. Isi kolom saldo fisik/rekening setelah memeriksa mutasi bank atau menghitung uang tunai. Transfer antar akun harus seimbang antara transfer masuk dan transfer keluar. | F14: Dana di Bank Dana Klien harus diperlakukan sebagai dana terbatas, bukan kas bebas operasional. Isi kolom saldo fisik/rekening setelah memeriksa mutasi bank atau menghitung uang tunai. Transfer antar akun harus seimbang antara transfer masuk dan transfer keluar. | G14: Dana di Bank Dana Klien harus diperlakukan sebagai dana terbatas, bukan kas bebas operasional. Isi kolom saldo fisik/rekening setelah memeriksa mutasi bank atau menghitung uang tunai. Transfer antar akun harus seimbang antara transfer masuk dan transfer keluar. | H14: Dana di Bank Dana Klien harus diperlakukan sebagai dana terbatas, bukan kas bebas operasional. Isi kolom saldo fisik/rekening setelah memeriksa mutasi bank atau menghitung uang tunai. Transfer antar akun harus seimbang antara transfer masuk dan transfer keluar. | I14: Dana di Bank Dana Klien harus diperlakukan sebagai dana terbatas, bukan kas bebas operasional. Isi kolom saldo fisik/rekening setelah memeriksa mutasi bank atau menghitung uang tunai. Transfer antar akun harus seimbang antara transfer masuk dan transfer keluar. | J14: Dana di Bank Dana Klien harus diperlakukan sebagai dana terbatas, bukan kas bebas operasional. Isi kolom saldo fisik/rekening setelah memeriksa mutasi bank atau menghitung uang tunai. Transfer antar akun harus seimbang antara transfer masuk dan transfer keluar. | K14: Dana di Bank Dana Klien harus diperlakukan sebagai dana terbatas, bukan kas bebas operasional. Isi kolom saldo fisik/rekening setelah memeriksa mutasi bank atau menghitung uang tunai. Transfer antar akun harus seimbang antara transfer masuk dan transfer keluar. | L14: Dana di Bank Dana Klien harus diperlakukan sebagai dana terbatas, bukan kas bebas operasional. Isi kolom saldo fisik/rekening setelah memeriksa mutasi bank atau menghitung uang tunai. Transfer antar akun harus seimbang antara transfer masuk dan transfer keluar. | M14: Dana di Bank Dana Klien harus diperlakukan sebagai dana terbatas, bukan kas bebas operasional. Isi kolom saldo fisik/rekening setelah memeriksa mutasi bank atau menghitung uang tunai. Transfer antar akun harus seimbang antara transfer masuk dan transfer keluar. | N14: Dana di Bank Dana Klien harus diperlakukan sebagai dana terbatas, bukan kas bebas operasional. Isi kolom saldo fisik/rekening setelah memeriksa mutasi bank atau menghitung uang tunai. Transfer antar akun harus seimbang antara transfer masuk dan transfer keluar. | O14: Dana di Bank Dana Klien harus diperlakukan sebagai dana terbatas, bukan kas bebas operasional. Isi kolom saldo fisik/rekening setelah memeriksa mutasi bank atau menghitung uang tunai. Transfer antar akun harus seimbang antara transfer masuk dan transfer keluar. | P14: Dana di Bank Dana Klien harus diperlakukan sebagai dana terbatas, bukan kas bebas operasional. Isi kolom saldo fisik/rekening setelah memeriksa mutasi bank atau menghitung uang tunai. Transfer antar akun harus seimbang antara transfer masuk dan transfer keluar. | Q14: Dana di Bank Dana Klien harus diperlakukan sebagai dana terbatas, bukan kas bebas operasional. Isi kolom saldo fisik/rekening setelah memeriksa mutasi bank atau menghitung uang tunai. Transfer antar akun harus seimbang antara transfer masuk dan transfer keluar.
A15: Dana di Bank Dana Klien harus diperlakukan sebagai dana terbatas, bukan kas bebas operasional. Isi kolom saldo fisik/rekening setelah memeriksa mutasi bank atau menghitung uang tunai. Transfer antar akun harus seimbang antara transfer masuk dan transfer keluar. | B15: Dana di Bank Dana Klien harus diperlakukan sebagai dana terbatas, bukan kas bebas operasional. Isi kolom saldo fisik/rekening setelah memeriksa mutasi bank atau menghitung uang tunai. Transfer antar akun harus seimbang antara transfer masuk dan transfer keluar. | C15: Dana di Bank Dana Klien harus diperlakukan sebagai dana terbatas, bukan kas bebas operasional. Isi kolom saldo fisik/rekening setelah memeriksa mutasi bank atau menghitung uang tunai. Transfer antar akun harus seimbang antara transfer masuk dan transfer keluar. | D15: Dana di Bank Dana Klien harus diperlakukan sebagai dana terbatas, bukan kas bebas operasional. Isi kolom saldo fisik/rekening setelah memeriksa mutasi bank atau menghitung uang tunai. Transfer antar akun harus seimbang antara transfer masuk dan transfer keluar. | E15: Dana di Bank Dana Klien harus diperlakukan sebagai dana terbatas, bukan kas bebas operasional. Isi kolom saldo fisik/rekening setelah memeriksa mutasi bank atau menghitung uang tunai. Transfer antar akun harus seimbang antara transfer masuk dan transfer keluar. | F15: Dana di Bank Dana Klien harus diperlakukan sebagai dana terbatas, bukan kas bebas operasional. Isi kolom saldo fisik/rekening setelah memeriksa mutasi bank atau menghitung uang tunai. Transfer antar akun harus seimbang antara transfer masuk dan transfer keluar. | G15: Dana di Bank Dana Klien harus diperlakukan sebagai dana terbatas, bukan kas bebas operasional. Isi kolom saldo fisik/rekening setelah memeriksa mutasi bank atau menghitung uang tunai. Transfer antar akun harus seimbang antara transfer masuk dan transfer keluar. | H15: Dana di Bank Dana Klien harus diperlakukan sebagai dana terbatas, bukan kas bebas operasional. Isi kolom saldo fisik/rekening setelah memeriksa mutasi bank atau menghitung uang tunai. Transfer antar akun harus seimbang antara transfer masuk dan transfer keluar. | I15: Dana di Bank Dana Klien harus diperlakukan sebagai dana terbatas, bukan kas bebas operasional. Isi kolom saldo fisik/rekening setelah memeriksa mutasi bank atau menghitung uang tunai. Transfer antar akun harus seimbang antara transfer masuk dan transfer keluar. | J15: Dana di Bank Dana Klien harus diperlakukan sebagai dana terbatas, bukan kas bebas operasional. Isi kolom saldo fisik/rekening setelah memeriksa mutasi bank atau menghitung uang tunai. Transfer antar akun harus seimbang antara transfer masuk dan transfer keluar. | K15: Dana di Bank Dana Klien harus diperlakukan sebagai dana terbatas, bukan kas bebas operasional. Isi kolom saldo fisik/rekening setelah memeriksa mutasi bank atau menghitung uang tunai. Transfer antar akun harus seimbang antara transfer masuk dan transfer keluar. | L15: Dana di Bank Dana Klien harus diperlakukan sebagai dana terbatas, bukan kas bebas operasional. Isi kolom saldo fisik/rekening setelah memeriksa mutasi bank atau menghitung uang tunai. Transfer antar akun harus seimbang antara transfer masuk dan transfer keluar. | M15: Dana di Bank Dana Klien harus diperlakukan sebagai dana terbatas, bukan kas bebas operasional. Isi kolom saldo fisik/rekening setelah memeriksa mutasi bank atau menghitung uang tunai. Transfer antar akun harus seimbang antara transfer masuk dan transfer keluar. | N15: Dana di Bank Dana Klien harus diperlakukan sebagai dana terbatas, bukan kas bebas operasional. Isi kolom saldo fisik/rekening setelah memeriksa mutasi bank atau menghitung uang tunai. Transfer antar akun harus seimbang antara transfer masuk dan transfer keluar. | O15: Dana di Bank Dana Klien harus diperlakukan sebagai dana terbatas, bukan kas bebas operasional. Isi kolom saldo fisik/rekening setelah memeriksa mutasi bank atau menghitung uang tunai. Transfer antar akun harus seimbang antara transfer masuk dan transfer keluar. | P15: Dana di Bank Dana Klien harus diperlakukan sebagai dana terbatas, bukan kas bebas operasional. Isi kolom saldo fisik/rekening setelah memeriksa mutasi bank atau menghitung uang tunai. Transfer antar akun harus seimbang antara transfer masuk dan transfer keluar. | Q15: Dana di Bank Dana Klien harus diperlakukan sebagai dana terbatas, bukan kas bebas operasional. Isi kolom saldo fisik/rekening setelah memeriksa mutasi bank atau menghitung uang tunai. Transfer antar akun harus seimbang antara transfer masuk dan transfer keluar.
A16: Dana di Bank Dana Klien harus diperlakukan sebagai dana terbatas, bukan kas bebas operasional. Isi kolom saldo fisik/rekening setelah memeriksa mutasi bank atau menghitung uang tunai. Transfer antar akun harus seimbang antara transfer masuk dan transfer keluar. | B16: Dana di Bank Dana Klien harus diperlakukan sebagai dana terbatas, bukan kas bebas operasional. Isi kolom saldo fisik/rekening setelah memeriksa mutasi bank atau menghitung uang tunai. Transfer antar akun harus seimbang antara transfer masuk dan transfer keluar. | C16: Dana di Bank Dana Klien harus diperlakukan sebagai dana terbatas, bukan kas bebas operasional. Isi kolom saldo fisik/rekening setelah memeriksa mutasi bank atau menghitung uang tunai. Transfer antar akun harus seimbang antara transfer masuk dan transfer keluar. | D16: Dana di Bank Dana Klien harus diperlakukan sebagai dana terbatas, bukan kas bebas operasional. Isi kolom saldo fisik/rekening setelah memeriksa mutasi bank atau menghitung uang tunai. Transfer antar akun harus seimbang antara transfer masuk dan transfer keluar. | E16: Dana di Bank Dana Klien harus diperlakukan sebagai dana terbatas, bukan kas bebas operasional. Isi kolom saldo fisik/rekening setelah memeriksa mutasi bank atau menghitung uang tunai. Transfer antar akun harus seimbang antara transfer masuk dan transfer keluar. | F16: Dana di Bank Dana Klien harus diperlakukan sebagai dana terbatas, bukan kas bebas operasional. Isi kolom saldo fisik/rekening setelah memeriksa mutasi bank atau menghitung uang tunai. Transfer antar akun harus seimbang antara transfer masuk dan transfer keluar. | G16: Dana di Bank Dana Klien harus diperlakukan sebagai dana terbatas, bukan kas bebas operasional. Isi kolom saldo fisik/rekening setelah memeriksa mutasi bank atau menghitung uang tunai. Transfer antar akun harus seimbang antara transfer masuk dan transfer keluar. | H16: Dana di Bank Dana Klien harus diperlakukan sebagai dana terbatas, bukan kas bebas operasional. Isi kolom saldo fisik/rekening setelah memeriksa mutasi bank atau menghitung uang tunai. Transfer antar akun harus seimbang antara transfer masuk dan transfer keluar. | I16: Dana di Bank Dana Klien harus diperlakukan sebagai dana terbatas, bukan kas bebas operasional. Isi kolom saldo fisik/rekening setelah memeriksa mutasi bank atau menghitung uang tunai. Transfer antar akun harus seimbang antara transfer masuk dan transfer keluar. | J16: Dana di Bank Dana Klien harus diperlakukan sebagai dana terbatas, bukan kas bebas operasional. Isi kolom saldo fisik/rekening setelah memeriksa mutasi bank atau menghitung uang tunai. Transfer antar akun harus seimbang antara transfer masuk dan transfer keluar. | K16: Dana di Bank Dana Klien harus diperlakukan sebagai dana terbatas, bukan kas bebas operasional. Isi kolom saldo fisik/rekening setelah memeriksa mutasi bank atau menghitung uang tunai. Transfer antar akun harus seimbang antara transfer masuk dan transfer keluar. | L16: Dana di Bank Dana Klien harus diperlakukan sebagai dana terbatas, bukan kas bebas operasional. Isi kolom saldo fisik/rekening setelah memeriksa mutasi bank atau menghitung uang tunai. Transfer antar akun harus seimbang antara transfer masuk dan transfer keluar. | M16: Dana di Bank Dana Klien harus diperlakukan sebagai dana terbatas, bukan kas bebas operasional. Isi kolom saldo fisik/rekening setelah memeriksa mutasi bank atau menghitung uang tunai. Transfer antar akun harus seimbang antara transfer masuk dan transfer keluar. | N16: Dana di Bank Dana Klien harus diperlakukan sebagai dana terbatas, bukan kas bebas operasional. Isi kolom saldo fisik/rekening setelah memeriksa mutasi bank atau menghitung uang tunai. Transfer antar akun harus seimbang antara transfer masuk dan transfer keluar. | O16: Dana di Bank Dana Klien harus diperlakukan sebagai dana terbatas, bukan kas bebas operasional. Isi kolom saldo fisik/rekening setelah memeriksa mutasi bank atau menghitung uang tunai. Transfer antar akun harus seimbang antara transfer masuk dan transfer keluar. | P16: Dana di Bank Dana Klien harus diperlakukan sebagai dana terbatas, bukan kas bebas operasional. Isi kolom saldo fisik/rekening setelah memeriksa mutasi bank atau menghitung uang tunai. Transfer antar akun harus seimbang antara transfer masuk dan transfer keluar. | Q16: Dana di Bank Dana Klien harus diperlakukan sebagai dana terbatas, bukan kas bebas operasional. Isi kolom saldo fisik/rekening setelah memeriksa mutasi bank atau menghitung uang tunai. Transfer antar akun harus seimbang antara transfer masuk dan transfer keluar.

Sheet GAJI
A1: R | P | K PENGGAJIAN & HONOR TENAGA KERJA | B1: R | P | K PENGGAJIAN & HONOR TENAGA KERJA | C1: R | P | K PENGGAJIAN & HONOR TENAGA KERJA | D1: R | P | K PENGGAJIAN & HONOR TENAGA KERJA | E1: R | P | K PENGGAJIAN & HONOR TENAGA KERJA | F1: R | P | K PENGGAJIAN & HONOR TENAGA KERJA | G1: R | P | K PENGGAJIAN & HONOR TENAGA KERJA | H1: R | P | K PENGGAJIAN & HONOR TENAGA KERJA | I1: R | P | K PENGGAJIAN & HONOR TENAGA KERJA | J1: R | P | K PENGGAJIAN & HONOR TENAGA KERJA | K1: R | P | K PENGGAJIAN & HONOR TENAGA KERJA | L1: R | P | K PENGGAJIAN & HONOR TENAGA KERJA | M1: R | P | K PENGGAJIAN & HONOR TENAGA KERJA | N1: R | P | K PENGGAJIAN & HONOR TENAGA KERJA | O1: R | P | K PENGGAJIAN & HONOR TENAGA KERJA | P1: R | P | K PENGGAJIAN & HONOR TENAGA KERJA | Q1: R | P | K PENGGAJIAN & HONOR TENAGA KERJA | R1: R | P | K PENGGAJIAN & HONOR TENAGA KERJA | S1: R | P | K PENGGAJIAN & HONOR TENAGA KERJA | T1: R | P | K PENGGAJIAN & HONOR TENAGA KERJA | U1: R | P | K PENGGAJIAN & HONOR TENAGA KERJA | V1: R | P | K PENGGAJIAN & HONOR TENAGA KERJA | W1: R | P | K PENGGAJIAN & HONOR TENAGA KERJA
A2: R | P | K PENGGAJIAN & HONOR TENAGA KERJA | B2: R | P | K PENGGAJIAN & HONOR TENAGA KERJA | C2: R | P | K PENGGAJIAN & HONOR TENAGA KERJA | D2: R | P | K PENGGAJIAN & HONOR TENAGA KERJA | E2: R | P | K PENGGAJIAN & HONOR TENAGA KERJA | F2: R | P | K PENGGAJIAN & HONOR TENAGA KERJA | G2: R | P | K PENGGAJIAN & HONOR TENAGA KERJA | H2: R | P | K PENGGAJIAN & HONOR TENAGA KERJA | I2: R | P | K PENGGAJIAN & HONOR TENAGA KERJA | J2: R | P | K PENGGAJIAN & HONOR TENAGA KERJA | K2: R | P | K PENGGAJIAN & HONOR TENAGA KERJA | L2: R | P | K PENGGAJIAN & HONOR TENAGA KERJA | M2: R | P | K PENGGAJIAN & HONOR TENAGA KERJA | N2: R | P | K PENGGAJIAN & HONOR TENAGA KERJA | O2: R | P | K PENGGAJIAN & HONOR TENAGA KERJA | P2: R | P | K PENGGAJIAN & HONOR TENAGA KERJA | Q2: R | P | K PENGGAJIAN & HONOR TENAGA KERJA | R2: R | P | K PENGGAJIAN & HONOR TENAGA KERJA | S2: R | P | K PENGGAJIAN & HONOR TENAGA KERJA | T2: R | P | K PENGGAJIAN & HONOR TENAGA KERJA | U2: R | P | K PENGGAJIAN & HONOR TENAGA KERJA | V2: R | P | K PENGGAJIAN & HONOR TENAGA KERJA | W2: R | P | K PENGGAJIAN & HONOR TENAGA KERJA
A3: Payroll, slip gaji, dan biaya kantor dihitung otomatis. Persetujuan, nama penyetuju, dan tanggal otorisasi diisi manual sebelum pembayaran. | B3: Isi Periode Gaji dengan tanggal hari pertama bulan (contoh: 01/07/2026). ID payroll, bruto, gaji bersih, dan beban kantor dihitung otomatis. | C3: Isi Periode Gaji dengan tanggal hari pertama bulan (contoh: 01/07/2026). ID payroll, bruto, gaji bersih, dan beban kantor dihitung otomatis. | D3: Isi Periode Gaji dengan tanggal hari pertama bulan (contoh: 01/07/2026). ID payroll, bruto, gaji bersih, dan beban kantor dihitung otomatis. | E3: Isi Periode Gaji dengan tanggal hari pertama bulan (contoh: 01/07/2026). ID payroll, bruto, gaji bersih, dan beban kantor dihitung otomatis. | F3: Isi Periode Gaji dengan tanggal hari pertama bulan (contoh: 01/07/2026). ID payroll, bruto, gaji bersih, dan beban kantor dihitung otomatis. | G3: Isi Periode Gaji dengan tanggal hari pertama bulan (contoh: 01/07/2026). ID payroll, bruto, gaji bersih, dan beban kantor dihitung otomatis. | H3: Isi Periode Gaji dengan tanggal hari pertama bulan (contoh: 01/07/2026). ID payroll, bruto, gaji bersih, dan beban kantor dihitung otomatis. | I3: Isi Periode Gaji dengan tanggal hari pertama bulan (contoh: 01/07/2026). ID payroll, bruto, gaji bersih, dan beban kantor dihitung otomatis. | J3: Isi Periode Gaji dengan tanggal hari pertama bulan (contoh: 01/07/2026). ID payroll, bruto, gaji bersih, dan beban kantor dihitung otomatis. | K3: Isi Periode Gaji dengan tanggal hari pertama bulan (contoh: 01/07/2026). ID payroll, bruto, gaji bersih, dan beban kantor dihitung otomatis. | L3: Isi Periode Gaji dengan tanggal hari pertama bulan (contoh: 01/07/2026). ID payroll, bruto, gaji bersih, dan beban kantor dihitung otomatis. | M3: Isi Periode Gaji dengan tanggal hari pertama bulan (contoh: 01/07/2026). ID payroll, bruto, gaji bersih, dan beban kantor dihitung otomatis. | N3: Isi Periode Gaji dengan tanggal hari pertama bulan (contoh: 01/07/2026). ID payroll, bruto, gaji bersih, dan beban kantor dihitung otomatis. | O3: Isi Periode Gaji dengan tanggal hari pertama bulan (contoh: 01/07/2026). ID payroll, bruto, gaji bersih, dan beban kantor dihitung otomatis. | P3: Isi Periode Gaji dengan tanggal hari pertama bulan (contoh: 01/07/2026). ID payroll, bruto, gaji bersih, dan beban kantor dihitung otomatis. | Q3: Isi Periode Gaji dengan tanggal hari pertama bulan (contoh: 01/07/2026). ID payroll, bruto, gaji bersih, dan beban kantor dihitung otomatis. | R3: Isi Periode Gaji dengan tanggal hari pertama bulan (contoh: 01/07/2026). ID payroll, bruto, gaji bersih, dan beban kantor dihitung otomatis. | S3: Isi Periode Gaji dengan tanggal hari pertama bulan (contoh: 01/07/2026). ID payroll, bruto, gaji bersih, dan beban kantor dihitung otomatis. | T3: Isi Periode Gaji dengan tanggal hari pertama bulan (contoh: 01/07/2026). ID payroll, bruto, gaji bersih, dan beban kantor dihitung otomatis. | U3: Isi Periode Gaji dengan tanggal hari pertama bulan (contoh: 01/07/2026). ID payroll, bruto, gaji bersih, dan beban kantor dihitung otomatis. | V3: Isi Periode Gaji dengan tanggal hari pertama bulan (contoh: 01/07/2026). ID payroll, bruto, gaji bersih, dan beban kantor dihitung otomatis. | W3: Isi Periode Gaji dengan tanggal hari pertama bulan (contoh: 01/07/2026). ID payroll, bruto, gaji bersih, dan beban kantor dihitung otomatis.
A4: ID Payroll | B4: Periode Gaji | C4: Nama Pegawai | D4: Jabatan | E4: Jenis Pegawai | F4: Gaji Pokok | G4: Tunjangan Tetap | H4: Transport/Makan | I4: Lembur | J4: Bonus/Insentif | K4: Penghasilan Bruto | L4: PPh 21 Dipotong | M4: BPJS Bagian Pegawai | N4: Potongan Lain | O4: BPJS Bagian Kantor | P4: Gaji Bersih Dibayar | Q4: Total Beban Kantor | R4: Status Pembayaran | S4: Tanggal Bayar | T4: Akun Pembayaran | U4: Bukti Pembayaran | V4: Disetujui Oleh (Manual) | W4: Catatan | X4: Kode Perkara (Opsional) | Y4: Nama Klien / Perkara | Z4: Status Validasi | AA4: Status Persetujuan (Manual) | AB4: Tanggal Persetujuan | AC4: Catatan Persetujuan | AD4: Status Otorisasi
A5: =IF(B5="","",IFERROR("PAY-"&TEXT(B5,"yyyymm")&"-"&TEXT(ROW()-4,"000"),"PERIODE HARUS TANGGAL")) -> PAY-202607-001 | B5: 46204 | C5: Bianca Lianda Desfani | D5: Paralegal | E5: Magang | F5: 500000 | G5: 0 | H5: 0 | J5: 0 | K5: =IF(B5="","",SUM(F5:J5)) -> 500000 | L5: 0 | M5: 0 | N5: 0 | O5: 0 | P5: =IF(B5="","",MAX(K5-SUM(L5:N5),0)) -> 500000 | Q5: =IF(B5="","",K5+O5) -> 500000 | R5: Dibayar | S5: 46232 | T5: Kas Fajar | V5: Fajar Roni | W5: Mengguankan Fee Fajar | X5: 001/2026 | Y5: =IF(X5="","",IFERROR(INDEX(PERKARA!$B$5:$B$104,MATCH(X5,PERKARA!$A$5:$A$104,0)),"ID TIDAK TERDAFTAR")) -> PT KKG | Z5: =IF(B5="","",IF(A5="PERIODE HARUS TANGGAL","PERIODE TIDAK VALID",IF(COUNTIF($A$5:$A$124,A5)>1,"ID PAYROLL DUPLIKAT",IF(AND(X5<>"",Y5="ID TIDAK TERDAFTAR"),"PERKARA TIDAK VALID",IF(AND(R5="Dibayar",T5=""),"AKUN PEMBAYARAN BELUM DIISI",IF(AND(R5="Dibayar",S5=""),"TANGGAL PEMBAYARAN BELUM DIISI",IF(AND(R5="Dibayar",AD5<>"LENGKAP"),"DIBAYAR TANPA OTORISASI","OK"))))))) -> OK | AA5: Disetujui | AB5: 46232 | AD5: =IF(B5="","",IF(AA5="Ditolak","DITOLAK",IF(AND(AA5="Disetujui",V5<>""),"LENGKAP",IF(AA5="Disetujui","NAMA PENYETUJU BELUM DIISI","MENUNGGU PERSETUJUAN MANUAL")))) -> LENGKAP
A6: =IF(B6="","",IFERROR("PAY-"&TEXT(B6,"yyyymm")&"-"&TEXT(ROW()-4,"000"),"PERIODE HARUS TANGGAL")) -> PAY-202607-002 | B6: 46204 | C6: Dafina Putri Felisha | D6: Paralegal | E6: Magang | F6: 500000 | G6: 0 | H6: 0 | J6: 0 | K6: =IF(B6="","",SUM(F6:J6)) -> 500000 | L6: 0 | M6: 0 | N6: 0 | O6: 0 | P6: =IF(B6="","",MAX(K6-SUM(L6:N6),0)) -> 500000 | Q6: =IF(B6="","",K6+O6) -> 500000 | R6: Dibayar | S6: 46232 | T6: Kas Fajar | V6: Fajar Roni | W6: Mengguankan Fee Fajar | X6: 001/2026 | Y6: =IF(X6="","",IFERROR(INDEX(PERKARA!$B$5:$B$104,MATCH(X6,PERKARA!$A$5:$A$104,0)),"ID TIDAK TERDAFTAR")) -> PT KKG | Z6: =IF(B6="","",IF(A6="PERIODE HARUS TANGGAL","PERIODE TIDAK VALID",IF(COUNTIF($A$5:$A$124,A6)>1,"ID PAYROLL DUPLIKAT",IF(AND(X6<>"",Y6="ID TIDAK TERDAFTAR"),"PERKARA TIDAK VALID",IF(AND(R6="Dibayar",T6=""),"AKUN PEMBAYARAN BELUM DIISI",IF(AND(R6="Dibayar",S6=""),"TANGGAL PEMBAYARAN BELUM DIISI",IF(AND(R6="Dibayar",AD6<>"LENGKAP"),"DIBAYAR TANPA OTORISASI","OK"))))))) -> OK | AA6: Disetujui | AB6: 46232 | AD6: =IF(B6="","",IF(AA6="Ditolak","DITOLAK",IF(AND(AA6="Disetujui",V6<>""),"LENGKAP",IF(AA6="Disetujui","NAMA PENYETUJU BELUM DIISI","MENUNGGU PERSETUJUAN MANUAL")))) -> LENGKAP
A7: =IF(B7="","",IFERROR("PAY-"&TEXT(B7,"yyyymm")&"-"&TEXT(ROW()-4,"000"),"PERIODE HARUS TANGGAL")) -> PAY-202608-003 | B7: 46235 | C7: Bianca Lianda Desfani | D7: Paralegal | E7: Magang | F7: 1500000 | G7: 0 | H7: 0 | J7: 0 | K7: =IF(B7="","",SUM(F7:J7)) -> 1500000 | L7: 0 | M7: 0 | N7: 0 | O7: 0 | P7: =IF(B7="","",MAX(K7-SUM(L7:N7),0)) -> 1500000 | Q7: =IF(B7="","",K7+O7) -> 1500000 | R7: Belum Dibayar | T7: Kas Kantor | V7: Fajar Roni | X7: 001/2026 | Y7: =IF(X7="","",IFERROR(INDEX(PERKARA!$B$5:$B$104,MATCH(X7,PERKARA!$A$5:$A$104,0)),"ID TIDAK TERDAFTAR")) -> PT KKG | Z7: =IF(B7="","",IF(A7="PERIODE HARUS TANGGAL","PERIODE TIDAK VALID",IF(COUNTIF($A$5:$A$124,A7)>1,"ID PAYROLL DUPLIKAT",IF(AND(X7<>"",Y7="ID TIDAK TERDAFTAR"),"PERKARA TIDAK VALID",IF(AND(R7="Dibayar",T7=""),"AKUN PEMBAYARAN BELUM DIISI",IF(AND(R7="Dibayar",S7=""),"TANGGAL PEMBAYARAN BELUM DIISI",IF(AND(R7="Dibayar",AD7<>"LENGKAP"),"DIBAYAR TANPA OTORISASI","OK"))))))) -> OK | AA7: Disetujui | AB7: 46227 | AD7: =IF(B7="","",IF(AA7="Ditolak","DITOLAK",IF(AND(AA7="Disetujui",V7<>""),"LENGKAP",IF(AA7="Disetujui","NAMA PENYETUJU BELUM DIISI","MENUNGGU PERSETUJUAN MANUAL")))) -> LENGKAP
A8: =IF(B8="","",IFERROR("PAY-"&TEXT(B8,"yyyymm")&"-"&TEXT(ROW()-4,"000"),"PERIODE HARUS TANGGAL")) -> PAY-202608-004 | B8: 46236 | C8: Dafina Putri Felisha | D8: Paralegal | E8: Magang | F8: 1500000 | G8: 0 | H8: 0 | J8: 0 | K8: =IF(B8="","",SUM(F8:J8)) -> 1500000 | L8: 0 | M8: 0 | N8: 0 | O8: 0 | P8: =IF(B8="","",MAX(K8-SUM(L8:N8),0)) -> 1500000 | Q8: =IF(B8="","",K8+O8) -> 1500000 | R8: Belum Dibayar | T8: Kas Kantor | V8: Fajar Roni | X8: 001/2026 | Y8: =IF(X8="","",IFERROR(INDEX(PERKARA!$B$5:$B$104,MATCH(X8,PERKARA!$A$5:$A$104,0)),"ID TIDAK TERDAFTAR")) -> PT KKG | Z8: =IF(B8="","",IF(A8="PERIODE HARUS TANGGAL","PERIODE TIDAK VALID",IF(COUNTIF($A$5:$A$124,A8)>1,"ID PAYROLL DUPLIKAT",IF(AND(X8<>"",Y8="ID TIDAK TERDAFTAR"),"PERKARA TIDAK VALID",IF(AND(R8="Dibayar",T8=""),"AKUN PEMBAYARAN BELUM DIISI",IF(AND(R8="Dibayar",S8=""),"TANGGAL PEMBAYARAN BELUM DIISI",IF(AND(R8="Dibayar",AD8<>"LENGKAP"),"DIBAYAR TANPA OTORISASI","OK"))))))) -> OK | AA8: Disetujui | AB8: 46227 | AD8: =IF(B8="","",IF(AA8="Ditolak","DITOLAK",IF(AND(AA8="Disetujui",V8<>""),"LENGKAP",IF(AA8="Disetujui","NAMA PENYETUJU BELUM DIISI","MENUNGGU PERSETUJUAN MANUAL")))) -> LENGKAP
A9: =IF(B9="","",IFERROR("PAY-"&TEXT(B9,"yyyymm")&"-"&TEXT(ROW()-4,"000"),"PERIODE HARUS TANGGAL")) | K9: =IF(B9="","",SUM(F9:J9)) | P9: =IF(B9="","",MAX(K9-SUM(L9:N9),0)) | Q9: =IF(B9="","",K9+O9) | Y9: =IF(X9="","",IFERROR(INDEX(PERKARA!$B$5:$B$104,MATCH(X9,PERKARA!$A$5:$A$104,0)),"ID TIDAK TERDAFTAR")) | Z9: =IF(B9="","",IF(A9="PERIODE HARUS TANGGAL","PERIODE TIDAK VALID",IF(COUNTIF($A$5:$A$124,A9)>1,"ID PAYROLL DUPLIKAT",IF(AND(X9<>"",Y9="ID TIDAK TERDAFTAR"),"PERKARA TIDAK VALID",IF(AND(R9="Dibayar",T9=""),"AKUN PEMBAYARAN BELUM DIISI",IF(AND(R9="Dibayar",S9=""),"TANGGAL PEMBAYARAN BELUM DIISI",IF(AND(R9="Dibayar",AD9<>"LENGKAP"),"DIBAYAR TANPA OTORISASI","OK"))))))) | AD9: =IF(B9="","",IF(AA9="Ditolak","DITOLAK",IF(AND(AA9="Disetujui",V9<>""),"LENGKAP",IF(AA9="Disetujui","NAMA PENYETUJU BELUM DIISI","MENUNGGU PERSETUJUAN MANUAL"))))
A10: =IF(B10="","",IFERROR("PAY-"&TEXT(B10,"yyyymm")&"-"&TEXT(ROW()-4,"000"),"PERIODE HARUS TANGGAL")) | K10: =IF(B10="","",SUM(F10:J10)) | P10: =IF(B10="","",MAX(K10-SUM(L10:N10),0)) | Q10: =IF(B10="","",K10+O10) | Y10: =IF(X10="","",IFERROR(INDEX(PERKARA!$B$5:$B$104,MATCH(X10,PERKARA!$A$5:$A$104,0)),"ID TIDAK TERDAFTAR")) | Z10: =IF(B10="","",IF(A10="PERIODE HARUS TANGGAL","PERIODE TIDAK VALID",IF(COUNTIF($A$5:$A$124,A10)>1,"ID PAYROLL DUPLIKAT",IF(AND(X10<>"",Y10="ID TIDAK TERDAFTAR"),"PERKARA TIDAK VALID",IF(AND(R10="Dibayar",T10=""),"AKUN PEMBAYARAN BELUM DIISI",IF(AND(R10="Dibayar",S10=""),"TANGGAL PEMBAYARAN BELUM DIISI",IF(AND(R10="Dibayar",AD10<>"LENGKAP"),"DIBAYAR TANPA OTORISASI","OK"))))))) | AD10: =IF(B10="","",IF(AA10="Ditolak","DITOLAK",IF(AND(AA10="Disetujui",V10<>""),"LENGKAP",IF(AA10="Disetujui","NAMA PENYETUJU BELUM DIISI","MENUNGGU PERSETUJUAN MANUAL"))))
A11: =IF(B11="","",IFERROR("PAY-"&TEXT(B11,"yyyymm")&"-"&TEXT(ROW()-4,"000"),"PERIODE HARUS TANGGAL")) | K11: =IF(B11="","",SUM(F11:J11)) | P11: =IF(B11="","",MAX(K11-SUM(L11:N11),0)) | Q11: =IF(B11="","",K11+O11) | Y11: =IF(X11="","",IFERROR(INDEX(PERKARA!$B$5:$B$104,MATCH(X11,PERKARA!$A$5:$A$104,0)),"ID TIDAK TERDAFTAR")) | Z11: =IF(B11="","",IF(A11="PERIODE HARUS TANGGAL","PERIODE TIDAK VALID",IF(COUNTIF($A$5:$A$124,A11)>1,"ID PAYROLL DUPLIKAT",IF(AND(X11<>"",Y11="ID TIDAK TERDAFTAR"),"PERKARA TIDAK VALID",IF(AND(R11="Dibayar",T11=""),"AKUN PEMBAYARAN BELUM DIISI",IF(AND(R11="Dibayar",S11=""),"TANGGAL PEMBAYARAN BELUM DIISI",IF(AND(R11="Dibayar",AD11<>"LENGKAP"),"DIBAYAR TANPA OTORISASI","OK"))))))) | AD11: =IF(B11="","",IF(AA11="Ditolak","DITOLAK",IF(AND(AA11="Disetujui",V11<>""),"LENGKAP",IF(AA11="Disetujui","NAMA PENYETUJU BELUM DIISI","MENUNGGU PERSETUJUAN MANUAL"))))
A12: =IF(B12="","",IFERROR("PAY-"&TEXT(B12,"yyyymm")&"-"&TEXT(ROW()-4,"000"),"PERIODE HARUS TANGGAL")) | K12: =IF(B12="","",SUM(F12:J12)) | P12: =IF(B12="","",MAX(K12-SUM(L12:N12),0)) | Q12: =IF(B12="","",K12+O12) | Y12: =IF(X12="","",IFERROR(INDEX(PERKARA!$B$5:$B$104,MATCH(X12,PERKARA!$A$5:$A$104,0)),"ID TIDAK TERDAFTAR")) | Z12: =IF(B12="","",IF(A12="PERIODE HARUS TANGGAL","PERIODE TIDAK VALID",IF(COUNTIF($A$5:$A$124,A12)>1,"ID PAYROLL DUPLIKAT",IF(AND(X12<>"",Y12="ID TIDAK TERDAFTAR"),"PERKARA TIDAK VALID",IF(AND(R12="Dibayar",T12=""),"AKUN PEMBAYARAN BELUM DIISI",IF(AND(R12="Dibayar",S12=""),"TANGGAL PEMBAYARAN BELUM DIISI",IF(AND(R12="Dibayar",AD12<>"LENGKAP"),"DIBAYAR TANPA OTORISASI","OK"))))))) | AD12: =IF(B12="","",IF(AA12="Ditolak","DITOLAK",IF(AND(AA12="Disetujui",V12<>""),"LENGKAP",IF(AA12="Disetujui","NAMA PENYETUJU BELUM DIISI","MENUNGGU PERSETUJUAN MANUAL"))))
A13: =IF(B13="","",IFERROR("PAY-"&TEXT(B13,"yyyymm")&"-"&TEXT(ROW()-4,"000"),"PERIODE HARUS TANGGAL")) | K13: =IF(B13="","",SUM(F13:J13)) | P13: =IF(B13="","",MAX(K13-SUM(L13:N13),0)) | Q13: =IF(B13="","",K13+O13) | Y13: =IF(X13="","",IFERROR(INDEX(PERKARA!$B$5:$B$104,MATCH(X13,PERKARA!$A$5:$A$104,0)),"ID TIDAK TERDAFTAR")) | Z13: =IF(B13="","",IF(A13="PERIODE HARUS TANGGAL","PERIODE TIDAK VALID",IF(COUNTIF($A$5:$A$124,A13)>1,"ID PAYROLL DUPLIKAT",IF(AND(X13<>"",Y13="ID TIDAK TERDAFTAR"),"PERKARA TIDAK VALID",IF(AND(R13="Dibayar",T13=""),"AKUN PEMBAYARAN BELUM DIISI",IF(AND(R13="Dibayar",S13=""),"TANGGAL PEMBAYARAN BELUM DIISI",IF(AND(R13="Dibayar",AD13<>"LENGKAP"),"DIBAYAR TANPA OTORISASI","OK"))))))) | AD13: =IF(B13="","",IF(AA13="Ditolak","DITOLAK",IF(AND(AA13="Disetujui",V13<>""),"LENGKAP",IF(AA13="Disetujui","NAMA PENYETUJU BELUM DIISI","MENUNGGU PERSETUJUAN MANUAL"))))
A14: =IF(B14="","",IFERROR("PAY-"&TEXT(B14,"yyyymm")&"-"&TEXT(ROW()-4,"000"),"PERIODE HARUS TANGGAL")) | K14: =IF(B14="","",SUM(F14:J14)) | P14: =IF(B14="","",MAX(K14-SUM(L14:N14),0)) | Q14: =IF(B14="","",K14+O14) | Y14: =IF(X14="","",IFERROR(INDEX(PERKARA!$B$5:$B$104,MATCH(X14,PERKARA!$A$5:$A$104,0)),"ID TIDAK TERDAFTAR")) | Z14: =IF(B14="","",IF(A14="PERIODE HARUS TANGGAL","PERIODE TIDAK VALID",IF(COUNTIF($A$5:$A$124,A14)>1,"ID PAYROLL DUPLIKAT",IF(AND(X14<>"",Y14="ID TIDAK TERDAFTAR"),"PERKARA TIDAK VALID",IF(AND(R14="Dibayar",T14=""),"AKUN PEMBAYARAN BELUM DIISI",IF(AND(R14="Dibayar",S14=""),"TANGGAL PEMBAYARAN BELUM DIISI",IF(AND(R14="Dibayar",AD14<>"LENGKAP"),"DIBAYAR TANPA OTORISASI","OK"))))))) | AD14: =IF(B14="","",IF(AA14="Ditolak","DITOLAK",IF(AND(AA14="Disetujui",V14<>""),"LENGKAP",IF(AA14="Disetujui","NAMA PENYETUJU BELUM DIISI","MENUNGGU PERSETUJUAN MANUAL"))))
A15: =IF(B15="","",IFERROR("PAY-"&TEXT(B15,"yyyymm")&"-"&TEXT(ROW()-4,"000"),"PERIODE HARUS TANGGAL")) | K15: =IF(B15="","",SUM(F15:J15)) | P15: =IF(B15="","",MAX(K15-SUM(L15:N15),0)) | Q15: =IF(B15="","",K15+O15) | Y15: =IF(X15="","",IFERROR(INDEX(PERKARA!$B$5:$B$104,MATCH(X15,PERKARA!$A$5:$A$104,0)),"ID TIDAK TERDAFTAR")) | Z15: =IF(B15="","",IF(A15="PERIODE HARUS TANGGAL","PERIODE TIDAK VALID",IF(COUNTIF($A$5:$A$124,A15)>1,"ID PAYROLL DUPLIKAT",IF(AND(X15<>"",Y15="ID TIDAK TERDAFTAR"),"PERKARA TIDAK VALID",IF(AND(R15="Dibayar",T15=""),"AKUN PEMBAYARAN BELUM DIISI",IF(AND(R15="Dibayar",S15=""),"TANGGAL PEMBAYARAN BELUM DIISI",IF(AND(R15="Dibayar",AD15<>"LENGKAP"),"DIBAYAR TANPA OTORISASI","OK"))))))) | AD15: =IF(B15="","",IF(AA15="Ditolak","DITOLAK",IF(AND(AA15="Disetujui",V15<>""),"LENGKAP",IF(AA15="Disetujui","NAMA PENYETUJU BELUM DIISI","MENUNGGU PERSETUJUAN MANUAL"))))
A16: =IF(B16="","",IFERROR("PAY-"&TEXT(B16,"yyyymm")&"-"&TEXT(ROW()-4,"000"),"PERIODE HARUS TANGGAL")) | K16: =IF(B16="","",SUM(F16:J16)) | P16: =IF(B16="","",MAX(K16-SUM(L16:N16),0)) | Q16: =IF(B16="","",K16+O16) | Y16: =IF(X16="","",IFERROR(INDEX(PERKARA!$B$5:$B$104,MATCH(X16,PERKARA!$A$5:$A$104,0)),"ID TIDAK TERDAFTAR")) | Z16: =IF(B16="","",IF(A16="PERIODE HARUS TANGGAL","PERIODE TIDAK VALID",IF(COUNTIF($A$5:$A$124,A16)>1,"ID PAYROLL DUPLIKAT",IF(AND(X16<>"",Y16="ID TIDAK TERDAFTAR"),"PERKARA TIDAK VALID",IF(AND(R16="Dibayar",T16=""),"AKUN PEMBAYARAN BELUM DIISI",IF(AND(R16="Dibayar",S16=""),"TANGGAL PEMBAYARAN BELUM DIISI",IF(AND(R16="Dibayar",AD16<>"LENGKAP"),"DIBAYAR TANPA OTORISASI","OK"))))))) | AD16: =IF(B16="","",IF(AA16="Ditolak","DITOLAK",IF(AND(AA16="Disetujui",V16<>""),"LENGKAP",IF(AA16="Disetujui","NAMA PENYETUJU BELUM DIISI","MENUNGGU PERSETUJUAN MANUAL"))))
A17: =IF(B17="","",IFERROR("PAY-"&TEXT(B17,"yyyymm")&"-"&TEXT(ROW()-4,"000"),"PERIODE HARUS TANGGAL")) | K17: =IF(B17="","",SUM(F17:J17)) | P17: =IF(B17="","",MAX(K17-SUM(L17:N17),0)) | Q17: =IF(B17="","",K17+O17) | Y17: =IF(X17="","",IFERROR(INDEX(PERKARA!$B$5:$B$104,MATCH(X17,PERKARA!$A$5:$A$104,0)),"ID TIDAK TERDAFTAR")) | Z17: =IF(B17="","",IF(A17="PERIODE HARUS TANGGAL","PERIODE TIDAK VALID",IF(COUNTIF($A$5:$A$124,A17)>1,"ID PAYROLL DUPLIKAT",IF(AND(X17<>"",Y17="ID TIDAK TERDAFTAR"),"PERKARA TIDAK VALID",IF(AND(R17="Dibayar",T17=""),"AKUN PEMBAYARAN BELUM DIISI",IF(AND(R17="Dibayar",S17=""),"TANGGAL PEMBAYARAN BELUM DIISI",IF(AND(R17="Dibayar",AD17<>"LENGKAP"),"DIBAYAR TANPA OTORISASI","OK"))))))) | AD17: =IF(B17="","",IF(AA17="Ditolak","DITOLAK",IF(AND(AA17="Disetujui",V17<>""),"LENGKAP",IF(AA17="Disetujui","NAMA PENYETUJU BELUM DIISI","MENUNGGU PERSETUJUAN MANUAL"))))
A18: =IF(B18="","",IFERROR("PAY-"&TEXT(B18,"yyyymm")&"-"&TEXT(ROW()-4,"000"),"PERIODE HARUS TANGGAL")) | K18: =IF(B18="","",SUM(F18:J18)) | P18: =IF(B18="","",MAX(K18-SUM(L18:N18),0)) | Q18: =IF(B18="","",K18+O18) | Y18: =IF(X18="","",IFERROR(INDEX(PERKARA!$B$5:$B$104,MATCH(X18,PERKARA!$A$5:$A$104,0)),"ID TIDAK TERDAFTAR")) | Z18: =IF(B18="","",IF(A18="PERIODE HARUS TANGGAL","PERIODE TIDAK VALID",IF(COUNTIF($A$5:$A$124,A18)>1,"ID PAYROLL DUPLIKAT",IF(AND(X18<>"",Y18="ID TIDAK TERDAFTAR"),"PERKARA TIDAK VALID",IF(AND(R18="Dibayar",T18=""),"AKUN PEMBAYARAN BELUM DIISI",IF(AND(R18="Dibayar",S18=""),"TANGGAL PEMBAYARAN BELUM DIISI",IF(AND(R18="Dibayar",AD18<>"LENGKAP"),"DIBAYAR TANPA OTORISASI","OK"))))))) | AD18: =IF(B18="","",IF(AA18="Ditolak","DITOLAK",IF(AND(AA18="Disetujui",V18<>""),"LENGKAP",IF(AA18="Disetujui","NAMA PENYETUJU BELUM DIISI","MENUNGGU PERSETUJUAN MANUAL"))))
A19: =IF(B19="","",IFERROR("PAY-"&TEXT(B19,"yyyymm")&"-"&TEXT(ROW()-4,"000"),"PERIODE HARUS TANGGAL")) | K19: =IF(B19="","",SUM(F19:J19)) | P19: =IF(B19="","",MAX(K19-SUM(L19:N19),0)) | Q19: =IF(B19="","",K19+O19) | Y19: =IF(X19="","",IFERROR(INDEX(PERKARA!$B$5:$B$104,MATCH(X19,PERKARA!$A$5:$A$104,0)),"ID TIDAK TERDAFTAR")) | Z19: =IF(B19="","",IF(A19="PERIODE HARUS TANGGAL","PERIODE TIDAK VALID",IF(COUNTIF($A$5:$A$124,A19)>1,"ID PAYROLL DUPLIKAT",IF(AND(X19<>"",Y19="ID TIDAK TERDAFTAR"),"PERKARA TIDAK VALID",IF(AND(R19="Dibayar",T19=""),"AKUN PEMBAYARAN BELUM DIISI",IF(AND(R19="Dibayar",S19=""),"TANGGAL PEMBAYARAN BELUM DIISI",IF(AND(R19="Dibayar",AD19<>"LENGKAP"),"DIBAYAR TANPA OTORISASI","OK"))))))) | AD19: =IF(B19="","",IF(AA19="Ditolak","DITOLAK",IF(AND(AA19="Disetujui",V19<>""),"LENGKAP",IF(AA19="Disetujui","NAMA PENYETUJU BELUM DIISI","MENUNGGU PERSETUJUAN MANUAL"))))
A20: =IF(B20="","",IFERROR("PAY-"&TEXT(B20,"yyyymm")&"-"&TEXT(ROW()-4,"000"),"PERIODE HARUS TANGGAL")) | K20: =IF(B20="","",SUM(F20:J20)) | P20: =IF(B20="","",MAX(K20-SUM(L20:N20),0)) | Q20: =IF(B20="","",K20+O20) | Y20: =IF(X20="","",IFERROR(INDEX(PERKARA!$B$5:$B$104,MATCH(X20,PERKARA!$A$5:$A$104,0)),"ID TIDAK TERDAFTAR")) | Z20: =IF(B20="","",IF(A20="PERIODE HARUS TANGGAL","PERIODE TIDAK VALID",IF(COUNTIF($A$5:$A$124,A20)>1,"ID PAYROLL DUPLIKAT",IF(AND(X20<>"",Y20="ID TIDAK TERDAFTAR"),"PERKARA TIDAK VALID",IF(AND(R20="Dibayar",T20=""),"AKUN PEMBAYARAN BELUM DIISI",IF(AND(R20="Dibayar",S20=""),"TANGGAL PEMBAYARAN BELUM DIISI",IF(AND(R20="Dibayar",AD20<>"LENGKAP"),"DIBAYAR TANPA OTORISASI","OK"))))))) | AD20: =IF(B20="","",IF(AA20="Ditolak","DITOLAK",IF(AND(AA20="Disetujui",V20<>""),"LENGKAP",IF(AA20="Disetujui","NAMA PENYETUJU BELUM DIISI","MENUNGGU PERSETUJUAN MANUAL"))))
